Workbook

Sheet 🏠 Hoje
A1: 🏗️ PAINEL DA OBRA - Consulado Geral da Itália
A2: ="Hoje: "&TEXT(TODAY(),"dd/mm/yyyy")&" - "&TEXT(TODAY(),"dddd") -> Hoje: 28/06/2026 - domingo
A4: 🚨 Atrasados | B4: ⏳ Em andamento | C4: 📅 A iniciar | D4: ✅ Concluídos | E4: 📋 Subitens total | F4: 💼 Subitens hoje
A5: =COUNTIF(Gestao!F8:F171,"Atrasado") -> 57 | B5: =COUNTIF(Gestao!F8:F171,"Em andamento") -> 32 | C5: =COUNTIF(Gestao!F8:F171,"A iniciar") -> 74 | D5: =COUNTIF(Gestao!$G$8:$G$500,"Finalizado") -> 0 | E5: =COUNTA(Detalhamento!A9:A329) -> 321 | F5: =SUMPRODUCT((Detalhamento!E9:E329<=TODAY())*(Detalhamento!F9:F329>=TODAY())*(Detalhamento!A9:A329<>"")) -> 0
A7: 🚨 SUBITENS ATRASADOS
A8: Item Principal | B8: Subitem | C8: Atividade | D8: Descrição | E8: Término | F8: Status
A9: =IFERROR(__xludf.DUMMYFUNCTION("IFERROR(QUERY(Detalhamento!A9:H2020,""select A,B,C,D,F,H where A is not null and H <> 'Concluído' and F < date '""&TEXT(TODAY(),""yyyy-mm-dd"")&""' order by F limit 50"",0),""Nenhum subitem atrasado"")"),"Nenhum subitem atrasado") -> Nenhum subitem atrasado
A62: 📅 PRÓXIMOS 15 DIAS
A63: Item Principal | B63: Subitem | C63: Atividade | D63: Descrição | E63: Início | F63: Status
A64: =IFERROR(__xludf.DUMMYFUNCTION("IFERROR(QUERY(Detalhamento!A9:H2020,""select A,B,C,D,E,H where A is not null and E >= date '""&TEXT(TODAY(),""yyyy-mm-dd"")&""' and E <= date '""&TEXT(TODAY()+15,""yyyy-mm-dd"")&""' order by E limit 50"",0),""Nada nos próximos 15 dias"")"),"Nada nos próximos 15 dias") -> Nada nos próximos 15 dias
A117: 💰 PAGAMENTOS A FAZER (próx. 7 dias)
A118: Tipo | B118: Beneficiário | C118: Descrição | D118: Valor | E118: Vencimento | F118: Status
A119: =IFERROR(__xludf.DUMMYFUNCTION("IFERROR(QUERY(Pagamentos!A7:V600,""select A,B,D,N,O,R where O >= date '""&TEXT(TODAY(),""yyyy-mm-dd"")&""' and O <= date '""&TEXT(TODAY()+7,""yyyy-mm-dd"")&""' and R <> 'Pago' order by O limit 30"",0),""Nenhum pagamento nos próximos 7 dias"")"),"Nenhum pagamento nos próximos 7 dias") -> Nenhum pagamento nos próximos 7 dias

Sheet 📊 Dashboard
A1: 📊 PAINEL DA OBRA — Consulado Geral da Itália
A2: Avanço · Prazos · Materiais — atualizado automático
A4: ATRASADOS | C4: EM ANDAMENTO | E4: A INICIAR | G4: CONCLUÍDOS | I4: SUBITENS | K4: % AVANÇO
A5: ='🏠 Hoje'!A5 -> 57 | C5: ='🏠 Hoje'!B5 -> 32 | E5: ='🏠 Hoje'!C5 -> 74 | G5: ='🏠 Hoje'!D5 -> 0 | I5: ='🏠 Hoje'!E5 -> 321 | K5: =IFERROR(AVERAGEIFS(Detalhamento!O8:O1000,Detalhamento!C8:C1000,"<>"),0) -> 0
A7: 📈 AVANÇO POR DISCIPLINA | E7: ⏰ PRÓXIMOS VENCIMENTOS | I7: 🧱 ESTOQUE ATUAL
A8: Disciplina | B8: Subitens | C8: % Avanço | D8: Volume | E8: Item | F8: Atividade | G8: Término | I8: Material | J8: Categoria | K8: Estoque
A9: Preliminares | B9: =COUNTIF(Detalhamento!$G$8:$G1000,A9) -> 4 | C9: =IFERROR(AVERAGEIF(Detalhamento!$G$8:$G1000,A9,Detalhamento!$O$8:$O1000),0) -> 0 | D9: =IF(B9=0,"",REPT("▮",MAX(1,ROUND(B9/MAX($B$9:$B$23)*12,0)))) -> ▮ | E9: {=IF($AA9:$AA24="","",$AA9:$AA24)} -> 1.1 | F9: {=IF($AB9:$AB24="","",IF(LEN($AB9:$AB24)>50,LEFT($AB9:$AB24,49)&"…",$AB9:$AB24))} -> Gerenciamento técnico de obra - 2 Engenheiros (40… | G9: {=IF($AC9:$AC24="","",$AC9:$AC24)} | I9: =IFERROR(__xludf.DUMMYFUNCTION("QUERY(Inventario!A6:H1000,""select A,B,F where F > 0 order by F desc limit 16"",0)"),"Areia media lavada") -> Areia media lavada | J9: =IFERROR(__xludf.DUMMYFUNCTION("""COMPUTED_VALUE"""),"Material") -> Material | K9: =IFERROR(__xludf.DUMMYFUNCTION("""COMPUTED_VALUE"""),318.0) -> 318 | AA9: =IFERROR(__xludf.DUMMYFUNCTION("ARRAY_CONSTRAIN(UNIQUE(FILTER({Detalhamento!A8:A1000,Detalhamento!C8:C1000,Detalhamento!F8:F1000},(Detalhamento!C8:C1000<>"""")*(Detalhamento!H8:H1000<>""Concluído""))),16,3)"),"1.1") -> 1.1 | AB9: =IFERROR(__xludf.DUMMYFUNCTION("""COMPUTED_VALUE"""),"Gerenciamento técnico de obra - 2 Engenheiros (40h/mês) , assistente tecnico (40h/mês) , mestre de obra (160h/mês)") -> Gerenciamento técnico de obra - 2 Engenheiros (40h/mês) , assistente tecnico (40h/mês) , mestre de obra (160h/mês)
A10: Civil | B10: =COUNTIF(Detalhamento!$G$8:$G1000,A10) -> 281 | C10: =IFERROR(AVERAGEIF(Detalhamento!$G$8:$G1000,A10,Detalhamento!$O$8:$O1000),0) -> 0 | D10: =IF(B10=0,"",REPT("▮",MAX(1,ROUND(B10/MAX($B$9:$B$23)*12,0)))) -> ▮▮▮▮▮▮▮▮▮▮▮▮ | E10: 1.3 | F10: Mobilização de canteiro e equipes e deslocamento | I10: =IFERROR(__xludf.DUMMYFUNCTION("""COMPUTED_VALUE"""),"Cimento CP-II 50kg") -> Cimento CP-II 50kg | J10: =IFERROR(__xludf.DUMMYFUNCTION("""COMPUTED_VALUE"""),"Material") -> Material | K10: =IFERROR(__xludf.DUMMYFUNCTION("""COMPUTED_VALUE"""),50.0) -> 50 | AA10: =IFERROR(__xludf.DUMMYFUNCTION("""COMPUTED_VALUE"""),"1.3") -> 1.3 | AB10: =IFERROR(__xludf.DUMMYFUNCTION("""COMPUTED_VALUE"""),"Mobilização de canteiro e equipes e deslocamento") -> Mobilização de canteiro e equipes e deslocamento
A11: Demolições | B11: =COUNTIF(Detalhamento!$G$8:$G1000,A11) -> 0 | C11: =IFERROR(AVERAGEIF(Detalhamento!$G$8:$G1000,A11,Detalhamento!$O$8:$O1000),0) -> 0 | D11: =IF(B11=0,"",REPT("▮",MAX(1,ROUND(B11/MAX($B$9:$B$23)*12,0)))) | E11: 1.4 | F11: Tapume de vedacao ou protecao, executado com chap… | AA11: =IFERROR(__xludf.DUMMYFUNCTION("""COMPUTED_VALUE"""),"1.4") -> 1.4 | AB11: =IFERROR(__xludf.DUMMYFUNCTION("""COMPUTED_VALUE"""),"Tapume de vedacao ou protecao, executado com chapas de compensado, tipo chapa resinada ou similar, com 6mm de espessura, exclusive pintura. Proteção chegada elvadores;.") -> Tapume de vedacao ou protecao, executado com chapas de compensado, tipo chapa resinada ou similar, com 6mm de espessura, exclusive pintura. Proteção chegada elvadores;.
A12: Revestimento | B12: =COUNTIF(Detalhamento!$G$8:$G1000,A12) -> 85 | C12: =IFERROR(AVERAGEIF(Detalhamento!$G$8:$G1000,A12,Detalhamento!$O$8:$O1000),0) -> 0 | D12: =IF(B12=0,"",REPT("▮",MAX(1,ROUND(B12/MAX($B$9:$B$23)*12,0)))) -> ▮▮▮▮ | E12: 1.5 | F12: Limpeza permanente de obra | AA12: =IFERROR(__xludf.DUMMYFUNCTION("""COMPUTED_VALUE"""),"1.5") -> 1.5 | AB12: =IFERROR(__xludf.DUMMYFUNCTION("""COMPUTED_VALUE"""),"Limpeza permanente de obra") -> Limpeza permanente de obra
A13: Pintura | B13: =COUNTIF(Detalhamento!$G$8:$G1000,A13) -> 65 | C13: =IFERROR(AVERAGEIF(Detalhamento!$G$8:$G1000,A13,Detalhamento!$O$8:$O1000),0) -> 0 | D13: =IF(B13=0,"",REPT("▮",MAX(1,ROUND(B13/MAX($B$9:$B$23)*12,0)))) -> ▮▮▮ | E13: 2.1 | F13: Demolicão manual de alvenaria de tijolos furados,… | AA13: =IFERROR(__xludf.DUMMYFUNCTION("""COMPUTED_VALUE"""),"2.1") -> 2.1 | AB13: =IFERROR(__xludf.DUMMYFUNCTION("""COMPUTED_VALUE"""),"Demolicão manual de alvenaria de tijolos furados, contrapiso de 5 cm no deposito 5, inclusive empilhamento dentro do canteiro de servico.") -> Demolicão manual de alvenaria de tijolos furados, contrapiso de 5 cm no deposito 5, inclusive empilhamento dentro do canteiro de servico.
A14: Elétrica | B14: =COUNTIF(Detalhamento!$G$8:$G1000,A14) -> 0 | C14: =IFERROR(AVERAGEIF(Detalhamento!$G$8:$G1000,A14,Detalhamento!$O$8:$O1000),0) -> 0 | D14: =IF(B14=0,"",REPT("▮",MAX(1,ROUND(B14/MAX($B$9:$B$23)*12,0)))) | E14: 2.2 | F14: Demolição controlada e monitrada para rebaixament… | AA14: =IFERROR(__xludf.DUMMYFUNCTION("""COMPUTED_VALUE"""),"2.2") -> 2.2 | AB14: =IFERROR(__xludf.DUMMYFUNCTION("""COMPUTED_VALUE"""),"Demolição controlada e monitrada para rebaixamento da laje e abertura na laje superior e dos vãos de portas nos andares") -> Demolição controlada e monitrada para rebaixamento da laje e abertura na laje superior e dos vãos de portas nos andares
A15: Hidráulica | B15: =COUNTIF(Detalhamento!$G$8:$G1000,A15) -> 0 | C15: =IFERROR(AVERAGEIF(Detalhamento!$G$8:$G1000,A15,Detalhamento!$O$8:$O1000),0) -> 0 | D15: =IF(B15=0,"",REPT("▮",MAX(1,ROUND(B15/MAX($B$9:$B$23)*12,0)))) | E15: 2.3 | F15: Caçamba para entulho 4m³ | AA15: =IFERROR(__xludf.DUMMYFUNCTION("""COMPUTED_VALUE"""),"2.3") -> 2.3 | AB15: =IFERROR(__xludf.DUMMYFUNCTION("""COMPUTED_VALUE"""),"Caçamba para entulho 4m³") -> Caçamba para entulho 4m³
A16: Instalacoes | B16: =COUNTIF(Detalhamento!$G$8:$G1000,A16) -> 12 | C16: =IFERROR(AVERAGEIF(Detalhamento!$G$8:$G1000,A16,Detalhamento!$O$8:$O1000),0) -> 0 | D16: =IF(B16=0,"",REPT("▮",MAX(1,ROUND(B16/MAX($B$9:$B$23)*12,0)))) -> ▮ | E16: 2.4 | F16: Transporte de entulho e grades | AA16: =IFERROR(__xludf.DUMMYFUNCTION("""COMPUTED_VALUE"""),"2.4") -> 2.4 | AB16: =IFERROR(__xludf.DUMMYFUNCTION("""COMPUTED_VALUE"""),"Transporte de entulho e grades") -> Transporte de entulho e grades
A17: Esquadrias | B17: =COUNTIF(Detalhamento!$G$8:$G1000,A17) -> 28 | C17: =IFERROR(AVERAGEIF(Detalhamento!$G$8:$G1000,A17,Detalhamento!$O$8:$O1000),0) -> 0 | D17: =IF(B17=0,"",REPT("▮",MAX(1,ROUND(B17/MAX($B$9:$B$23)*12,0)))) -> ▮ | E17: 2.5 | F17: Caçamba para entulho 4m³ | AA17: =IFERROR(__xludf.DUMMYFUNCTION("""COMPUTED_VALUE"""),"2.5") -> 2.5 | AB17: =IFERROR(__xludf.DUMMYFUNCTION("""COMPUTED_VALUE"""),"Caçamba para entulho 4m³") -> Caçamba para entulho 4m³
A18: Serralheria | B18: =COUNTIF(Detalhamento!$G$8:$G1000,A18) -> 48 | C18: =IFERROR(AVERAGEIF(Detalhamento!$G$8:$G1000,A18,Detalhamento!$O$8:$O1000),0) -> 0 | D18: =IF(B18=0,"",REPT("▮",MAX(1,ROUND(B18/MAX($B$9:$B$23)*12,0)))) -> ▮▮ | E18: 2.6 | F18: Transporte de entulho | AA18: =IFERROR(__xludf.DUMMYFUNCTION("""COMPUTED_VALUE"""),"2.6") -> 2.6 | AB18: =IFERROR(__xludf.DUMMYFUNCTION("""COMPUTED_VALUE"""),"Transporte de entulho") -> Transporte de entulho
A19: Forro | B19: =COUNTIF(Detalhamento!$G$8:$G1000,A19) -> 38 | C19: =IFERROR(AVERAGEIF(Detalhamento!$G$8:$G1000,A19,Detalhamento!$O$8:$O1000),0) -> 0 | D19: =IF(B19=0,"",REPT("▮",MAX(1,ROUND(B19/MAX($B$9:$B$23)*12,0)))) -> ▮▮ | E19: 2.7 | F19: Montagem e desmontagem de andaime direcional estr… | AA19: =IFERROR(__xludf.DUMMYFUNCTION("""COMPUTED_VALUE"""),"2.7") -> 2.7 | AB19: =IFERROR(__xludf.DUMMYFUNCTION("""COMPUTED_VALUE"""),"Montagem e desmontagem de andaime direcional estrutural com chumbadores e plataforma") -> Montagem e desmontagem de andaime direcional estrutural com chumbadores e plataforma
A20: Climatizacao | B20: =COUNTIF(Detalhamento!$G$8:$G1000,A20) -> 23 | C20: =IFERROR(AVERAGEIF(Detalhamento!$G$8:$G1000,A20,Detalhamento!$O$8:$O1000),0) -> 0 | D20: =IF(B20=0,"",REPT("▮",MAX(1,ROUND(B20/MAX($B$9:$B$23)*12,0)))) -> ▮ | E20: 3.1 | F20: Construção do prolongamento da caixa do elevador | AA20: =IFERROR(__xludf.DUMMYFUNCTION("""COMPUTED_VALUE"""),"3.1") -> 3.1 | AB20: =IFERROR(__xludf.DUMMYFUNCTION("""COMPUTED_VALUE"""),"Construção do prolongamento da caixa do elevador") -> Construção do prolongamento da caixa do elevador
A21: Impermeabilizacao | B21: =COUNTIF(Detalhamento!$G$8:$G1000,A21) -> 16 | C21: =IFERROR(AVERAGEIF(Detalhamento!$G$8:$G1000,A21,Detalhamento!$O$8:$O1000),0) -> 0 | D21: =IF(B21=0,"",REPT("▮",MAX(1,ROUND(B21/MAX($B$9:$B$23)*12,0)))) -> ▮ | E21: 3.2 | F21: Construção da laje de cobertura da torre com Alça… | AA21: =IFERROR(__xludf.DUMMYFUNCTION("""COMPUTED_VALUE"""),"3.2") -> 3.2 | AB21: =IFERROR(__xludf.DUMMYFUNCTION("""COMPUTED_VALUE"""),"Construção da laje de cobertura da torre com Alça para içamento do pistão") -> Construção da laje de cobertura da torre com Alça para içamento do pistão
A22: Elevadores | B22: =COUNTIF(Detalhamento!$G$8:$G1000,A22) -> 31 | C22: =IFERROR(AVERAGEIF(Detalhamento!$G$8:$G1000,A22,Detalhamento!$O$8:$O1000),0) -> 0 | D22: =IF(B22=0,"",REPT("▮",MAX(1,ROUND(B22/MAX($B$9:$B$23)*12,0)))) -> ▮ | E22: 3.3 | F22: Cintas intermediárias em todos os andares | AA22: =IFERROR(__xludf.DUMMYFUNCTION("""COMPUTED_VALUE"""),"3.3") -> 3.3 | AB22: =IFERROR(__xludf.DUMMYFUNCTION("""COMPUTED_VALUE"""),"Cintas intermediárias em todos os andares") -> Cintas intermediárias em todos os andares
A23: Limpeza | B23: =COUNTIF(Detalhamento!$G$8:$G1000,A23) -> 6 | C23: =IFERROR(AVERAGEIF(Detalhamento!$G$8:$G1000,A23,Detalhamento!$O$8:$O1000),0) -> 0 | D23: =IF(B23=0,"",REPT("▮",MAX(1,ROUND(B23/MAX($B$9:$B$23)*12,0)))) -> ▮ | E23: 3.4 | F23: Fechamento das laterais e fundos em alvenaria no … | AA23: =IFERROR(__xludf.DUMMYFUNCTION("""COMPUTED_VALUE"""),"3.4") -> 3.4 | AB23: =IFERROR(__xludf.DUMMYFUNCTION("""COMPUTED_VALUE"""),"Fechamento das laterais e fundos em alvenaria no prolongamento da torre") -> Fechamento das laterais e fundos em alvenaria no prolongamento da torre
E24: 3.5 | F24: Rebocamento no prolongamento da torre | AA24: =IFERROR(__xludf.DUMMYFUNCTION("""COMPUTED_VALUE"""),"3.5") -> 3.5 | AB24: =IFERROR(__xludf.DUMMYFUNCTION("""COMPUTED_VALUE"""),"Rebocamento no prolongamento da torre") -> Rebocamento no prolongamento da torre
A26: 🔴 BLOQUEIOS (itens parados) | E26: 💰 MATERIAL / COMPRAS | I26: 🔗 COMPATIBILIZAÇÃO
A27: Motivo | B27: Qtd | E27: Indicador | F27: Valor | I27: Indicador | J27: Valor
A28: Falta pessoa | B28: =COUNTIF(Detalhamento!J8:J1000,"Não") -> 0 | E28: Total material (qtd x valor) | F28: =SUMPRODUCT(SC!H6:H205,SC!J6:J205) -> 14422.64 | I28: Itens de contrato | J28: =COUNTA(Compatibilizacao!A5:A1000) -> 996
A29: Falta documento | B29: =COUNTIF(Detalhamento!K8:K1000,"Não") -> 0 | E29: Lançamentos de compra | F29: =COUNTA(SC!D6:D205) -> 7 | I29: Com orçamento | J29: =COUNTIF(Compatibilizacao!F5:F1000,"*🟢*") -> 42
A30: Falta material | B30: =COUNTIF(Detalhamento!L8:L1000,"Não") -> 0 | E30: Itens em estoque (>0) | F30: =COUNTIF(Inventario!F6:F1000,">0") -> 2 | I30: SEM orçamento | J30: =COUNTIF(Compatibilizacao!F5:F1000,"*🔴*") -> 126
A31: Falta ferramenta | B31: =COUNTIF(Detalhamento!M8:M1000,"Não") -> 0 | I31: % cobertura | J31: =IFERROR(COUNTIF(Compatibilizacao!F5:F1000,"*🟢*")/COUNTA(Compatibilizacao!A5:A1000),0) -> 0.042168675
A32: Falta equipamento | B32: =COUNTIF(Detalhamento!N8:N1000,"Não") -> 0

Sheet AUX_ItensContrato
A1: NOVO
A2: 46023
A3: 46054
A4: 46082
A5: 46113
A6: 46143
A7: 46024
A8: 46055
A9: 46083
A10: 46114
A11: 46144
A12: 46175
A13: 46205
... A31: 46360
A32: 4.13
A33: 4.14
A34: 4.15
A35: 4.16
A36: 4.17
A37: 11
A38: 12
A39: 12
A40: 46034
A41: 13
A42: 14
A43: 46035
A44: 46027
A45: 46058
A46: 46086
A47: 46117
A48: 46147
... A55: 46361
A56: 5.13
A57: 5.14
A58: 5.15
A59: 5.16
A60: 5.17
A61: 5.18
A62: 5.19
A63: 5.20
A64: 5.21
A65: 5.22
A66: 5.23
A67: 5.24
... A92: 5.49
A93: 46028
A94: 46059
A95: 46087
A96: 46118
A97: 46148
A98: 46179
A99: 46209
A100: 46240
A101: 46271
A102: 46301
A103: 46332
A104: 46362
A105: 6.13
A106: 6.14
A107: 6.15
A108: 6.16
A109: 6.17
A110: 6.18
A111: 6.19
A112: 6.20
A113: 6.21
A114: 6.22
A115: 6.23
A116: 6.24
... A129: 6.37
A130: 46029
A131: 46060
A132: 46088
A133: 46119
A134: 46149
A135: 46180
A136: 46210
A137: 46241
A138: 46272
A139: 46302
A140: 46333
A141: 46363
... A166: 46042

Sheet Dashboard_OLD
B1: 📊 DASHBOARD DA OBRA
B2: ="Consulado Geral da Itália · atualizado em "&TEXT(TODAY(),"dd/mm/yyyy") -> Consulado Geral da Itália · atualizado em 28/06/2026
B4: % AVANÇO FÍSICO | D4: ETAPAS CONCLUÍDAS | F4: ITENS ATRASADOS | I4: ENTREGAS 30 DIAS | K4: PAGO / PREVISTO
B5: =IFERROR(COUNTIF(Detalhamento!$H$9:$H1000,"Concluído")/COUNTA(Detalhamento!$H$9:$H1000),0) -> 0.0066518847 | D5: =COUNTIF(Detalhamento!$H$9:$H1000,"Concluído")&" / "&COUNTA(Detalhamento!$H$9:$H1000) -> 6 / 902 | F5: =COUNTIF(Gestao!$F$4:$F1000,"Atrasado") -> 58 | I5: =COUNTIFS(Gestao!$E$4:$E1000,">="&TODAY(),Gestao!$E$4:$E1000,"<="&TODAY()+30) -> 7 | K5: =IFERROR(TEXT(Orcamentos!$Q$6,"R$ #.##0")&" / "&TEXT(Orcamentos!$O$6,"R$ #.##0"),"—") -> R$ ,0 / R$ ,0
B8: PROGRESSO POR STATUS — etapas | H8: POR SEGMENTO — etapas
B9: Status | C9: Qtd | D9: % | E9: Barra | H9: Segmento | I9: Etapas | J9: Concl. | K9: % | L9: Barra
B10: Concluído | C10: =COUNTIF(Detalhamento!$H$9:$H1000,"Concluído") -> 6 | D10: =IFERROR(C10/COUNTA(Detalhamento!$H$9:$H1000),0) -> 0.0066518847 | E10: =IFERROR(REPT("▮",ROUND(D10*20,0)),"") | H10: Civil | I10: =COUNTIF(Detalhamento!$G$9:$G1000,"Civil") -> 281 | J10: =COUNTIFS(Detalhamento!$G$9:$G1000,"Civil",Detalhamento!$H$9:$H1000,"Concluído") -> 0 | K10: =IFERROR(J10/I10,0) -> 0 | L10: =IFERROR(REPT("▮",ROUND(K10*12,0)),"")
B11: Em andamento | C11: =COUNTIF(Detalhamento!$H$9:$H1000,"Em andamento") -> 2 | D11: =IFERROR(C11/COUNTA(Detalhamento!$H$9:$H1000),0) -> 0.0022172949 | E11: =IFERROR(REPT("▮",ROUND(D11*20,0)),"") | H11: Estrutura | I11: =COUNTIF(Detalhamento!$G$9:$G1000,"Estrutura") -> 0 | J11: =COUNTIFS(Detalhamento!$G$9:$G1000,"Estrutura",Detalhamento!$H$9:$H1000,"Concluído") -> 0 | K11: =IFERROR(J11/I11,0) -> 0 | L11: =IFERROR(REPT("▮",ROUND(K11*12,0)),"")
B12: A iniciar | C12: =COUNTIF(Detalhamento!$H$9:$H1000,"A iniciar") -> 894 | D12: =IFERROR(C12/COUNTA(Detalhamento!$H$9:$H1000),0) -> 0.99113082 | E12: =IFERROR(REPT("▮",ROUND(D12*20,0)),"") -> ▮▮▮▮▮▮▮▮▮▮▮▮▮▮▮▮▮▮▮▮ | H12: Instalacoes | I12: =COUNTIF(Detalhamento!$G$9:$G1000,"Instalacoes") -> 12 | J12: =COUNTIFS(Detalhamento!$G$9:$G1000,"Instalacoes",Detalhamento!$H$9:$H1000,"Concluído") -> 0 | K12: =IFERROR(J12/I12,0) -> 0 | L12: =IFERROR(REPT("▮",ROUND(K12*12,0)),"")
H13: Hidraulica | I13: =COUNTIF(Detalhamento!$G$9:$G1000,"Hidraulica") -> 30 | J13: =COUNTIFS(Detalhamento!$G$9:$G1000,"Hidraulica",Detalhamento!$H$9:$H1000,"Concluído") -> 0 | K13: =IFERROR(J13/I13,0) -> 0 | L13: =IFERROR(REPT("▮",ROUND(K13*12,0)),"")
B14: POR ANDAR / ÁREA — itens (Gestão) | H14: Eletrica | I14: =COUNTIF(Detalhamento!$G$9:$G1000,"Eletrica") -> 86 | J14: =COUNTIFS(Detalhamento!$G$9:$G1000,"Eletrica",Detalhamento!$H$9:$H1000,"Concluído") -> 0 | K14: =IFERROR(J14/I14,0) -> 0 | L14: =IFERROR(REPT("▮",ROUND(K14*12,0)),"")
B15: Área | C15: Itens | D15: Atrasado | E15: Em and. | F15: A iniciar | H15: Climatizacao | I15: =COUNTIF(Detalhamento!$G$9:$G1000,"Climatizacao") -> 23 | J15: =COUNTIFS(Detalhamento!$G$9:$G1000,"Climatizacao",Detalhamento!$H$9:$H1000,"Concluído") -> 0 | K15: =IFERROR(J15/I15,0) -> 0 | L15: =IFERROR(REPT("▮",ROUND(K15*12,0)),"")
B16: Andar 8 | C16: =COUNTIF(Gestao!$C$4:$C1000,"Andar 8") -> 49 | D16: =COUNTIFS(Gestao!$C$4:$C1000,"Andar 8",Gestao!$F$4:$F1000,"Atrasado") -> 19 | E16: =COUNTIFS(Gestao!$C$4:$C1000,"Andar 8",Gestao!$F$4:$F1000,"Em andamento") -> 8 | F16: =COUNTIFS(Gestao!$C$4:$C1000,"Andar 8",Gestao!$F$4:$F1000,"A iniciar") -> 21 | H16: Revestimento | I16: =COUNTIF(Detalhamento!$G$9:$G1000,"Revestimento") -> 85 | J16: =COUNTIFS(Detalhamento!$G$9:$G1000,"Revestimento",Detalhamento!$H$9:$H1000,"Concluído") -> 0 | K16: =IFERROR(J16/I16,0) -> 0 | L16: =IFERROR(REPT("▮",ROUND(K16*12,0)),"")
B17: Andar 9 | C17: =COUNTIF(Gestao!$C$4:$C1000,"Andar 9") -> 37 | D17: =COUNTIFS(Gestao!$C$4:$C1000,"Andar 9",Gestao!$F$4:$F1000,"Atrasado") -> 15 | E17: =COUNTIFS(Gestao!$C$4:$C1000,"Andar 9",Gestao!$F$4:$F1000,"Em andamento") -> 6 | F17: =COUNTIFS(Gestao!$C$4:$C1000,"Andar 9",Gestao!$F$4:$F1000,"A iniciar") -> 16 | H17: Forro | I17: =COUNTIF(Detalhamento!$G$9:$G1000,"Forro") -> 38 | J17: =COUNTIFS(Detalhamento!$G$9:$G1000,"Forro",Detalhamento!$H$9:$H1000,"Concluído") -> 0 | K17: =IFERROR(J17/I17,0) -> 0 | L17: =IFERROR(REPT("▮",ROUND(K17*12,0)),"")
B18: Roof Top | C18: =COUNTIF(Gestao!$C$4:$C1000,"Roof Top") -> 12 | D18: =COUNTIFS(Gestao!$C$4:$C1000,"Roof Top",Gestao!$F$4:$F1000,"Atrasado") -> 6 | E18: =COUNTIFS(Gestao!$C$4:$C1000,"Roof Top",Gestao!$F$4:$F1000,"Em andamento") -> 0 | F18: =COUNTIFS(Gestao!$C$4:$C1000,"Roof Top",Gestao!$F$4:$F1000,"A iniciar") -> 6 | H18: Pintura | I18: =COUNTIF(Detalhamento!$G$9:$G1000,"Pintura") -> 65 | J18: =COUNTIFS(Detalhamento!$G$9:$G1000,"Pintura",Detalhamento!$H$9:$H1000,"Concluído") -> 0 | K18: =IFERROR(J18/I18,0) -> 0 | L18: =IFERROR(REPT("▮",ROUND(K18*12,0)),"")
B19: Elevadores | C19: =COUNTIF(Gestao!$C$4:$C1000,"Elevadores") -> 41 | D19: =COUNTIFS(Gestao!$C$4:$C1000,"Elevadores",Gestao!$F$4:$F1000,"Atrasado") -> 11 | E19: =COUNTIFS(Gestao!$C$4:$C1000,"Elevadores",Gestao!$F$4:$F1000,"Em andamento") -> 16 | F19: =COUNTIFS(Gestao!$C$4:$C1000,"Elevadores",Gestao!$F$4:$F1000,"A iniciar") -> 11 | H19: Esquadrias | I19: =COUNTIF(Detalhamento!$G$9:$G1000,"Esquadrias") -> 28 | J19: =COUNTIFS(Detalhamento!$G$9:$G1000,"Esquadrias",Detalhamento!$H$9:$H1000,"Concluído") -> 0 | K19: =IFERROR(J19/I19,0) -> 0 | L19: =IFERROR(REPT("▮",ROUND(K19*12,0)),"")
B20: Preliminares | C20: =COUNTIF(Gestao!$C$4:$C1000,"Preliminares") -> 5 | D20: =COUNTIFS(Gestao!$C$4:$C1000,"Preliminares",Gestao!$F$4:$F1000,"Atrasado") -> 4 | E20: =COUNTIFS(Gestao!$C$4:$C1000,"Preliminares",Gestao!$F$4:$F1000,"Em andamento") -> 1 | F20: =COUNTIFS(Gestao!$C$4:$C1000,"Preliminares",Gestao!$F$4:$F1000,"A iniciar") -> 0 | H20: Serralheria | I20: =COUNTIF(Detalhamento!$G$9:$G1000,"Serralheria") -> 48 | J20: =COUNTIFS(Detalhamento!$G$9:$G1000,"Serralheria",Detalhamento!$H$9:$H1000,"Concluído") -> 5 | K20: =IFERROR(J20/I20,0) -> 0.10416667 | L20: =IFERROR(REPT("▮",ROUND(K20*12,0)),"") -> ▮
B21: M1 - Novo Arquivo | C21: =COUNTIF(Gestao!$C$4:$C1000,"M1 - Novo Arquivo") -> 12 | D21: =COUNTIFS(Gestao!$C$4:$C1000,"M1 - Novo Arquivo",Gestao!$F$4:$F1000,"Atrasado") -> 0 | E21: =COUNTIFS(Gestao!$C$4:$C1000,"M1 - Novo Arquivo",Gestao!$F$4:$F1000,"Em andamento") -> 0 | F21: =COUNTIFS(Gestao!$C$4:$C1000,"M1 - Novo Arquivo",Gestao!$F$4:$F1000,"A iniciar") -> 12 | H21: Impermeabilizacao | I21: =COUNTIF(Detalhamento!$G$9:$G1000,"Impermeabilizacao") -> 16 | J21: =COUNTIFS(Detalhamento!$G$9:$G1000,"Impermeabilizacao",Detalhamento!$H$9:$H1000,"Concluído") -> 0 | K21: =IFERROR(J21/I21,0) -> 0 | L21: =IFERROR(REPT("▮",ROUND(K21*12,0)),"")
B22: Halls - M1/Terreo/M2 | C22: =COUNTIF(Gestao!$C$4:$C1000,"Halls - M1/Terreo/M2") -> 10 | D22: =COUNTIFS(Gestao!$C$4:$C1000,"Halls - M1/Terreo/M2",Gestao!$F$4:$F1000,"Atrasado") -> 3 | E22: =COUNTIFS(Gestao!$C$4:$C1000,"Halls - M1/Terreo/M2",Gestao!$F$4:$F1000,"Em andamento") -> 1 | F22: =COUNTIFS(Gestao!$C$4:$C1000,"Halls - M1/Terreo/M2",Gestao!$F$4:$F1000,"A iniciar") -> 6 | H22: Elevadores | I22: =COUNTIF(Detalhamento!$G$9:$G1000,"Elevadores") -> 31 | J22: =COUNTIFS(Detalhamento!$G$9:$G1000,"Elevadores",Detalhamento!$H$9:$H1000,"Concluído") -> 0 | K22: =IFERROR(J22/I22,0) -> 0 | L22: =IFERROR(REPT("▮",ROUND(K22*12,0)),"")
B23: Halls - Subsolos | C23: =COUNTIF(Gestao!$C$4:$C1000,"Halls - Subsolos") -> 2 | D23: =COUNTIFS(Gestao!$C$4:$C1000,"Halls - Subsolos",Gestao!$F$4:$F1000,"Atrasado") -> 0 | E23: =COUNTIFS(Gestao!$C$4:$C1000,"Halls - Subsolos",Gestao!$F$4:$F1000,"Em andamento") -> 0 | F23: =COUNTIFS(Gestao!$C$4:$C1000,"Halls - Subsolos",Gestao!$F$4:$F1000,"A iniciar") -> 2 | H23: Preliminares | I23: =COUNTIF(Detalhamento!$G$9:$G1000,"Preliminares") -> 3 | J23: =COUNTIFS(Detalhamento!$G$9:$G1000,"Preliminares",Detalhamento!$H$9:$H1000,"Concluído") -> 1 | K23: =IFERROR(J23/I23,0) -> 0.33333333 | L23: =IFERROR(REPT("▮",ROUND(K23*12,0)),"") -> ▮▮▮▮
H24: Limpeza | I24: =COUNTIF(Detalhamento!$G$9:$G1000,"Limpeza") -> 6 | J24: =COUNTIFS(Detalhamento!$G$9:$G1000,"Limpeza",Detalhamento!$H$9:$H1000,"Concluído") -> 0 | K24: =IFERROR(J24/I24,0) -> 0 | L24: =IFERROR(REPT("▮",ROUND(K24*12,0)),"")
B25: ⚠️ ITENS ATRASADOS (Gestão)
B26: Item | C26: Atividade | D26: Área | E26: Término
B27: =IFERROR(__xludf.DUMMYFUNCTION("IFERROR(QUERY(Gestao!A4:F1000,""select A,B,C,E where F = 'Atrasado' order by E limit 52"",0),""Nenhum atrasado"")"),"1.2") -> 1.2 | C27: =IFERROR(__xludf.DUMMYFUNCTION("""COMPUTED_VALUE"""),"Emissão de ART Obra(Anotação de responsabilidade técnica)") -> Emissão de ART Obra(Anotação de responsabilidade técnica) | D27: =IFERROR(__xludf.DUMMYFUNCTION("""COMPUTED_VALUE"""),"Preliminares") -> Preliminares | E27: =IFERROR(__xludf.DUMMYFUNCTION("""COMPUTED_VALUE"""),46050.0) -> 46050 | H27: FINANCEIRO (consolidado)
B28: =IFERROR(__xludf.DUMMYFUNCTION("""COMPUTED_VALUE"""),"1.3") -> 1.3 | C28: =IFERROR(__xludf.DUMMYFUNCTION("""COMPUTED_VALUE"""),"Mobilização de canteiro e equipes e deslocamento") -> Mobilização de canteiro e equipes e deslocamento | D28: =IFERROR(__xludf.DUMMYFUNCTION("""COMPUTED_VALUE"""),"Preliminares") -> Preliminares | E28: =IFERROR(__xludf.DUMMYFUNCTION("""COMPUTED_VALUE"""),46065.0) -> 46065 | H28: Previsto (R$) | K28: =Orcamentos!$O$6 -> 0
B29: =IFERROR(__xludf.DUMMYFUNCTION("""COMPUTED_VALUE"""),"6.1") -> 6.1 | C29: =IFERROR(__xludf.DUMMYFUNCTION("""COMPUTED_VALUE"""),"Demolicão manual de alvenaria de tijolos furados, contrapiso de 5 cm no deposito 5, inclusive empilhamento dentro do canteiro de servico.") -> Demolicão manual de alvenaria de tijolos furados, contrapiso de 5 cm no deposito 5, inclusive empilhamento dentro do canteiro de servico. | D29: =IFERROR(__xludf.DUMMYFUNCTION("""COMPUTED_VALUE"""),"Andar 9") -> Andar 9 | E29: =IFERROR(__xludf.DUMMYFUNCTION("""COMPUTED_VALUE"""),46072.0) -> 46072 | H29: Real / Devido (R$) | K29: =Orcamentos!$P$6 -> 0
B30: =IFERROR(__xludf.DUMMYFUNCTION("""COMPUTED_VALUE"""),"6.6") -> 6.6 | C30: =IFERROR(__xludf.DUMMYFUNCTION("""COMPUTED_VALUE"""),"Retiro porta existente.") -> Retiro porta existente. | D30: =IFERROR(__xludf.DUMMYFUNCTION("""COMPUTED_VALUE"""),"Andar 9") -> Andar 9 | E30: =IFERROR(__xludf.DUMMYFUNCTION("""COMPUTED_VALUE"""),46072.0) -> 46072 | H30: Pago (R$) | K30: =Orcamentos!$Q$6 -> 0
B31: =IFERROR(__xludf.DUMMYFUNCTION("""COMPUTED_VALUE"""),"1.1") -> 1.1 | C31: =IFERROR(__xludf.DUMMYFUNCTION("""COMPUTED_VALUE"""),"Gerenciamento técnico de obra - 2 Engenheiros (40h/mês) , assistente tecnico (40h/mês) , mestre de obra (160h/mês)") -> Gerenciamento técnico de obra - 2 Engenheiros (40h/mês) , assistente tecnico (40h/mês) , mestre de obra (160h/mês) | D31: =IFERROR(__xludf.DUMMYFUNCTION("""COMPUTED_VALUE"""),"Preliminares") -> Preliminares | E31: =IFERROR(__xludf.DUMMYFUNCTION("""COMPUTED_VALUE"""),46073.0) -> 46073 | H31: Saldo (R$) | K31: =Orcamentos!$R$6 -> 0
B32: =IFERROR(__xludf.DUMMYFUNCTION("""COMPUTED_VALUE"""),"1.4") -> 1.4 | C32: =IFERROR(__xludf.DUMMYFUNCTION("""COMPUTED_VALUE"""),"Tapume de vedacao ou protecao, executado com chapas de compensado, tipo chapa resinada ou similar, com 6mm de espessura, exclusive pintura. Proteção chegada elvadores;.") -> Tapume de vedacao ou protecao, executado com chapas de compensado, tipo chapa resinada ou similar, com 6mm de espessura, exclusive pintura. Proteção chegada elvadores;. | D32: =IFERROR(__xludf.DUMMYFUNCTION("""COMPUTED_VALUE"""),"Preliminares") -> Preliminares | E32: =IFERROR(__xludf.DUMMYFUNCTION("""COMPUTED_VALUE"""),46080.0) -> 46080 | H32: A pagar (R$) | K32: =Pagamentos!$C$2
B33: =IFERROR(__xludf.DUMMYFUNCTION("""COMPUTED_VALUE"""),"5.7") -> 5.7 | C33: =IFERROR(__xludf.DUMMYFUNCTION("""COMPUTED_VALUE"""),"Retiro porta existente.") -> Retiro porta existente. | D33: =IFERROR(__xludf.DUMMYFUNCTION("""COMPUTED_VALUE"""),"Andar 8") -> Andar 8 | E33: =IFERROR(__xludf.DUMMYFUNCTION("""COMPUTED_VALUE"""),46080.0) -> 46080 | H33: Vencendo 7 dias (R$) | K33: =Pagamentos!$G$2
B34: =IFERROR(__xludf.DUMMYFUNCTION("""COMPUTED_VALUE"""),"5.11") -> 5.11 | C34: =IFERROR(__xludf.DUMMYFUNCTION("""COMPUTED_VALUE"""),"Realização da nova janela considerando as aberturas já existentes e os fechamentos com tijolos onde necessarios.") -> Realização da nova janela considerando as aberturas já existentes e os fechamentos com tijolos onde necessarios. | D34: =IFERROR(__xludf.DUMMYFUNCTION("""COMPUTED_VALUE"""),"Andar 8") -> Andar 8 | E34: =IFERROR(__xludf.DUMMYFUNCTION("""COMPUTED_VALUE"""),46086.0) -> 46086 | H34: Pagamentos atrasados (R$) | K34: =Pagamentos!$I$2
B35: =IFERROR(__xludf.DUMMYFUNCTION("""COMPUTED_VALUE"""),"5.1") -> 5.1 | C35: =IFERROR(__xludf.DUMMYFUNCTION("""COMPUTED_VALUE"""),"Demolicão manual de alvenaria de tijolos furados, contrapiso de 5 cm no deposito 5, inclusive empilhamento dentro do canteiro de servico.") -> Demolicão manual de alvenaria de tijolos furados, contrapiso de 5 cm no deposito 5, inclusive empilhamento dentro do canteiro de servico. | D35: =IFERROR(__xludf.DUMMYFUNCTION("""COMPUTED_VALUE"""),"Andar 8") -> Andar 8 | E35: =IFERROR(__xludf.DUMMYFUNCTION("""COMPUTED_VALUE"""),46094.0) -> 46094
B36: =IFERROR(__xludf.DUMMYFUNCTION("""COMPUTED_VALUE"""),"5.9") -> 5.9 | C36: =IFERROR(__xludf.DUMMYFUNCTION("""COMPUTED_VALUE"""),"Demolição do suporte em concreto do velho sistema de ar-condicionado e nivelamento bruto do piso") -> Demolição do suporte em concreto do velho sistema de ar-condicionado e nivelamento bruto do piso | D36: =IFERROR(__xludf.DUMMYFUNCTION("""COMPUTED_VALUE"""),"Andar 8") -> Andar 8 | E36: =IFERROR(__xludf.DUMMYFUNCTION("""COMPUTED_VALUE"""),46094.0) -> 46094
B37: =IFERROR(__xludf.DUMMYFUNCTION("""COMPUTED_VALUE"""),"5.2") -> 5.2 | C37: =IFERROR(__xludf.DUMMYFUNCTION("""COMPUTED_VALUE"""),"Demolição controlada e monitrada para rebaixamento da laje e abertura na laje e paredes em concreto armado") -> Demolição controlada e monitrada para rebaixamento da laje e abertura na laje e paredes em concreto armado | D37: =IFERROR(__xludf.DUMMYFUNCTION("""COMPUTED_VALUE"""),"Andar 8") -> Andar 8 | E37: =IFERROR(__xludf.DUMMYFUNCTION("""COMPUTED_VALUE"""),46103.0) -> 46103
B38: =IFERROR(__xludf.DUMMYFUNCTION("""COMPUTED_VALUE"""),"5.8") -> 5.8 | C38: =IFERROR(__xludf.DUMMYFUNCTION("""COMPUTED_VALUE"""),"Demolição controlada e monitorada do cocreto para abertura das novas portas") -> Demolição controlada e monitorada do cocreto para abertura das novas portas | D38: =IFERROR(__xludf.DUMMYFUNCTION("""COMPUTED_VALUE"""),"Andar 8") -> Andar 8 | E38: =IFERROR(__xludf.DUMMYFUNCTION("""COMPUTED_VALUE"""),46122.0) -> 46122
B39: =IFERROR(__xludf.DUMMYFUNCTION("""COMPUTED_VALUE"""),"6.2") -> 6.2 | C39: =IFERROR(__xludf.DUMMYFUNCTION("""COMPUTED_VALUE"""),"Demolição controlada e monitrada para rebaixamento da laje e abertura na laje e paredes em concreto armado") -> Demolição controlada e monitrada para rebaixamento da laje e abertura na laje e paredes em concreto armado | D39: =IFERROR(__xludf.DUMMYFUNCTION("""COMPUTED_VALUE"""),"Andar 9") -> Andar 9 | E39: =IFERROR(__xludf.DUMMYFUNCTION("""COMPUTED_VALUE"""),46135.0) -> 46135
B40: =IFERROR(__xludf.DUMMYFUNCTION("""COMPUTED_VALUE"""),"5.13") -> 5.13 | C40: =IFERROR(__xludf.DUMMYFUNCTION("""COMPUTED_VALUE"""),"Construção da separação das duas novas portas e da parede de separação do novo corredor verso externo.") -> Construção da separação das duas novas portas e da parede de separação do novo corredor verso externo. | D40: =IFERROR(__xludf.DUMMYFUNCTION("""COMPUTED_VALUE"""),"Andar 8") -> Andar 8 | E40: =IFERROR(__xludf.DUMMYFUNCTION("""COMPUTED_VALUE"""),46136.0) -> 46136
B41: =IFERROR(__xludf.DUMMYFUNCTION("""COMPUTED_VALUE"""),"5.15") -> 5.15 | C41: =IFERROR(__xludf.DUMMYFUNCTION("""COMPUTED_VALUE"""),"Fornecimento e execução de parede em alvenaria com bloco cimentício, considerando chapisco e reboco (desonerado)") -> Fornecimento e execução de parede em alvenaria com bloco cimentício, considerando chapisco e reboco (desonerado) | D41: =IFERROR(__xludf.DUMMYFUNCTION("""COMPUTED_VALUE"""),"Andar 8") -> Andar 8 | E41: =IFERROR(__xludf.DUMMYFUNCTION("""COMPUTED_VALUE"""),46136.0) -> 46136
B42: =IFERROR(__xludf.DUMMYFUNCTION("""COMPUTED_VALUE"""),"5.32") -> 5.32 | C42: =IFERROR(__xludf.DUMMYFUNCTION("""COMPUTED_VALUE"""),"Fornecimento e instalação de QUADRO DE DITRIBUÇÃO completo, embutido ou sobreposto, em caixa metálica ou termoplástica, com porta, pintura eletrostática e grau de proteção mínimo IP40. Equipado com disjuntores termomagnéticos monopolares, bipolares ou tri"&"polares conforme projeto, barramentos de fase, neutro e terra, trilho DIN, identificação dos circuitos e acessórios. Inclusos todos os materiais, componentes, mão de obra para montagem, fixação, aterramento, testes e conformidade com as normas técnicas vi"&"gentes (NBR 5410 e NR-10).") -> Fornecimento e instalação de QUADRO DE DITRIBUÇÃO completo, embutido ou sobreposto, em caixa metálica ou termoplástica, com porta, pintura eletrostática e grau de proteção mínimo IP40. Equipado com disjuntores termomagnéticos monopolares, bipolares ou tripolares conforme projeto, barramentos de fase, neutro e terra, trilho DIN, identificação dos circuitos e acessórios. Inclusos todos os materiais, componentes, mão de obra para montagem, fixação, aterramento, testes e conformidade com as normas técnicas vigentes (NBR 5410 e NR-10). | D42: =IFERROR(__xludf.DUMMYFUNCTION("""COMPUTED_VALUE"""),"Andar 8") -> Andar 8 | E42: =IFERROR(__xludf.DUMMYFUNCTION("""COMPUTED_VALUE"""),46142.0) -> 46142
B43: =IFERROR(__xludf.DUMMYFUNCTION("""COMPUTED_VALUE"""),"5.33") -> 5.33 | C43: =IFERROR(__xludf.DUMMYFUNCTION("""COMPUTED_VALUE"""),"Execução de ponto elétrico completo embutido, composto por 1 tomada 2P+T 20A, 220V e 1 ponto de luz (sem luminária), com fornecimento e instalação de eletrodutos rígidos PVC, caixas de embutir, cabos de cobre ( 25 tomadas + 25 ponto de luz) antichama (fas"&"e, neutro e terra), conectores, suporte e espelho. Inclui instalação da infraestrutura embutida em alvenaria, passagem dos condutores, fixação dos mecanismos, identificação dos circuitos e testes de funcionamento, conforme NBR 5410 e NR-10.") -> Execução de ponto elétrico completo embutido, composto por 1 tomada 2P+T 20A, 220V e 1 ponto de luz (sem luminária), com fornecimento e instalação de eletrodutos rígidos PVC, caixas de embutir, cabos de cobre ( 25 tomadas + 25 ponto de luz) antichama (fase, neutro e terra), conectores, suporte e espelho. Inclui instalação da infraestrutura embutida em alvenaria, passagem dos condutores, fixação dos mecanismos, identificação dos circuitos e testes de funcionamento, conforme NBR 5410 e NR-10. | D43: =IFERROR(__xludf.DUMMYFUNCTION("""COMPUTED_VALUE"""),"Andar 8") -> Andar 8 | E43: =IFERROR(__xludf.DUMMYFUNCTION("""COMPUTED_VALUE"""),46142.0) -> 46142
B44: =IFERROR(__xludf.DUMMYFUNCTION("""COMPUTED_VALUE"""),"5.34") -> 5.34 | C44: =IFERROR(__xludf.DUMMYFUNCTION("""COMPUTED_VALUE"""),"Ponto de água fria em PVC Marrom") -> Ponto de água fria em PVC Marrom | D44: =IFERROR(__xludf.DUMMYFUNCTION("""COMPUTED_VALUE"""),"Andar 8") -> Andar 8 | E44: =IFERROR(__xludf.DUMMYFUNCTION("""COMPUTED_VALUE"""),46142.0) -> 46142
B45: =IFERROR(__xludf.DUMMYFUNCTION("""COMPUTED_VALUE"""),"5.35") -> 5.35 | C45: =IFERROR(__xludf.DUMMYFUNCTION("""COMPUTED_VALUE"""),"Ponto de esgoto em PVC branco 50mm ou 100mm") -> Ponto de esgoto em PVC branco 50mm ou 100mm | D45: =IFERROR(__xludf.DUMMYFUNCTION("""COMPUTED_VALUE"""),"Andar 8") -> Andar 8 | E45: =IFERROR(__xludf.DUMMYFUNCTION("""COMPUTED_VALUE"""),46142.0) -> 46142
B46: =IFERROR(__xludf.DUMMYFUNCTION("""COMPUTED_VALUE"""),"5.18") -> 5.18 | C46: =IFERROR(__xludf.DUMMYFUNCTION("""COMPUTED_VALUE"""),"Novo reboco nas paredes e no teto.") -> Novo reboco nas paredes e no teto. | D46: =IFERROR(__xludf.DUMMYFUNCTION("""COMPUTED_VALUE"""),"Andar 8") -> Andar 8 | E46: =IFERROR(__xludf.DUMMYFUNCTION("""COMPUTED_VALUE"""),46147.0) -> 46147
B47: =IFERROR(__xludf.DUMMYFUNCTION("""COMPUTED_VALUE"""),"6.7") -> 6.7 | C47: =IFERROR(__xludf.DUMMYFUNCTION("""COMPUTED_VALUE"""),"Fornecimento e execução de parede em alvenaria com bloco cimentício, considerando chapisco e reboco (desonerado)") -> Fornecimento e execução de parede em alvenaria com bloco cimentício, considerando chapisco e reboco (desonerado) | D47: =IFERROR(__xludf.DUMMYFUNCTION("""COMPUTED_VALUE"""),"Andar 9") -> Andar 9 | E47: =IFERROR(__xludf.DUMMYFUNCTION("""COMPUTED_VALUE"""),46149.0) -> 46149
B48: =IFERROR(__xludf.DUMMYFUNCTION("""COMPUTED_VALUE"""),"7.1") -> 7.1 | C48: =IFERROR(__xludf.DUMMYFUNCTION("""COMPUTED_VALUE"""),"Demolição controlada e monitrada para rebaixamento da laje e abertura na laje e paredes em concreto armado") -> Demolição controlada e monitrada para rebaixamento da laje e abertura na laje e paredes em concreto armado | D48: =IFERROR(__xludf.DUMMYFUNCTION("""COMPUTED_VALUE"""),"Roof Top") -> Roof Top | E48: =IFERROR(__xludf.DUMMYFUNCTION("""COMPUTED_VALUE"""),46149.0) -> 46149
B49: =IFERROR(__xludf.DUMMYFUNCTION("""COMPUTED_VALUE"""),"7.2") -> 7.2 | C49: =IFERROR(__xludf.DUMMYFUNCTION("""COMPUTED_VALUE"""),"Caçamba para entulho 4m³") -> Caçamba para entulho 4m³ | D49: =IFERROR(__xludf.DUMMYFUNCTION("""COMPUTED_VALUE"""),"Roof Top") -> Roof Top | E49: =IFERROR(__xludf.DUMMYFUNCTION("""COMPUTED_VALUE"""),46149.0) -> 46149
B50: =IFERROR(__xludf.DUMMYFUNCTION("""COMPUTED_VALUE"""),"7.3") -> 7.3 | C50: =IFERROR(__xludf.DUMMYFUNCTION("""COMPUTED_VALUE"""),"Transporte de entulho e grades") -> Transporte de entulho e grades | D50: =IFERROR(__xludf.DUMMYFUNCTION("""COMPUTED_VALUE"""),"Roof Top") -> Roof Top | E50: =IFERROR(__xludf.DUMMYFUNCTION("""COMPUTED_VALUE"""),46149.0) -> 46149
B51: =IFERROR(__xludf.DUMMYFUNCTION("""COMPUTED_VALUE"""),"7.4") -> 7.4 | C51: =IFERROR(__xludf.DUMMYFUNCTION("""COMPUTED_VALUE"""),"Caçamba para entulho 4m³") -> Caçamba para entulho 4m³ | D51: =IFERROR(__xludf.DUMMYFUNCTION("""COMPUTED_VALUE"""),"Roof Top") -> Roof Top | E51: =IFERROR(__xludf.DUMMYFUNCTION("""COMPUTED_VALUE"""),46149.0) -> 46149
B52: =IFERROR(__xludf.DUMMYFUNCTION("""COMPUTED_VALUE"""),"7.5") -> 7.5 | C52: =IFERROR(__xludf.DUMMYFUNCTION("""COMPUTED_VALUE"""),"Transporte de entulho") -> Transporte de entulho | D52: =IFERROR(__xludf.DUMMYFUNCTION("""COMPUTED_VALUE"""),"Roof Top") -> Roof Top | E52: =IFERROR(__xludf.DUMMYFUNCTION("""COMPUTED_VALUE"""),46149.0) -> 46149
B53: =IFERROR(__xludf.DUMMYFUNCTION("""COMPUTED_VALUE"""),"7.6") -> 7.6 | C53: =IFERROR(__xludf.DUMMYFUNCTION("""COMPUTED_VALUE"""),"Retiro porta existente.") -> Retiro porta existente. | D53: =IFERROR(__xludf.DUMMYFUNCTION("""COMPUTED_VALUE"""),"Roof Top") -> Roof Top | E53: =IFERROR(__xludf.DUMMYFUNCTION("""COMPUTED_VALUE"""),46149.0) -> 46149
B54: =IFERROR(__xludf.DUMMYFUNCTION("""COMPUTED_VALUE"""),"6.22") -> 6.22 | C54: =IFERROR(__xludf.DUMMYFUNCTION("""COMPUTED_VALUE"""),"Fornecimento e instalação de QUADRO DE DITRIBUÇÃO completo, embutido ou sobreposto, em caixa metálica ou termoplástica, com porta, pintura eletrostática e grau de proteção mínimo IP40. Equipado com disjuntores termomagnéticos monopolares, bipolares ou tri"&"polares conforme projeto, barramentos de fase, neutro e terra, trilho DIN, identificação dos circuitos e acessórios. Inclusos todos os materiais, componentes, mão de obra para montagem, fixação, aterramento, testes e conformidade com as normas técnicas vi"&"gentes (NBR 5410 e NR-10).") -> Fornecimento e instalação de QUADRO DE DITRIBUÇÃO completo, embutido ou sobreposto, em caixa metálica ou termoplástica, com porta, pintura eletrostática e grau de proteção mínimo IP40. Equipado com disjuntores termomagnéticos monopolares, bipolares ou tripolares conforme projeto, barramentos de fase, neutro e terra, trilho DIN, identificação dos circuitos e acessórios. Inclusos todos os materiais, componentes, mão de obra para montagem, fixação, aterramento, testes e conformidade com as normas técnicas vigentes (NBR 5410 e NR-10). | D54: =IFERROR(__xludf.DUMMYFUNCTION("""COMPUTED_VALUE"""),"Andar 9") -> Andar 9 | E54: =IFERROR(__xludf.DUMMYFUNCTION("""COMPUTED_VALUE"""),46156.0) -> 46156
B55: =IFERROR(__xludf.DUMMYFUNCTION("""COMPUTED_VALUE"""),"6.24") -> 6.24 | C55: =IFERROR(__xludf.DUMMYFUNCTION("""COMPUTED_VALUE"""),"Ponto de água fria em PVC Marrom") -> Ponto de água fria em PVC Marrom | D55: =IFERROR(__xludf.DUMMYFUNCTION("""COMPUTED_VALUE"""),"Andar 9") -> Andar 9 | E55: =IFERROR(__xludf.DUMMYFUNCTION("""COMPUTED_VALUE"""),46156.0) -> 46156
B56: =IFERROR(__xludf.DUMMYFUNCTION("""COMPUTED_VALUE"""),"6.25") -> 6.25 | C56: =IFERROR(__xludf.DUMMYFUNCTION("""COMPUTED_VALUE"""),"Ponto de esgoto em PVC branco 50mm ou 100mm") -> Ponto de esgoto em PVC branco 50mm ou 100mm | D56: =IFERROR(__xludf.DUMMYFUNCTION("""COMPUTED_VALUE"""),"Andar 9") -> Andar 9 | E56: =IFERROR(__xludf.DUMMYFUNCTION("""COMPUTED_VALUE"""),46156.0) -> 46156
B57: =IFERROR(__xludf.DUMMYFUNCTION("""COMPUTED_VALUE"""),"2.1") -> 2.1 | C57: =IFERROR(__xludf.DUMMYFUNCTION("""COMPUTED_VALUE"""),"Demolicão manual de alvenaria de tijolos furados, contrapiso de 5 cm no deposito 5, inclusive empilhamento dentro do canteiro de servico.") -> Demolicão manual de alvenaria de tijolos furados, contrapiso de 5 cm no deposito 5, inclusive empilhamento dentro do canteiro de servico. | D57: =IFERROR(__xludf.DUMMYFUNCTION("""COMPUTED_VALUE"""),"Elevadores") -> Elevadores | E57: =IFERROR(__xludf.DUMMYFUNCTION("""COMPUTED_VALUE"""),46166.0) -> 46166
B58: =IFERROR(__xludf.DUMMYFUNCTION("""COMPUTED_VALUE"""),"2.3") -> 2.3 | C58: =IFERROR(__xludf.DUMMYFUNCTION("""COMPUTED_VALUE"""),"Caçamba para entulho 4m³") -> Caçamba para entulho 4m³ | D58: =IFERROR(__xludf.DUMMYFUNCTION("""COMPUTED_VALUE"""),"Elevadores") -> Elevadores | E58: =IFERROR(__xludf.DUMMYFUNCTION("""COMPUTED_VALUE"""),46166.0) -> 46166
B59: =IFERROR(__xludf.DUMMYFUNCTION("""COMPUTED_VALUE"""),"2.4") -> 2.4 | C59: =IFERROR(__xludf.DUMMYFUNCTION("""COMPUTED_VALUE"""),"Transporte de entulho e grades") -> Transporte de entulho e grades | D59: =IFERROR(__xludf.DUMMYFUNCTION("""COMPUTED_VALUE"""),"Elevadores") -> Elevadores | E59: =IFERROR(__xludf.DUMMYFUNCTION("""COMPUTED_VALUE"""),46166.0) -> 46166
B60: =IFERROR(__xludf.DUMMYFUNCTION("""COMPUTED_VALUE"""),"5.19") -> 5.19 | C60: =IFERROR(__xludf.DUMMYFUNCTION("""COMPUTED_VALUE"""),"Nivelamento fino do piso.") -> Nivelamento fino do piso. | D60: =IFERROR(__xludf.DUMMYFUNCTION("""COMPUTED_VALUE"""),"Andar 8") -> Andar 8 | E60: =IFERROR(__xludf.DUMMYFUNCTION("""COMPUTED_VALUE"""),46170.0) -> 46170
B61: =IFERROR(__xludf.DUMMYFUNCTION("""COMPUTED_VALUE"""),"6.23") -> 6.23 | C61: =IFERROR(__xludf.DUMMYFUNCTION("""COMPUTED_VALUE"""),"Execução de ponto elétrico completo embutido, composto por 1 tomada 2P+T 20A, 220V e 1 ponto de luz (sem luminária), com fornecimento e instalação de eletrodutos rígidos PVC, caixas de embutir, cabos de cobre ( 25 tomadas + 25 ponto de luz) antichama (fas"&"e, neutro e terra), conectores, suporte e espelho. Inclui instalação da infraestrutura embutida em alvenaria, passagem dos condutores, fixação dos mecanismos, identificação dos circuitos e testes de funcionamento, conforme NBR 5410 e NR-10.") -> Execução de ponto elétrico completo embutido, composto por 1 tomada 2P+T 20A, 220V e 1 ponto de luz (sem luminária), com fornecimento e instalação de eletrodutos rígidos PVC, caixas de embutir, cabos de cobre ( 25 tomadas + 25 ponto de luz) antichama (fase, neutro e terra), conectores, suporte e espelho. Inclui instalação da infraestrutura embutida em alvenaria, passagem dos condutores, fixação dos mecanismos, identificação dos circuitos e testes de funcionamento, conforme NBR 5410 e NR-10. | D61: =IFERROR(__xludf.DUMMYFUNCTION("""COMPUTED_VALUE"""),"Andar 9") -> Andar 9 | E61: =IFERROR(__xludf.DUMMYFUNCTION("""COMPUTED_VALUE"""),46170.0) -> 46170
B62: =IFERROR(__xludf.DUMMYFUNCTION("""COMPUTED_VALUE"""),"20.01") -> 20.01 | C62: =IFERROR(__xludf.DUMMYFUNCTION("""COMPUTED_VALUE"""),"Fechamento do entre poço do elevador com estrutura metálica") -> Fechamento do entre poço do elevador com estrutura metálica | D62: =IFERROR(__xludf.DUMMYFUNCTION("""COMPUTED_VALUE"""),"Elevadores") -> Elevadores | E62: =IFERROR(__xludf.DUMMYFUNCTION("""COMPUTED_VALUE"""),46176.0) -> 46176
B63: =IFERROR(__xludf.DUMMYFUNCTION("""COMPUTED_VALUE"""),"5.16") -> 5.16 | C63: =IFERROR(__xludf.DUMMYFUNCTION("""COMPUTED_VALUE"""),"Forro mineral modular, em placas 625x625 mm ou 625x1250 mm, com acabamento texturizado branco, espessura média de 15 a 20 mm, com propriedades acústicas e térmicas, instalado em estrutura metálica tipo T (aparen­te), com nivelamento e alinhamento conforme"&" projeto. Incluso todos os materiais, cortes, arremates, peças de fixação e mão de obra.") -> Forro mineral modular, em placas 625x625 mm ou 625x1250 mm, com acabamento texturizado branco, espessura média de 15 a 20 mm, com propriedades acústicas e térmicas, instalado em estrutura metálica tipo T (aparen­te), com nivelamento e alinhamento conforme projeto. Incluso todos os materiais, cortes, arremates, peças de fixação e mão de obra. | D63: =IFERROR(__xludf.DUMMYFUNCTION("""COMPUTED_VALUE"""),"Andar 8") -> Andar 8 | E63: =IFERROR(__xludf.DUMMYFUNCTION("""COMPUTED_VALUE"""),46177.0) -> 46177
B64: =IFERROR(__xludf.DUMMYFUNCTION("""COMPUTED_VALUE"""),"4.8") -> 4.8 | C64: =IFERROR(__xludf.DUMMYFUNCTION("""COMPUTED_VALUE"""),"Cabo Flexível PP Extensão 3x25mm Rolo Com 100 Metros- Prismyan afumex") -> Cabo Flexível PP Extensão 3x25mm Rolo Com 100 Metros- Prismyan afumex | D64: =IFERROR(__xludf.DUMMYFUNCTION("""COMPUTED_VALUE"""),"Elevadores") -> Elevadores | E64: =IFERROR(__xludf.DUMMYFUNCTION("""COMPUTED_VALUE"""),46180.0) -> 46180
B65: =IFERROR(__xludf.DUMMYFUNCTION("""COMPUTED_VALUE"""),"4.10") -> 4.10 | C65: =IFERROR(__xludf.DUMMYFUNCTION("""COMPUTED_VALUE"""),"Disjuntores 32A") -> Disjuntores 32A | D65: =IFERROR(__xludf.DUMMYFUNCTION("""COMPUTED_VALUE"""),"Elevadores") -> Elevadores | E65: =IFERROR(__xludf.DUMMYFUNCTION("""COMPUTED_VALUE"""),46180.0) -> 46180
B66: =IFERROR(__xludf.DUMMYFUNCTION("""COMPUTED_VALUE"""),"4.11") -> 4.11 | C66: =IFERROR(__xludf.DUMMYFUNCTION("""COMPUTED_VALUE"""),"Cabo Flexível PP Extensão 3x4mm Rolo Com 100 Metros - Prismyan afumex") -> Cabo Flexível PP Extensão 3x4mm Rolo Com 100 Metros - Prismyan afumex | D66: =IFERROR(__xludf.DUMMYFUNCTION("""COMPUTED_VALUE"""),"Elevadores") -> Elevadores | E66: =IFERROR(__xludf.DUMMYFUNCTION("""COMPUTED_VALUE"""),46180.0) -> 46180
B67: =IFERROR(__xludf.DUMMYFUNCTION("""COMPUTED_VALUE"""),"4.12") -> 4.12 | C67: =IFERROR(__xludf.DUMMYFUNCTION("""COMPUTED_VALUE"""),"Cabo Flexível PP Extensão 3x2,5mm Rolo Com 100 Metros- Prismyan afumex") -> Cabo Flexível PP Extensão 3x2,5mm Rolo Com 100 Metros- Prismyan afumex | D67: =IFERROR(__xludf.DUMMYFUNCTION("""COMPUTED_VALUE"""),"Elevadores") -> Elevadores | E67: =IFERROR(__xludf.DUMMYFUNCTION("""COMPUTED_VALUE"""),46180.0) -> 46180
B68: =IFERROR(__xludf.DUMMYFUNCTION("""COMPUTED_VALUE"""),"5.10") -> 5.10 | C68: =IFERROR(__xludf.DUMMYFUNCTION("""COMPUTED_VALUE"""),"Ampliamento laje +36,55") -> Ampliamento laje +36,55 | D68: =IFERROR(__xludf.DUMMYFUNCTION("""COMPUTED_VALUE"""),"Andar 8") -> Andar 8 | E68: =IFERROR(__xludf.DUMMYFUNCTION("""COMPUTED_VALUE"""),46180.0) -> 46180
B69: =IFERROR(__xludf.DUMMYFUNCTION("""COMPUTED_VALUE"""),"5.3") -> 5.3 | C69: =IFERROR(__xludf.DUMMYFUNCTION("""COMPUTED_VALUE"""),"Transporte de entulho e grades") -> Transporte de entulho e grades | D69: =IFERROR(__xludf.DUMMYFUNCTION("""COMPUTED_VALUE"""),"Andar 8") -> Andar 8 | E69: =IFERROR(__xludf.DUMMYFUNCTION("""COMPUTED_VALUE"""),46184.0) -> 46184
B70: =IFERROR(__xludf.DUMMYFUNCTION("""COMPUTED_VALUE"""),"6.10") -> 6.10 | C70: =IFERROR(__xludf.DUMMYFUNCTION("""COMPUTED_VALUE"""),"Novo reboco nas paredes e no teto.") -> Novo reboco nas paredes e no teto. | D70: =IFERROR(__xludf.DUMMYFUNCTION("""COMPUTED_VALUE"""),"Andar 9") -> Andar 9 | E70: =IFERROR(__xludf.DUMMYFUNCTION("""COMPUTED_VALUE"""),46184.0) -> 46184
B71: =IFERROR(__xludf.DUMMYFUNCTION("""COMPUTED_VALUE"""),"6.11") -> 6.11 | C71: =IFERROR(__xludf.DUMMYFUNCTION("""COMPUTED_VALUE"""),"Nivelamento fino do piso.") -> Nivelamento fino do piso. | D71: =IFERROR(__xludf.DUMMYFUNCTION("""COMPUTED_VALUE"""),"Andar 9") -> Andar 9 | E71: =IFERROR(__xludf.DUMMYFUNCTION("""COMPUTED_VALUE"""),46184.0) -> 46184
B72: =IFERROR(__xludf.DUMMYFUNCTION("""COMPUTED_VALUE"""),"9.1") -> 9.1 | C72: =IFERROR(__xludf.DUMMYFUNCTION("""COMPUTED_VALUE"""),"Demolicão manual de forro , inclusive empilhamento dentro do canteiro de servico.") -> Demolicão manual de forro , inclusive empilhamento dentro do canteiro de servico. | D72: =IFERROR(__xludf.DUMMYFUNCTION("""COMPUTED_VALUE"""),"Halls - M1/Terreo/M2") -> Halls - M1/Terreo/M2 | E72: =IFERROR(__xludf.DUMMYFUNCTION("""COMPUTED_VALUE"""),46184.0) -> 46184
B73: =IFERROR(__xludf.DUMMYFUNCTION("""COMPUTED_VALUE"""),"9.2") -> 9.2 | C73: =IFERROR(__xludf.DUMMYFUNCTION("""COMPUTED_VALUE"""),"Retiro porta existente Combate Incendio") -> Retiro porta existente Combate Incendio | D73: =IFERROR(__xludf.DUMMYFUNCTION("""COMPUTED_VALUE"""),"Halls - M1/Terreo/M2") -> Halls - M1/Terreo/M2 | E73: =IFERROR(__xludf.DUMMYFUNCTION("""COMPUTED_VALUE"""),46184.0) -> 46184
B74: =IFERROR(__xludf.DUMMYFUNCTION("""COMPUTED_VALUE"""),"4.15") -> 4.15 | C74: =IFERROR(__xludf.DUMMYFUNCTION("""COMPUTED_VALUE"""),"Fornecimento Luminária Led com suporte 60 cm 9w 6500k") -> Fornecimento Luminária Led com suporte 60 cm 9w 6500k | D74: =IFERROR(__xludf.DUMMYFUNCTION("""COMPUTED_VALUE"""),"Elevadores") -> Elevadores | E74: =IFERROR(__xludf.DUMMYFUNCTION("""COMPUTED_VALUE"""),46187.0) -> 46187
B75: =IFERROR(__xludf.DUMMYFUNCTION("""COMPUTED_VALUE"""),"4.16") -> 4.16 | C75: =IFERROR(__xludf.DUMMYFUNCTION("""COMPUTED_VALUE"""),"Fornecimento Luminária Led com suporte 120 cm 18w 6500k") -> Fornecimento Luminária Led com suporte 120 cm 18w 6500k | D75: =IFERROR(__xludf.DUMMYFUNCTION("""COMPUTED_VALUE"""),"Elevadores") -> Elevadores | E75: =IFERROR(__xludf.DUMMYFUNCTION("""COMPUTED_VALUE"""),46187.0) -> 46187
B76: =IFERROR(__xludf.DUMMYFUNCTION("""COMPUTED_VALUE"""),"2.7") -> 2.7 | C76: =IFERROR(__xludf.DUMMYFUNCTION("""COMPUTED_VALUE"""),"Montagem e desmontagem de andaime direcional estrutural com chumbadores e plataforma") -> Montagem e desmontagem de andaime direcional estrutural com chumbadores e plataforma | D76: =IFERROR(__xludf.DUMMYFUNCTION("""COMPUTED_VALUE"""),"Elevadores") -> Elevadores | E76: =IFERROR(__xludf.DUMMYFUNCTION("""COMPUTED_VALUE"""),46191.0) -> 46191
B77: =IFERROR(__xludf.DUMMYFUNCTION("""COMPUTED_VALUE"""),"5.6") -> 5.6 | C77: =IFERROR(__xludf.DUMMYFUNCTION("""COMPUTED_VALUE"""),"Montagem e desmontagem de andaime direcional estrutural com chumbadores e plataforma e sistema de decida") -> Montagem e desmontagem de andaime direcional estrutural com chumbadores e plataforma e sistema de decida | D77: =IFERROR(__xludf.DUMMYFUNCTION("""COMPUTED_VALUE"""),"Andar 8") -> Andar 8 | E77: =IFERROR(__xludf.DUMMYFUNCTION("""COMPUTED_VALUE"""),46191.0) -> 46191
B78: =IFERROR(__xludf.DUMMYFUNCTION("""COMPUTED_VALUE"""),"6.3") -> 6.3 | C78: =IFERROR(__xludf.DUMMYFUNCTION("""COMPUTED_VALUE"""),"Transporte de entulho e grades") -> Transporte de entulho e grades | D78: =IFERROR(__xludf.DUMMYFUNCTION("""COMPUTED_VALUE"""),"Andar 9") -> Andar 9 | E78: =IFERROR(__xludf.DUMMYFUNCTION("""COMPUTED_VALUE"""),46191.0) -> 46191
B80: 📅 PRÓXIMAS ENTREGAS (30 dias)
B81: Item | C81: Atividade | D81: Área | E81: Término
B82: =IFERROR(__xludf.DUMMYFUNCTION("IFERROR(QUERY(Gestao!A4:F1000,""select A,B,C,E where E >= date '""&TEXT(TODAY(),""yyyy-mm-dd"")&""' and E <= date '""&TEXT(TODAY()+30,""yyyy-mm-dd"")&""' order by E"",0),""Nada nos próximos 30 dias"")"),"5.17") -> 5.17 | C82: =IFERROR(__xludf.DUMMYFUNCTION("""COMPUTED_VALUE"""),"Fornecimento e instalação de forro de gesso acartonado tipo RU (resistente à umidade – cor verde), fixado em estrutura metálica galvanizada (perfil F530, montantes e guias), com parafusos apropriados, fita telada nas juntas e aplicação de massa para trata"&"mento de emendas. Indicado para áreas úmidas como banheiros e lavabos. Incluso todos os materiais, mão de obra, fixações, nivelamento e limpeza da área. Execução conforme normas técnicas da ABNT e boas práticas de instalação.") -> Fornecimento e instalação de forro de gesso acartonado tipo RU (resistente à umidade – cor verde), fixado em estrutura metálica galvanizada (perfil F530, montantes e guias), com parafusos apropriados, fita telada nas juntas e aplicação de massa para tratamento de emendas. Indicado para áreas úmidas como banheiros e lavabos. Incluso todos os materiais, mão de obra, fixações, nivelamento e limpeza da área. Execução conforme normas técnicas da ABNT e boas práticas de instalação. | D82: =IFERROR(__xludf.DUMMYFUNCTION("""COMPUTED_VALUE"""),"Andar 8") -> Andar 8 | E82: =IFERROR(__xludf.DUMMYFUNCTION("""COMPUTED_VALUE"""),46201.0) -> 46201
B83: =IFERROR(__xludf.DUMMYFUNCTION("""COMPUTED_VALUE"""),"5.4") -> 5.4 | C83: =IFERROR(__xludf.DUMMYFUNCTION("""COMPUTED_VALUE"""),"Caçamba para entulho 4m³") -> Caçamba para entulho 4m³ | D83: =IFERROR(__xludf.DUMMYFUNCTION("""COMPUTED_VALUE"""),"Andar 8") -> Andar 8 | E83: =IFERROR(__xludf.DUMMYFUNCTION("""COMPUTED_VALUE"""),46202.0) -> 46202
B84: =IFERROR(__xludf.DUMMYFUNCTION("""COMPUTED_VALUE"""),"6.34") -> 6.34 | C84: =IFERROR(__xludf.DUMMYFUNCTION("""COMPUTED_VALUE"""),"Execução de impermeabilização em área externa (lajes, sacadas, terraços ou calçadas), incluindo limpeza da base, regularização com argamassa, aplicação de primer e impermeabilizante tipo manta asfáltica com acabamento aluminizado ou cimento polimérico bic"&"omponente, conforme especificação do projeto. Inclui reforço em ralos, cantos e rodapés, teste de estanqueidade e proteção mecânica (argamassa ou contrapiso). Incluso todos os materiais, ferramentas e mão de obra especializada. Execução conforme NBR 9574 "&"e NBR 9575.") -> Execução de impermeabilização em área externa (lajes, sacadas, terraços ou calçadas), incluindo limpeza da base, regularização com argamassa, aplicação de primer e impermeabilizante tipo manta asfáltica com acabamento aluminizado ou cimento polimérico bicomponente, conforme especificação do projeto. Inclui reforço em ralos, cantos e rodapés, teste de estanqueidade e proteção mecânica (argamassa ou contrapiso). Incluso todos os materiais, ferramentas e mão de obra especializada. Execução conforme NBR 9574 e NBR 9575. | D84: =IFERROR(__xludf.DUMMYFUNCTION("""COMPUTED_VALUE"""),"Andar 9") -> Andar 9 | E84: =IFERROR(__xludf.DUMMYFUNCTION("""COMPUTED_VALUE"""),46205.0) -> 46205
B85: =IFERROR(__xludf.DUMMYFUNCTION("""COMPUTED_VALUE"""),"9.5") -> 9.5 | C85: =IFERROR(__xludf.DUMMYFUNCTION("""COMPUTED_VALUE"""),"Desmontagem e montagem Luminária Calha Embutir 2 Lâmpadas LED T8") -> Desmontagem e montagem Luminária Calha Embutir 2 Lâmpadas LED T8 | D85: =IFERROR(__xludf.DUMMYFUNCTION("""COMPUTED_VALUE"""),"Halls - M1/Terreo/M2") -> Halls - M1/Terreo/M2 | E85: =IFERROR(__xludf.DUMMYFUNCTION("""COMPUTED_VALUE"""),46212.0) -> 46212
B86: =IFERROR(__xludf.DUMMYFUNCTION("""COMPUTED_VALUE"""),"12.1") -> 12.1 | C86: =IFERROR(__xludf.DUMMYFUNCTION("""COMPUTED_VALUE"""),"Intervenções nos halls dos elevadores - fase - elevador 2 - 15 andares") -> Intervenções nos halls dos elevadores - fase - elevador 2 - 15 andares | D86: =IFERROR(__xludf.DUMMYFUNCTION("""COMPUTED_VALUE"""),"Elevadores") -> Elevadores | E86: =IFERROR(__xludf.DUMMYFUNCTION("""COMPUTED_VALUE"""),46218.0) -> 46218
B87: =IFERROR(__xludf.DUMMYFUNCTION("""COMPUTED_VALUE"""),"14") -> 14 | C87: =IFERROR(__xludf.DUMMYFUNCTION("""COMPUTED_VALUE"""),"Intervenções nos halls dos elevadores - fase - elevador 3 - 7 andares") -> Intervenções nos halls dos elevadores - fase - elevador 3 - 7 andares | D87: =IFERROR(__xludf.DUMMYFUNCTION("""COMPUTED_VALUE"""),"Elevadores") -> Elevadores | E87: =IFERROR(__xludf.DUMMYFUNCTION("""COMPUTED_VALUE"""),46218.0) -> 46218
B88: =IFERROR(__xludf.DUMMYFUNCTION("""COMPUTED_VALUE"""),"12") -> 12 | C88: =IFERROR(__xludf.DUMMYFUNCTION("""COMPUTED_VALUE"""),"Elevador 2 - 15 andar andares- 8 pessoas") -> Elevador 2 - 15 andar andares- 8 pessoas | D88: =IFERROR(__xludf.DUMMYFUNCTION("""COMPUTED_VALUE"""),"Elevadores") -> Elevadores | E88: =IFERROR(__xludf.DUMMYFUNCTION("""COMPUTED_VALUE"""),46227.0) -> 46227

Sheet Gestao
A1: NICE ENGENHARIA | D1: Plano de Obra - Consulado Geral da Itália
D2: GESTÃO - visão geral por item. Inclui rotina de aditivos.
A4: Total de itens | D4: Atrasados | J4: A iniciar | M4: Finalizados | N4: Avanco da obra
A5: =COUNTA(A8:A201) -> 164 | D5: =COUNTIF(F8:F201,"Atrasado") -> 57 | J5: =COUNTIF(F8:F201,"A iniciar") -> 74 | M5: =COUNTIF($G$8:$G$500,"Finalizado") -> 0 | N5: =IFERROR(SUM(H8:H201)/COUNTA(A8:A201),0) -> 0
A7: Item | B7: Atividade | C7: Andar / Área | D7: Início | E7: Término | F7: Situação | G7: Andamento | H7: % Avanco | I7: Pessoas (status) | J7: Docs (status) | K7: Materiais (status) | L7: Ferramentas (status) | M7: Equipamentos (status) | N7: Observações | O7: Tipo
A8: 1.1 | B8: Gerenciamento técnico de obra - 2 Engenheiros (40h/mês) , assistente tecnico (40h/mês) , mestre de obra (160h/mês) | C8: Preliminares | D8: 46047 | E8: 46073 | F8: =IF(OR($D8="",$E8=""),"Sem data",IF($E8<TODAY(),"Atrasado",IF($D8>TODAY(),"A iniciar","Em andamento"))) -> Atrasado | I8: =IF(COUNTIF(Detalhamento!A9:A329,A8)=0,"-",IF(COUNTIFS(Detalhamento!A9:A329,A8,Detalhamento!J9:J329,"Pendente")>0,"Pendente",IF(COUNTIFS(Detalhamento!A9:A329,A8,Detalhamento!J9:J329,"OK")>0,"OK","-"))) -> - | J8: =IF(COUNTIF(Detalhamento!A9:A329,A8)=0,"-",IF(COUNTIFS(Detalhamento!A9:A329,A8,Detalhamento!K9:K329,"Pendente")>0,"Pendente",IF(COUNTIFS(Detalhamento!A9:A329,A8,Detalhamento!K9:K329,"OK")>0,"OK","-"))) -> - | K8: =IF(COUNTIF(Detalhamento!A9:A329,A8)=0,"-",IF(COUNTIFS(Detalhamento!A9:A329,A8,Detalhamento!L9:L329,"Pendente")>0,"Pendente",IF(COUNTIFS(Detalhamento!A9:A329,A8,Detalhamento!L9:L329,"OK")>0,"OK","-"))) -> - | L8: =IF(COUNTIF(Detalhamento!A9:A329,A8)=0,"-",IF(COUNTIFS(Detalhamento!A9:A329,A8,Detalhamento!M9:M329,"Pendente")>0,"Pendente",IF(COUNTIFS(Detalhamento!A9:A329,A8,Detalhamento!M9:M329,"OK")>0,"OK","-"))) -> - | M8: =IF(COUNTIF(Detalhamento!A9:A329,A8)=0,"-",IF(COUNTIFS(Detalhamento!A9:A329,A8,Detalhamento!N9:N329,"Pendente")>0,"Pendente",IF(COUNTIFS(Detalhamento!A9:A329,A8,Detalhamento!N9:N329,"OK")>0,"OK","-"))) -> - | O8: Original | P8: =IF(A8="",0,COUNTIF(Detalhamento!A9:A329,A8)) -> 0 | Q8: =IF(A8="",0,COUNTIFS(Detalhamento!A9:A329,A8,Detalhamento!H9:H329,"Concluído")) -> 0 | R8: =IFERROR(IF(P8=0,"",Q8/P8),"")
A9: 1.2 | B9: Emissão de ART Obra(Anotação de responsabilidade técnica) | C9: Preliminares | D9: 46050 | E9: 46050 | F9: =IF(OR($D9="",$E9=""),"Sem data",IF($E9<TODAY(),"Atrasado",IF($D9>TODAY(),"A iniciar","Em andamento"))) -> Atrasado | I9: =IF(COUNTIF(Detalhamento!A9:A329,A9)=0,"-",IF(COUNTIFS(Detalhamento!A9:A329,A9,Detalhamento!J9:J329,"Pendente")>0,"Pendente",IF(COUNTIFS(Detalhamento!A9:A329,A9,Detalhamento!J9:J329,"OK")>0,"OK","-"))) -> - | J9: =IF(COUNTIF(Detalhamento!A9:A329,A9)=0,"-",IF(COUNTIFS(Detalhamento!A9:A329,A9,Detalhamento!K9:K329,"Pendente")>0,"Pendente",IF(COUNTIFS(Detalhamento!A9:A329,A9,Detalhamento!K9:K329,"OK")>0,"OK","-"))) -> - | K9: =IF(COUNTIF(Detalhamento!A9:A329,A9)=0,"-",IF(COUNTIFS(Detalhamento!A9:A329,A9,Detalhamento!L9:L329,"Pendente")>0,"Pendente",IF(COUNTIFS(Detalhamento!A9:A329,A9,Detalhamento!L9:L329,"OK")>0,"OK","-"))) -> - | L9: =IF(COUNTIF(Detalhamento!A9:A329,A9)=0,"-",IF(COUNTIFS(Detalhamento!A9:A329,A9,Detalhamento!M9:M329,"Pendente")>0,"Pendente",IF(COUNTIFS(Detalhamento!A9:A329,A9,Detalhamento!M9:M329,"OK")>0,"OK","-"))) -> - | M9: =IF(COUNTIF(Detalhamento!A9:A329,A9)=0,"-",IF(COUNTIFS(Detalhamento!A9:A329,A9,Detalhamento!N9:N329,"Pendente")>0,"Pendente",IF(COUNTIFS(Detalhamento!A9:A329,A9,Detalhamento!N9:N329,"OK")>0,"OK","-"))) -> - | O9: Original | P9: =IF(A9="",0,COUNTIF(Detalhamento!A9:A329,A9)) -> 1 | Q9: =IF(A9="",0,COUNTIFS(Detalhamento!A9:A329,A9,Detalhamento!H9:H329,"Concluído")) -> 1 | R9: =IFERROR(IF(P9=0,"",Q9/P9),"") -> 1
A10: 1.3 | B10: Mobilização de canteiro e equipes e deslocamento | C10: Preliminares | D10: 46050 | E10: 46065 | F10: =IF(OR($D10="",$E10=""),"Sem data",IF($E10<TODAY(),"Atrasado",IF($D10>TODAY(),"A iniciar","Em andamento"))) -> Atrasado | I10: =IF(COUNTIF(Detalhamento!A9:A329,A10)=0,"-",IF(COUNTIFS(Detalhamento!A9:A329,A10,Detalhamento!J9:J329,"Pendente")>0,"Pendente",IF(COUNTIFS(Detalhamento!A9:A329,A10,Detalhamento!J9:J329,"OK")>0,"OK","-"))) -> - | J10: =IF(COUNTIF(Detalhamento!A9:A329,A10)=0,"-",IF(COUNTIFS(Detalhamento!A9:A329,A10,Detalhamento!K9:K329,"Pendente")>0,"Pendente",IF(COUNTIFS(Detalhamento!A9:A329,A10,Detalhamento!K9:K329,"OK")>0,"OK","-"))) -> - | K10: =IF(COUNTIF(Detalhamento!A9:A329,A10)=0,"-",IF(COUNTIFS(Detalhamento!A9:A329,A10,Detalhamento!L9:L329,"Pendente")>0,"Pendente",IF(COUNTIFS(Detalhamento!A9:A329,A10,Detalhamento!L9:L329,"OK")>0,"OK","-"))) -> - | L10: =IF(COUNTIF(Detalhamento!A9:A329,A10)=0,"-",IF(COUNTIFS(Detalhamento!A9:A329,A10,Detalhamento!M9:M329,"Pendente")>0,"Pendente",IF(COUNTIFS(Detalhamento!A9:A329,A10,Detalhamento!M9:M329,"OK")>0,"OK","-"))) -> - | M10: =IF(COUNTIF(Detalhamento!A9:A329,A10)=0,"-",IF(COUNTIFS(Detalhamento!A9:A329,A10,Detalhamento!N9:N329,"Pendente")>0,"Pendente",IF(COUNTIFS(Detalhamento!A9:A329,A10,Detalhamento!N9:N329,"OK")>0,"OK","-"))) -> - | O10: Original | P10: =IF(A10="",0,COUNTIF(Detalhamento!A9:A329,A10)) -> 1 | Q10: =IF(A10="",0,COUNTIFS(Detalhamento!A9:A329,A10,Detalhamento!H9:H329,"Concluído")) -> 0 | R10: =IFERROR(IF(P10=0,"",Q10/P10),"") -> 0
A11: 1.4 | B11: Tapume de vedacao ou protecao, executado com chapas de compensado, tipo chapa resinada ou similar, com 6mm de espessura, exclusive pintura. Proteção chegada elvadores;. | C11: Preliminares | D11: 46050 | E11: 46080 | F11: =IF(OR($D11="",$E11=""),"Sem data",IF($E11<TODAY(),"Atrasado",IF($D11>TODAY(),"A iniciar","Em andamento"))) -> Atrasado | I11: =IF(COUNTIF(Detalhamento!A9:A329,A11)=0,"-",IF(COUNTIFS(Detalhamento!A9:A329,A11,Detalhamento!J9:J329,"Pendente")>0,"Pendente",IF(COUNTIFS(Detalhamento!A9:A329,A11,Detalhamento!J9:J329,"OK")>0,"OK","-"))) -> - | J11: =IF(COUNTIF(Detalhamento!A9:A329,A11)=0,"-",IF(COUNTIFS(Detalhamento!A9:A329,A11,Detalhamento!K9:K329,"Pendente")>0,"Pendente",IF(COUNTIFS(Detalhamento!A9:A329,A11,Detalhamento!K9:K329,"OK")>0,"OK","-"))) -> - | K11: =IF(COUNTIF(Detalhamento!A9:A329,A11)=0,"-",IF(COUNTIFS(Detalhamento!A9:A329,A11,Detalhamento!L9:L329,"Pendente")>0,"Pendente",IF(COUNTIFS(Detalhamento!A9:A329,A11,Detalhamento!L9:L329,"OK")>0,"OK","-"))) -> - | L11: =IF(COUNTIF(Detalhamento!A9:A329,A11)=0,"-",IF(COUNTIFS(Detalhamento!A9:A329,A11,Detalhamento!M9:M329,"Pendente")>0,"Pendente",IF(COUNTIFS(Detalhamento!A9:A329,A11,Detalhamento!M9:M329,"OK")>0,"OK","-"))) -> - | M11: =IF(COUNTIF(Detalhamento!A9:A329,A11)=0,"-",IF(COUNTIFS(Detalhamento!A9:A329,A11,Detalhamento!N9:N329,"Pendente")>0,"Pendente",IF(COUNTIFS(Detalhamento!A9:A329,A11,Detalhamento!N9:N329,"OK")>0,"OK","-"))) -> - | O11: Original | P11: =IF(A11="",0,COUNTIF(Detalhamento!A9:A329,A11)) -> 1 | Q11: =IF(A11="",0,COUNTIFS(Detalhamento!A9:A329,A11,Detalhamento!H9:H329,"Concluído")) -> 0 | R11: =IFERROR(IF(P11=0,"",Q11/P11),"") -> 0
A12: 1.5 | B12: Limpeza permanente de obra | C12: Preliminares | D12: 46047 | E12: 46408 | F12: =IF(OR($D12="",$E12=""),"Sem data",IF($E12<TODAY(),"Atrasado",IF($D12>TODAY(),"A iniciar","Em andamento"))) -> Em andamento | I12: =IF(COUNTIF(Detalhamento!A9:A329,A12)=0,"-",IF(COUNTIFS(Detalhamento!A9:A329,A12,Detalhamento!J9:J329,"Pendente")>0,"Pendente",IF(COUNTIFS(Detalhamento!A9:A329,A12,Detalhamento!J9:J329,"OK")>0,"OK","-"))) -> - | J12: =IF(COUNTIF(Detalhamento!A9:A329,A12)=0,"-",IF(COUNTIFS(Detalhamento!A9:A329,A12,Detalhamento!K9:K329,"Pendente")>0,"Pendente",IF(COUNTIFS(Detalhamento!A9:A329,A12,Detalhamento!K9:K329,"OK")>0,"OK","-"))) -> - | K12: =IF(COUNTIF(Detalhamento!A9:A329,A12)=0,"-",IF(COUNTIFS(Detalhamento!A9:A329,A12,Detalhamento!L9:L329,"Pendente")>0,"Pendente",IF(COUNTIFS(Detalhamento!A9:A329,A12,Detalhamento!L9:L329,"OK")>0,"OK","-"))) -> - | L12: =IF(COUNTIF(Detalhamento!A9:A329,A12)=0,"-",IF(COUNTIFS(Detalhamento!A9:A329,A12,Detalhamento!M9:M329,"Pendente")>0,"Pendente",IF(COUNTIFS(Detalhamento!A9:A329,A12,Detalhamento!M9:M329,"OK")>0,"OK","-"))) -> - | M12: =IF(COUNTIF(Detalhamento!A9:A329,A12)=0,"-",IF(COUNTIFS(Detalhamento!A9:A329,A12,Detalhamento!N9:N329,"Pendente")>0,"Pendente",IF(COUNTIFS(Detalhamento!A9:A329,A12,Detalhamento!N9:N329,"OK")>0,"OK","-"))) -> - | O12: Original | P12: =IF(A12="",0,COUNTIF(Detalhamento!A9:A329,A12)) -> 1 | Q12: =IF(A12="",0,COUNTIFS(Detalhamento!A9:A329,A12,Detalhamento!H9:H329,"Concluído")) -> 0 | R12: =IFERROR(IF(P12=0,"",Q12/P12),"") -> 0
A13: 2.1 | B13: Demolicão manual de alvenaria de tijolos furados, contrapiso de 5 cm no deposito 5, inclusive empilhamento dentro do canteiro de servico. | C13: Elevadores | D13: 46117 | E13: 46166 | F13: =IF(OR($D13="",$E13=""),"Sem data",IF($E13<TODAY(),"Atrasado",IF($D13>TODAY(),"A iniciar","Em andamento"))) -> Atrasado | I13: =IF(COUNTIF(Detalhamento!A9:A329,A13)=0,"-",IF(COUNTIFS(Detalhamento!A9:A329,A13,Detalhamento!J9:J329,"Pendente")>0,"Pendente",IF(COUNTIFS(Detalhamento!A9:A329,A13,Detalhamento!J9:J329,"OK")>0,"OK","-"))) -> - | J13: =IF(COUNTIF(Detalhamento!A9:A329,A13)=0,"-",IF(COUNTIFS(Detalhamento!A9:A329,A13,Detalhamento!K9:K329,"Pendente")>0,"Pendente",IF(COUNTIFS(Detalhamento!A9:A329,A13,Detalhamento!K9:K329,"OK")>0,"OK","-"))) -> - | K13: =IF(COUNTIF(Detalhamento!A9:A329,A13)=0,"-",IF(COUNTIFS(Detalhamento!A9:A329,A13,Detalhamento!L9:L329,"Pendente")>0,"Pendente",IF(COUNTIFS(Detalhamento!A9:A329,A13,Detalhamento!L9:L329,"OK")>0,"OK","-"))) -> - | L13: =IF(COUNTIF(Detalhamento!A9:A329,A13)=0,"-",IF(COUNTIFS(Detalhamento!A9:A329,A13,Detalhamento!M9:M329,"Pendente")>0,"Pendente",IF(COUNTIFS(Detalhamento!A9:A329,A13,Detalhamento!M9:M329,"OK")>0,"OK","-"))) -> - | M13: =IF(COUNTIF(Detalhamento!A9:A329,A13)=0,"-",IF(COUNTIFS(Detalhamento!A9:A329,A13,Detalhamento!N9:N329,"Pendente")>0,"Pendente",IF(COUNTIFS(Detalhamento!A9:A329,A13,Detalhamento!N9:N329,"OK")>0,"OK","-"))) -> - | O13: Original | P13: =IF(A13="",0,COUNTIF(Detalhamento!A9:A329,A13)) -> 7 | Q13: =IF(A13="",0,COUNTIFS(Detalhamento!A9:A329,A13,Detalhamento!H9:H329,"Concluído")) -> 0 | R13: =IFERROR(IF(P13=0,"",Q13/P13),"") -> 0
A14: 2.2 | B14: Demolição controlada e monitrada para rebaixamento da laje e abertura na laje superior e dos vãos de portas nos andares | C14: Elevadores | D14: 46117 | E14: 46240 | F14: =IF(OR($D14="",$E14=""),"Sem data",IF($E14<TODAY(),"Atrasado",IF($D14>TODAY(),"A iniciar","Em andamento"))) -> Em andamento | I14: =IF(COUNTIF(Detalhamento!A9:A329,A14)=0,"-",IF(COUNTIFS(Detalhamento!A9:A329,A14,Detalhamento!J9:J329,"Pendente")>0,"Pendente",IF(COUNTIFS(Detalhamento!A9:A329,A14,Detalhamento!J9:J329,"OK")>0,"OK","-"))) -> - | J14: =IF(COUNTIF(Detalhamento!A9:A329,A14)=0,"-",IF(COUNTIFS(Detalhamento!A9:A329,A14,Detalhamento!K9:K329,"Pendente")>0,"Pendente",IF(COUNTIFS(Detalhamento!A9:A329,A14,Detalhamento!K9:K329,"OK")>0,"OK","-"))) -> - | K14: =IF(COUNTIF(Detalhamento!A9:A329,A14)=0,"-",IF(COUNTIFS(Detalhamento!A9:A329,A14,Detalhamento!L9:L329,"Pendente")>0,"Pendente",IF(COUNTIFS(Detalhamento!A9:A329,A14,Detalhamento!L9:L329,"OK")>0,"OK","-"))) -> - | L14: =IF(COUNTIF(Detalhamento!A9:A329,A14)=0,"-",IF(COUNTIFS(Detalhamento!A9:A329,A14,Detalhamento!M9:M329,"Pendente")>0,"Pendente",IF(COUNTIFS(Detalhamento!A9:A329,A14,Detalhamento!M9:M329,"OK")>0,"OK","-"))) -> - | M14: =IF(COUNTIF(Detalhamento!A9:A329,A14)=0,"-",IF(COUNTIFS(Detalhamento!A9:A329,A14,Detalhamento!N9:N329,"Pendente")>0,"Pendente",IF(COUNTIFS(Detalhamento!A9:A329,A14,Detalhamento!N9:N329,"OK")>0,"OK","-"))) -> - | O14: Original | P14: =IF(A14="",0,COUNTIF(Detalhamento!A9:A329,A14)) -> 8 | Q14: =IF(A14="",0,COUNTIFS(Detalhamento!A9:A329,A14,Detalhamento!H9:H329,"Concluído")) -> 0 | R14: =IFERROR(IF(P14=0,"",Q14/P14),"") -> 0
A15: 2.3 | B15: Caçamba para entulho 4m³ | C15: Elevadores | D15: 46117 | E15: 46166 | F15: =IF(OR($D15="",$E15=""),"Sem data",IF($E15<TODAY(),"Atrasado",IF($D15>TODAY(),"A iniciar","Em andamento"))) -> Atrasado | I15: =IF(COUNTIF(Detalhamento!A9:A329,A15)=0,"-",IF(COUNTIFS(Detalhamento!A9:A329,A15,Detalhamento!J9:J329,"Pendente")>0,"Pendente",IF(COUNTIFS(Detalhamento!A9:A329,A15,Detalhamento!J9:J329,"OK")>0,"OK","-"))) -> - | J15: =IF(COUNTIF(Detalhamento!A9:A329,A15)=0,"-",IF(COUNTIFS(Detalhamento!A9:A329,A15,Detalhamento!K9:K329,"Pendente")>0,"Pendente",IF(COUNTIFS(Detalhamento!A9:A329,A15,Detalhamento!K9:K329,"OK")>0,"OK","-"))) -> - | K15: =IF(COUNTIF(Detalhamento!A9:A329,A15)=0,"-",IF(COUNTIFS(Detalhamento!A9:A329,A15,Detalhamento!L9:L329,"Pendente")>0,"Pendente",IF(COUNTIFS(Detalhamento!A9:A329,A15,Detalhamento!L9:L329,"OK")>0,"OK","-"))) -> - | L15: =IF(COUNTIF(Detalhamento!A9:A329,A15)=0,"-",IF(COUNTIFS(Detalhamento!A9:A329,A15,Detalhamento!M9:M329,"Pendente")>0,"Pendente",IF(COUNTIFS(Detalhamento!A9:A329,A15,Detalhamento!M9:M329,"OK")>0,"OK","-"))) -> - | M15: =IF(COUNTIF(Detalhamento!A9:A329,A15)=0,"-",IF(COUNTIFS(Detalhamento!A9:A329,A15,Detalhamento!N9:N329,"Pendente")>0,"Pendente",IF(COUNTIFS(Detalhamento!A9:A329,A15,Detalhamento!N9:N329,"OK")>0,"OK","-"))) -> - | O15: Original | P15: =IF(A15="",0,COUNTIF(Detalhamento!A9:A329,A15)) -> 5 | Q15: =IF(A15="",0,COUNTIFS(Detalhamento!A9:A329,A15,Detalhamento!H9:H329,"Concluído")) -> 0 | R15: =IFERROR(IF(P15=0,"",Q15/P15),"") -> 0
A16: 2.4 | B16: Transporte de entulho e grades | C16: Elevadores | D16: 46117 | E16: 46166 | F16: =IF(OR($D16="",$E16=""),"Sem data",IF($E16<TODAY(),"Atrasado",IF($D16>TODAY(),"A iniciar","Em andamento"))) -> Atrasado | I16: =IF(COUNTIF(Detalhamento!A9:A329,A16)=0,"-",IF(COUNTIFS(Detalhamento!A9:A329,A16,Detalhamento!J9:J329,"Pendente")>0,"Pendente",IF(COUNTIFS(Detalhamento!A9:A329,A16,Detalhamento!J9:J329,"OK")>0,"OK","-"))) -> - | J16: =IF(COUNTIF(Detalhamento!A9:A329,A16)=0,"-",IF(COUNTIFS(Detalhamento!A9:A329,A16,Detalhamento!K9:K329,"Pendente")>0,"Pendente",IF(COUNTIFS(Detalhamento!A9:A329,A16,Detalhamento!K9:K329,"OK")>0,"OK","-"))) -> - | K16: =IF(COUNTIF(Detalhamento!A9:A329,A16)=0,"-",IF(COUNTIFS(Detalhamento!A9:A329,A16,Detalhamento!L9:L329,"Pendente")>0,"Pendente",IF(COUNTIFS(Detalhamento!A9:A329,A16,Detalhamento!L9:L329,"OK")>0,"OK","-"))) -> - | L16: =IF(COUNTIF(Detalhamento!A9:A329,A16)=0,"-",IF(COUNTIFS(Detalhamento!A9:A329,A16,Detalhamento!M9:M329,"Pendente")>0,"Pendente",IF(COUNTIFS(Detalhamento!A9:A329,A16,Detalhamento!M9:M329,"OK")>0,"OK","-"))) -> - | M16: =IF(COUNTIF(Detalhamento!A9:A329,A16)=0,"-",IF(COUNTIFS(Detalhamento!A9:A329,A16,Detalhamento!N9:N329,"Pendente")>0,"Pendente",IF(COUNTIFS(Detalhamento!A9:A329,A16,Detalhamento!N9:N329,"OK")>0,"OK","-"))) -> - | O16: Original | P16: =IF(A16="",0,COUNTIF(Detalhamento!A9:A329,A16)) -> 5 | Q16: =IF(A16="",0,COUNTIFS(Detalhamento!A9:A329,A16,Detalhamento!H9:H329,"Concluído")) -> 0 | R16: =IFERROR(IF(P16=0,"",Q16/P16),"") -> 0
A17: 2.5 | B17: Caçamba para entulho 4m³ | C17: Elevadores | D17: 46169 | E17: 46243 | F17: =IF(OR($D17="",$E17=""),"Sem data",IF($E17<TODAY(),"Atrasado",IF($D17>TODAY(),"A iniciar","Em andamento"))) -> Em andamento | I17: =IF(COUNTIF(Detalhamento!A9:A329,A17)=0,"-",IF(COUNTIFS(Detalhamento!A9:A329,A17,Detalhamento!J9:J329,"Pendente")>0,"Pendente",IF(COUNTIFS(Detalhamento!A9:A329,A17,Detalhamento!J9:J329,"OK")>0,"OK","-"))) -> - | J17: =IF(COUNTIF(Detalhamento!A9:A329,A17)=0,"-",IF(COUNTIFS(Detalhamento!A9:A329,A17,Detalhamento!K9:K329,"Pendente")>0,"Pendente",IF(COUNTIFS(Detalhamento!A9:A329,A17,Detalhamento!K9:K329,"OK")>0,"OK","-"))) -> - | K17: =IF(COUNTIF(Detalhamento!A9:A329,A17)=0,"-",IF(COUNTIFS(Detalhamento!A9:A329,A17,Detalhamento!L9:L329,"Pendente")>0,"Pendente",IF(COUNTIFS(Detalhamento!A9:A329,A17,Detalhamento!L9:L329,"OK")>0,"OK","-"))) -> - | L17: =IF(COUNTIF(Detalhamento!A9:A329,A17)=0,"-",IF(COUNTIFS(Detalhamento!A9:A329,A17,Detalhamento!M9:M329,"Pendente")>0,"Pendente",IF(COUNTIFS(Detalhamento!A9:A329,A17,Detalhamento!M9:M329,"OK")>0,"OK","-"))) -> - | M17: =IF(COUNTIF(Detalhamento!A9:A329,A17)=0,"-",IF(COUNTIFS(Detalhamento!A9:A329,A17,Detalhamento!N9:N329,"Pendente")>0,"Pendente",IF(COUNTIFS(Detalhamento!A9:A329,A17,Detalhamento!N9:N329,"OK")>0,"OK","-"))) -> - | O17: Original | P17: =IF(A17="",0,COUNTIF(Detalhamento!A9:A329,A17)) -> 5 | Q17: =IF(A17="",0,COUNTIFS(Detalhamento!A9:A329,A17,Detalhamento!H9:H329,"Concluído")) -> 0 | R17: =IFERROR(IF(P17=0,"",Q17/P17),"") -> 0
A18: 2.6 | B18: Transporte de entulho | C18: Elevadores | D18: 46169 | E18: 46243 | F18: =IF(OR($D18="",$E18=""),"Sem data",IF($E18<TODAY(),"Atrasado",IF($D18>TODAY(),"A iniciar","Em andamento"))) -> Em andamento | I18: =IF(COUNTIF(Detalhamento!A9:A329,A18)=0,"-",IF(COUNTIFS(Detalhamento!A9:A329,A18,Detalhamento!J9:J329,"Pendente")>0,"Pendente",IF(COUNTIFS(Detalhamento!A9:A329,A18,Detalhamento!J9:J329,"OK")>0,"OK","-"))) -> - | J18: =IF(COUNTIF(Detalhamento!A9:A329,A18)=0,"-",IF(COUNTIFS(Detalhamento!A9:A329,A18,Detalhamento!K9:K329,"Pendente")>0,"Pendente",IF(COUNTIFS(Detalhamento!A9:A329,A18,Detalhamento!K9:K329,"OK")>0,"OK","-"))) -> - | K18: =IF(COUNTIF(Detalhamento!A9:A329,A18)=0,"-",IF(COUNTIFS(Detalhamento!A9:A329,A18,Detalhamento!L9:L329,"Pendente")>0,"Pendente",IF(COUNTIFS(Detalhamento!A9:A329,A18,Detalhamento!L9:L329,"OK")>0,"OK","-"))) -> - | L18: =IF(COUNTIF(Detalhamento!A9:A329,A18)=0,"-",IF(COUNTIFS(Detalhamento!A9:A329,A18,Detalhamento!M9:M329,"Pendente")>0,"Pendente",IF(COUNTIFS(Detalhamento!A9:A329,A18,Detalhamento!M9:M329,"OK")>0,"OK","-"))) -> - | M18: =IF(COUNTIF(Detalhamento!A9:A329,A18)=0,"-",IF(COUNTIFS(Detalhamento!A9:A329,A18,Detalhamento!N9:N329,"Pendente")>0,"Pendente",IF(COUNTIFS(Detalhamento!A9:A329,A18,Detalhamento!N9:N329,"OK")>0,"OK","-"))) -> - | O18: Original | P18: =IF(A18="",0,COUNTIF(Detalhamento!A9:A329,A18)) -> 3 | Q18: =IF(A18="",0,COUNTIFS(Detalhamento!A9:A329,A18,Detalhamento!H9:H329,"Concluído")) -> 0 | R18: =IFERROR(IF(P18=0,"",Q18/P18),"") -> 0
A19: 2.7 | B19: Montagem e desmontagem de andaime direcional estrutural com chumbadores e plataforma | C19: Elevadores | D19: 46145 | E19: 46191 | F19: =IF(OR($D19="",$E19=""),"Sem data",IF($E19<TODAY(),"Atrasado",IF($D19>TODAY(),"A iniciar","Em andamento"))) -> Atrasado | I19: =IF(COUNTIF(Detalhamento!A9:A329,A19)=0,"-",IF(COUNTIFS(Detalhamento!A9:A329,A19,Detalhamento!J9:J329,"Pendente")>0,"Pendente",IF(COUNTIFS(Detalhamento!A9:A329,A19,Detalhamento!J9:J329,"OK")>0,"OK","-"))) -> - | J19: =IF(COUNTIF(Detalhamento!A9:A329,A19)=0,"-",IF(COUNTIFS(Detalhamento!A9:A329,A19,Detalhamento!K9:K329,"Pendente")>0,"Pendente",IF(COUNTIFS(Detalhamento!A9:A329,A19,Detalhamento!K9:K329,"OK")>0,"OK","-"))) -> - | K19: =IF(COUNTIF(Detalhamento!A9:A329,A19)=0,"-",IF(COUNTIFS(Detalhamento!A9:A329,A19,Detalhamento!L9:L329,"Pendente")>0,"Pendente",IF(COUNTIFS(Detalhamento!A9:A329,A19,Detalhamento!L9:L329,"OK")>0,"OK","-"))) -> - | L19: =IF(COUNTIF(Detalhamento!A9:A329,A19)=0,"-",IF(COUNTIFS(Detalhamento!A9:A329,A19,Detalhamento!M9:M329,"Pendente")>0,"Pendente",IF(COUNTIFS(Detalhamento!A9:A329,A19,Detalhamento!M9:M329,"OK")>0,"OK","-"))) -> - | M19: =IF(COUNTIF(Detalhamento!A9:A329,A19)=0,"-",IF(COUNTIFS(Detalhamento!A9:A329,A19,Detalhamento!N9:N329,"Pendente")>0,"Pendente",IF(COUNTIFS(Detalhamento!A9:A329,A19,Detalhamento!N9:N329,"OK")>0,"OK","-"))) -> - | O19: Original | P19: =IF(A19="",0,COUNTIF(Detalhamento!A9:A329,A19)) -> 7 | Q19: =IF(A19="",0,COUNTIFS(Detalhamento!A9:A329,A19,Detalhamento!H9:H329,"Concluído")) -> 0 | R19: =IFERROR(IF(P19=0,"",Q19/P19),"") -> 0
A20: 3.1 | B20: Construção do prolongamento da caixa do elevador | C20: Elevadores | D20: 46243 | E20: 46261 | F20: =IF(OR($D20="",$E20=""),"Sem data",IF($E20<TODAY(),"Atrasado",IF($D20>TODAY(),"A iniciar","Em andamento"))) -> A iniciar | I20: =IF(COUNTIF(Detalhamento!A9:A329,A20)=0,"-",IF(COUNTIFS(Detalhamento!A9:A329,A20,Detalhamento!J9:J329,"Pendente")>0,"Pendente",IF(COUNTIFS(Detalhamento!A9:A329,A20,Detalhamento!J9:J329,"OK")>0,"OK","-"))) -> - | J20: =IF(COUNTIF(Detalhamento!A9:A329,A20)=0,"-",IF(COUNTIFS(Detalhamento!A9:A329,A20,Detalhamento!K9:K329,"Pendente")>0,"Pendente",IF(COUNTIFS(Detalhamento!A9:A329,A20,Detalhamento!K9:K329,"OK")>0,"OK","-"))) -> - | K20: =IF(COUNTIF(Detalhamento!A9:A329,A20)=0,"-",IF(COUNTIFS(Detalhamento!A9:A329,A20,Detalhamento!L9:L329,"Pendente")>0,"Pendente",IF(COUNTIFS(Detalhamento!A9:A329,A20,Detalhamento!L9:L329,"OK")>0,"OK","-"))) -> - | L20: =IF(COUNTIF(Detalhamento!A9:A329,A20)=0,"-",IF(COUNTIFS(Detalhamento!A9:A329,A20,Detalhamento!M9:M329,"Pendente")>0,"Pendente",IF(COUNTIFS(Detalhamento!A9:A329,A20,Detalhamento!M9:M329,"OK")>0,"OK","-"))) -> - | M20: =IF(COUNTIF(Detalhamento!A9:A329,A20)=0,"-",IF(COUNTIFS(Detalhamento!A9:A329,A20,Detalhamento!N9:N329,"Pendente")>0,"Pendente",IF(COUNTIFS(Detalhamento!A9:A329,A20,Detalhamento!N9:N329,"OK")>0,"OK","-"))) -> - | O20: Original | P20: =IF(A20="",0,COUNTIF(Detalhamento!A9:A329,A20)) -> 5 | Q20: =IF(A20="",0,COUNTIFS(Detalhamento!A9:A329,A20,Detalhamento!H9:H329,"Concluído")) -> 0 | R20: =IFERROR(IF(P20=0,"",Q20/P20),"") -> 0
A21: 3.2 | B21: Construção da laje de cobertura da torre com Alça para içamento do pistão | C21: Elevadores | D21: 46278 | E21: 46289 | F21: =IF(OR($D21="",$E21=""),"Sem data",IF($E21<TODAY(),"Atrasado",IF($D21>TODAY(),"A iniciar","Em andamento"))) -> A iniciar | I21: =IF(COUNTIF(Detalhamento!A9:A329,A21)=0,"-",IF(COUNTIFS(Detalhamento!A9:A329,A21,Detalhamento!J9:J329,"Pendente")>0,"Pendente",IF(COUNTIFS(Detalhamento!A9:A329,A21,Detalhamento!J9:J329,"OK")>0,"OK","-"))) -> - | J21: =IF(COUNTIF(Detalhamento!A9:A329,A21)=0,"-",IF(COUNTIFS(Detalhamento!A9:A329,A21,Detalhamento!K9:K329,"Pendente")>0,"Pendente",IF(COUNTIFS(Detalhamento!A9:A329,A21,Detalhamento!K9:K329,"OK")>0,"OK","-"))) -> - | K21: =IF(COUNTIF(Detalhamento!A9:A329,A21)=0,"-",IF(COUNTIFS(Detalhamento!A9:A329,A21,Detalhamento!L9:L329,"Pendente")>0,"Pendente",IF(COUNTIFS(Detalhamento!A9:A329,A21,Detalhamento!L9:L329,"OK")>0,"OK","-"))) -> - | L21: =IF(COUNTIF(Detalhamento!A9:A329,A21)=0,"-",IF(COUNTIFS(Detalhamento!A9:A329,A21,Detalhamento!M9:M329,"Pendente")>0,"Pendente",IF(COUNTIFS(Detalhamento!A9:A329,A21,Detalhamento!M9:M329,"OK")>0,"OK","-"))) -> - | M21: =IF(COUNTIF(Detalhamento!A9:A329,A21)=0,"-",IF(COUNTIFS(Detalhamento!A9:A329,A21,Detalhamento!N9:N329,"Pendente")>0,"Pendente",IF(COUNTIFS(Detalhamento!A9:A329,A21,Detalhamento!N9:N329,"OK")>0,"OK","-"))) -> - | O21: Original | P21: =IF(A21="",0,COUNTIF(Detalhamento!A9:A329,A21)) -> 6 | Q21: =IF(A21="",0,COUNTIFS(Detalhamento!A9:A329,A21,Detalhamento!H9:H329,"Concluído")) -> 0 | R21: =IFERROR(IF(P21=0,"",Q21/P21),"") -> 0
A22: 3.3 | B22: Cintas intermediárias em todos os andares | C22: Elevadores | D22: 46145 | E22: 46345 | F22: =IF(OR($D22="",$E22=""),"Sem data",IF($E22<TODAY(),"Atrasado",IF($D22>TODAY(),"A iniciar","Em andamento"))) -> Em andamento | I22: =IF(COUNTIF(Detalhamento!A9:A329,A22)=0,"-",IF(COUNTIFS(Detalhamento!A9:A329,A22,Detalhamento!J9:J329,"Pendente")>0,"Pendente",IF(COUNTIFS(Detalhamento!A9:A329,A22,Detalhamento!J9:J329,"OK")>0,"OK","-"))) -> - | J22: =IF(COUNTIF(Detalhamento!A9:A329,A22)=0,"-",IF(COUNTIFS(Detalhamento!A9:A329,A22,Detalhamento!K9:K329,"Pendente")>0,"Pendente",IF(COUNTIFS(Detalhamento!A9:A329,A22,Detalhamento!K9:K329,"OK")>0,"OK","-"))) -> - | K22: =IF(COUNTIF(Detalhamento!A9:A329,A22)=0,"-",IF(COUNTIFS(Detalhamento!A9:A329,A22,Detalhamento!L9:L329,"Pendente")>0,"Pendente",IF(COUNTIFS(Detalhamento!A9:A329,A22,Detalhamento!L9:L329,"OK")>0,"OK","-"))) -> - | L22: =IF(COUNTIF(Detalhamento!A9:A329,A22)=0,"-",IF(COUNTIFS(Detalhamento!A9:A329,A22,Detalhamento!M9:M329,"Pendente")>0,"Pendente",IF(COUNTIFS(Detalhamento!A9:A329,A22,Detalhamento!M9:M329,"OK")>0,"OK","-"))) -> - | M22: =IF(COUNTIF(Detalhamento!A9:A329,A22)=0,"-",IF(COUNTIFS(Detalhamento!A9:A329,A22,Detalhamento!N9:N329,"Pendente")>0,"Pendente",IF(COUNTIFS(Detalhamento!A9:A329,A22,Detalhamento!N9:N329,"OK")>0,"OK","-"))) -> - | O22: Original | P22: =IF(A22="",0,COUNTIF(Detalhamento!A9:A329,A22)) -> 5 | Q22: =IF(A22="",0,COUNTIFS(Detalhamento!A9:A329,A22,Detalhamento!H9:H329,"Concluído")) -> 0 | R22: =IFERROR(IF(P22=0,"",Q22/P22),"") -> 0
A23: 3.4 | B23: Fechamento das laterais e fundos em alvenaria no prolongamento da torre | C23: Elevadores | D23: 46251 | E23: 46268 | F23: =IF(OR($D23="",$E23=""),"Sem data",IF($E23<TODAY(),"Atrasado",IF($D23>TODAY(),"A iniciar","Em andamento"))) -> A iniciar | I23: =IF(COUNTIF(Detalhamento!A9:A329,A23)=0,"-",IF(COUNTIFS(Detalhamento!A9:A329,A23,Detalhamento!J9:J329,"Pendente")>0,"Pendente",IF(COUNTIFS(Detalhamento!A9:A329,A23,Detalhamento!J9:J329,"OK")>0,"OK","-"))) -> - | J23: =IF(COUNTIF(Detalhamento!A9:A329,A23)=0,"-",IF(COUNTIFS(Detalhamento!A9:A329,A23,Detalhamento!K9:K329,"Pendente")>0,"Pendente",IF(COUNTIFS(Detalhamento!A9:A329,A23,Detalhamento!K9:K329,"OK")>0,"OK","-"))) -> - | K23: =IF(COUNTIF(Detalhamento!A9:A329,A23)=0,"-",IF(COUNTIFS(Detalhamento!A9:A329,A23,Detalhamento!L9:L329,"Pendente")>0,"Pendente",IF(COUNTIFS(Detalhamento!A9:A329,A23,Detalhamento!L9:L329,"OK")>0,"OK","-"))) -> - | L23: =IF(COUNTIF(Detalhamento!A9:A329,A23)=0,"-",IF(COUNTIFS(Detalhamento!A9:A329,A23,Detalhamento!M9:M329,"Pendente")>0,"Pendente",IF(COUNTIFS(Detalhamento!A9:A329,A23,Detalhamento!M9:M329,"OK")>0,"OK","-"))) -> - | M23: =IF(COUNTIF(Detalhamento!A9:A329,A23)=0,"-",IF(COUNTIFS(Detalhamento!A9:A329,A23,Detalhamento!N9:N329,"Pendente")>0,"Pendente",IF(COUNTIFS(Detalhamento!A9:A329,A23,Detalhamento!N9:N329,"OK")>0,"OK","-"))) -> - | O23: Original | P23: =IF(A23="",0,COUNTIF(Detalhamento!A9:A329,A23)) -> 4 | Q23: =IF(A23="",0,COUNTIFS(Detalhamento!A9:A329,A23,Detalhamento!H9:H329,"Concluído")) -> 0 | R23: =IFERROR(IF(P23=0,"",Q23/P23),"") -> 0
A24: 3.5 | B24: Rebocamento no prolongamento da torre | C24: Elevadores | D24: 46254 | E24: 46275 | F24: =IF(OR($D24="",$E24=""),"Sem data",IF($E24<TODAY(),"Atrasado",IF($D24>TODAY(),"A iniciar","Em andamento"))) -> A iniciar | I24: =IF(COUNTIF(Detalhamento!A9:A329,A24)=0,"-",IF(COUNTIFS(Detalhamento!A9:A329,A24,Detalhamento!J9:J329,"Pendente")>0,"Pendente",IF(COUNTIFS(Detalhamento!A9:A329,A24,Detalhamento!J9:J329,"OK")>0,"OK","-"))) -> - | J24: =IF(COUNTIF(Detalhamento!A9:A329,A24)=0,"-",IF(COUNTIFS(Detalhamento!A9:A329,A24,Detalhamento!K9:K329,"Pendente")>0,"Pendente",IF(COUNTIFS(Detalhamento!A9:A329,A24,Detalhamento!K9:K329,"OK")>0,"OK","-"))) -> - | K24: =IF(COUNTIF(Detalhamento!A9:A329,A24)=0,"-",IF(COUNTIFS(Detalhamento!A9:A329,A24,Detalhamento!L9:L329,"Pendente")>0,"Pendente",IF(COUNTIFS(Detalhamento!A9:A329,A24,Detalhamento!L9:L329,"OK")>0,"OK","-"))) -> - | L24: =IF(COUNTIF(Detalhamento!A9:A329,A24)=0,"-",IF(COUNTIFS(Detalhamento!A9:A329,A24,Detalhamento!M9:M329,"Pendente")>0,"Pendente",IF(COUNTIFS(Detalhamento!A9:A329,A24,Detalhamento!M9:M329,"OK")>0,"OK","-"))) -> - | M24: =IF(COUNTIF(Detalhamento!A9:A329,A24)=0,"-",IF(COUNTIFS(Detalhamento!A9:A329,A24,Detalhamento!N9:N329,"Pendente")>0,"Pendente",IF(COUNTIFS(Detalhamento!A9:A329,A24,Detalhamento!N9:N329,"OK")>0,"OK","-"))) -> - | O24: Original | P24: =IF(A24="",0,COUNTIF(Detalhamento!A9:A329,A24)) -> 6 | Q24: =IF(A24="",0,COUNTIFS(Detalhamento!A9:A329,A24,Detalhamento!H9:H329,"Concluído")) -> 0 | R24: =IFERROR(IF(P24=0,"",Q24/P24),"") -> 0
A25: 3.6 | B25: Pintura de cor clara em toda a parte interna da torre do elevador | C25: Elevadores | D25: 46278 | E25: 46282 | F25: =IF(OR($D25="",$E25=""),"Sem data",IF($E25<TODAY(),"Atrasado",IF($D25>TODAY(),"A iniciar","Em andamento"))) -> A iniciar | I25: =IF(COUNTIF(Detalhamento!A9:A329,A25)=0,"-",IF(COUNTIFS(Detalhamento!A9:A329,A25,Detalhamento!J9:J329,"Pendente")>0,"Pendente",IF(COUNTIFS(Detalhamento!A9:A329,A25,Detalhamento!J9:J329,"OK")>0,"OK","-"))) -> - | J25: =IF(COUNTIF(Detalhamento!A9:A329,A25)=0,"-",IF(COUNTIFS(Detalhamento!A9:A329,A25,Detalhamento!K9:K329,"Pendente")>0,"Pendente",IF(COUNTIFS(Detalhamento!A9:A329,A25,Detalhamento!K9:K329,"OK")>0,"OK","-"))) -> - | K25: =IF(COUNTIF(Detalhamento!A9:A329,A25)=0,"-",IF(COUNTIFS(Detalhamento!A9:A329,A25,Detalhamento!L9:L329,"Pendente")>0,"Pendente",IF(COUNTIFS(Detalhamento!A9:A329,A25,Detalhamento!L9:L329,"OK")>0,"OK","-"))) -> - | L25: =IF(COUNTIF(Detalhamento!A9:A329,A25)=0,"-",IF(COUNTIFS(Detalhamento!A9:A329,A25,Detalhamento!M9:M329,"Pendente")>0,"Pendente",IF(COUNTIFS(Detalhamento!A9:A329,A25,Detalhamento!M9:M329,"OK")>0,"OK","-"))) -> - | M25: =IF(COUNTIF(Detalhamento!A9:A329,A25)=0,"-",IF(COUNTIFS(Detalhamento!A9:A329,A25,Detalhamento!N9:N329,"Pendente")>0,"Pendente",IF(COUNTIFS(Detalhamento!A9:A329,A25,Detalhamento!N9:N329,"OK")>0,"OK","-"))) -> - | O25: Original | P25: =IF(A25="",0,COUNTIF(Detalhamento!A9:A329,A25)) -> 5 | Q25: =IF(A25="",0,COUNTIFS(Detalhamento!A9:A329,A25,Detalhamento!H9:H329,"Concluído")) -> 0 | R25: =IFERROR(IF(P25=0,"",Q25/P25),"") -> 0
A26: 4.1 | B26: Instalações de conduítes para sistema eletrico | C26: Elevadores | D26: 46152 | E26: 46342 | F26: =IF(OR($D26="",$E26=""),"Sem data",IF($E26<TODAY(),"Atrasado",IF($D26>TODAY(),"A iniciar","Em andamento"))) -> Em andamento | I26: =IF(COUNTIF(Detalhamento!A9:A329,A26)=0,"-",IF(COUNTIFS(Detalhamento!A9:A329,A26,Detalhamento!J9:J329,"Pendente")>0,"Pendente",IF(COUNTIFS(Detalhamento!A9:A329,A26,Detalhamento!J9:J329,"OK")>0,"OK","-"))) -> - | J26: =IF(COUNTIF(Detalhamento!A9:A329,A26)=0,"-",IF(COUNTIFS(Detalhamento!A9:A329,A26,Detalhamento!K9:K329,"Pendente")>0,"Pendente",IF(COUNTIFS(Detalhamento!A9:A329,A26,Detalhamento!K9:K329,"OK")>0,"OK","-"))) -> - | K26: =IF(COUNTIF(Detalhamento!A9:A329,A26)=0,"-",IF(COUNTIFS(Detalhamento!A9:A329,A26,Detalhamento!L9:L329,"Pendente")>0,"Pendente",IF(COUNTIFS(Detalhamento!A9:A329,A26,Detalhamento!L9:L329,"OK")>0,"OK","-"))) -> - | L26: =IF(COUNTIF(Detalhamento!A9:A329,A26)=0,"-",IF(COUNTIFS(Detalhamento!A9:A329,A26,Detalhamento!M9:M329,"Pendente")>0,"Pendente",IF(COUNTIFS(Detalhamento!A9:A329,A26,Detalhamento!M9:M329,"OK")>0,"OK","-"))) -> - | M26: =IF(COUNTIF(Detalhamento!A9:A329,A26)=0,"-",IF(COUNTIFS(Detalhamento!A9:A329,A26,Detalhamento!N9:N329,"Pendente")>0,"Pendente",IF(COUNTIFS(Detalhamento!A9:A329,A26,Detalhamento!N9:N329,"OK")>0,"OK","-"))) -> - | O26: Original | P26: =IF(A26="",0,COUNTIF(Detalhamento!A9:A329,A26)) -> 1 | Q26: =IF(A26="",0,COUNTIFS(Detalhamento!A9:A329,A26,Detalhamento!H9:H329,"Concluído")) -> 0 | R26: =IFERROR(IF(P26=0,"",Q26/P26),"") -> 0
A27: 4.2 | B27: Instalação de dutos para passagem de fiação e mangueira e passagem dos fios e fios 16 mm | C27: Elevadores | D27: 46152 | E27: 46342 | F27: =IF(OR($D27="",$E27=""),"Sem data",IF($E27<TODAY(),"Atrasado",IF($D27>TODAY(),"A iniciar","Em andamento"))) -> Em andamento | I27: =IF(COUNTIF(Detalhamento!A9:A329,A27)=0,"-",IF(COUNTIFS(Detalhamento!A9:A329,A27,Detalhamento!J9:J329,"Pendente")>0,"Pendente",IF(COUNTIFS(Detalhamento!A9:A329,A27,Detalhamento!J9:J329,"OK")>0,"OK","-"))) -> - | J27: =IF(COUNTIF(Detalhamento!A9:A329,A27)=0,"-",IF(COUNTIFS(Detalhamento!A9:A329,A27,Detalhamento!K9:K329,"Pendente")>0,"Pendente",IF(COUNTIFS(Detalhamento!A9:A329,A27,Detalhamento!K9:K329,"OK")>0,"OK","-"))) -> - | K27: =IF(COUNTIF(Detalhamento!A9:A329,A27)=0,"-",IF(COUNTIFS(Detalhamento!A9:A329,A27,Detalhamento!L9:L329,"Pendente")>0,"Pendente",IF(COUNTIFS(Detalhamento!A9:A329,A27,Detalhamento!L9:L329,"OK")>0,"OK","-"))) -> - | L27: =IF(COUNTIF(Detalhamento!A9:A329,A27)=0,"-",IF(COUNTIFS(Detalhamento!A9:A329,A27,Detalhamento!M9:M329,"Pendente")>0,"Pendente",IF(COUNTIFS(Detalhamento!A9:A329,A27,Detalhamento!M9:M329,"OK")>0,"OK","-"))) -> - | M27: =IF(COUNTIF(Detalhamento!A9:A329,A27)=0,"-",IF(COUNTIFS(Detalhamento!A9:A329,A27,Detalhamento!N9:N329,"Pendente")>0,"Pendente",IF(COUNTIFS(Detalhamento!A9:A329,A27,Detalhamento!N9:N329,"OK")>0,"OK","-"))) -> - | O27: Original | P27: =IF(A27="",0,COUNTIF(Detalhamento!A9:A329,A27)) -> 1 | Q27: =IF(A27="",0,COUNTIFS(Detalhamento!A9:A329,A27,Detalhamento!H9:H329,"Concluído")) -> 0 | R27: =IFERROR(IF(P27=0,"",Q27/P27),"") -> 0
A28: 4.3 | B28: Disjuntor trifásico 100 A no quadro geral da edificação | C28: Elevadores | D28: 46197 | E28: 46258 | F28: =IF(OR($D28="",$E28=""),"Sem data",IF($E28<TODAY(),"Atrasado",IF($D28>TODAY(),"A iniciar","Em andamento"))) -> Em andamento | I28: =IF(COUNTIF(Detalhamento!A9:A329,A28)=0,"-",IF(COUNTIFS(Detalhamento!A9:A329,A28,Detalhamento!J9:J329,"Pendente")>0,"Pendente",IF(COUNTIFS(Detalhamento!A9:A329,A28,Detalhamento!J9:J329,"OK")>0,"OK","-"))) -> - | J28: =IF(COUNTIF(Detalhamento!A9:A329,A28)=0,"-",IF(COUNTIFS(Detalhamento!A9:A329,A28,Detalhamento!K9:K329,"Pendente")>0,"Pendente",IF(COUNTIFS(Detalhamento!A9:A329,A28,Detalhamento!K9:K329,"OK")>0,"OK","-"))) -> - | K28: =IF(COUNTIF(Detalhamento!A9:A329,A28)=0,"-",IF(COUNTIFS(Detalhamento!A9:A329,A28,Detalhamento!L9:L329,"Pendente")>0,"Pendente",IF(COUNTIFS(Detalhamento!A9:A329,A28,Detalhamento!L9:L329,"OK")>0,"OK","-"))) -> - | L28: =IF(COUNTIF(Detalhamento!A9:A329,A28)=0,"-",IF(COUNTIFS(Detalhamento!A9:A329,A28,Detalhamento!M9:M329,"Pendente")>0,"Pendente",IF(COUNTIFS(Detalhamento!A9:A329,A28,Detalhamento!M9:M329,"OK")>0,"OK","-"))) -> - | M28: =IF(COUNTIF(Detalhamento!A9:A329,A28)=0,"-",IF(COUNTIFS(Detalhamento!A9:A329,A28,Detalhamento!N9:N329,"Pendente")>0,"Pendente",IF(COUNTIFS(Detalhamento!A9:A329,A28,Detalhamento!N9:N329,"OK")>0,"OK","-"))) -> - | O28: Original | P28: =IF(A28="",0,COUNTIF(Detalhamento!A9:A329,A28)) -> 1 | Q28: =IF(A28="",0,COUNTIFS(Detalhamento!A9:A329,A28,Detalhamento!H9:H329,"Concluído")) -> 0 | R28: =IFERROR(IF(P28=0,"",Q28/P28),"") -> 0
A29: 4.4 | B29: Ligação de força 220 V trifásico com chave seccionadora | C29: Elevadores | D29: 46197 | E29: 46258 | F29: =IF(OR($D29="",$E29=""),"Sem data",IF($E29<TODAY(),"Atrasado",IF($D29>TODAY(),"A iniciar","Em andamento"))) -> Em andamento | I29: =IF(COUNTIF(Detalhamento!A9:A329,A29)=0,"-",IF(COUNTIFS(Detalhamento!A9:A329,A29,Detalhamento!J9:J329,"Pendente")>0,"Pendente",IF(COUNTIFS(Detalhamento!A9:A329,A29,Detalhamento!J9:J329,"OK")>0,"OK","-"))) -> - | J29: =IF(COUNTIF(Detalhamento!A9:A329,A29)=0,"-",IF(COUNTIFS(Detalhamento!A9:A329,A29,Detalhamento!K9:K329,"Pendente")>0,"Pendente",IF(COUNTIFS(Detalhamento!A9:A329,A29,Detalhamento!K9:K329,"OK")>0,"OK","-"))) -> - | K29: =IF(COUNTIF(Detalhamento!A9:A329,A29)=0,"-",IF(COUNTIFS(Detalhamento!A9:A329,A29,Detalhamento!L9:L329,"Pendente")>0,"Pendente",IF(COUNTIFS(Detalhamento!A9:A329,A29,Detalhamento!L9:L329,"OK")>0,"OK","-"))) -> - | L29: =IF(COUNTIF(Detalhamento!A9:A329,A29)=0,"-",IF(COUNTIFS(Detalhamento!A9:A329,A29,Detalhamento!M9:M329,"Pendente")>0,"Pendente",IF(COUNTIFS(Detalhamento!A9:A329,A29,Detalhamento!M9:M329,"OK")>0,"OK","-"))) -> - | M29: =IF(COUNTIF(Detalhamento!A9:A329,A29)=0,"-",IF(COUNTIFS(Detalhamento!A9:A329,A29,Detalhamento!N9:N329,"Pendente")>0,"Pendente",IF(COUNTIFS(Detalhamento!A9:A329,A29,Detalhamento!N9:N329,"OK")>0,"OK","-"))) -> - | O29: Original | P29: =IF(A29="",0,COUNTIF(Detalhamento!A9:A329,A29)) -> 1 | Q29: =IF(A29="",0,COUNTIFS(Detalhamento!A9:A329,A29,Detalhamento!H9:H329,"Concluído")) -> 0 | R29: =IFERROR(IF(P29=0,"",Q29/P29),"") -> 0
A30: 4.5 | B30: Iluminação da caixa (arandelas, tubulação, luminárias e interruptores) | C30: Elevadores | D30: 46166 | E30: 46366 | F30: =IF(OR($D30="",$E30=""),"Sem data",IF($E30<TODAY(),"Atrasado",IF($D30>TODAY(),"A iniciar","Em andamento"))) -> Em andamento | I30: =IF(COUNTIF(Detalhamento!A9:A329,A30)=0,"-",IF(COUNTIFS(Detalhamento!A9:A329,A30,Detalhamento!J9:J329,"Pendente")>0,"Pendente",IF(COUNTIFS(Detalhamento!A9:A329,A30,Detalhamento!J9:J329,"OK")>0,"OK","-"))) -> - | J30: =IF(COUNTIF(Detalhamento!A9:A329,A30)=0,"-",IF(COUNTIFS(Detalhamento!A9:A329,A30,Detalhamento!K9:K329,"Pendente")>0,"Pendente",IF(COUNTIFS(Detalhamento!A9:A329,A30,Detalhamento!K9:K329,"OK")>0,"OK","-"))) -> - | K30: =IF(COUNTIF(Detalhamento!A9:A329,A30)=0,"-",IF(COUNTIFS(Detalhamento!A9:A329,A30,Detalhamento!L9:L329,"Pendente")>0,"Pendente",IF(COUNTIFS(Detalhamento!A9:A329,A30,Detalhamento!L9:L329,"OK")>0,"OK","-"))) -> - | L30: =IF(COUNTIF(Detalhamento!A9:A329,A30)=0,"-",IF(COUNTIFS(Detalhamento!A9:A329,A30,Detalhamento!M9:M329,"Pendente")>0,"Pendente",IF(COUNTIFS(Detalhamento!A9:A329,A30,Detalhamento!M9:M329,"OK")>0,"OK","-"))) -> - | M30: =IF(COUNTIF(Detalhamento!A9:A329,A30)=0,"-",IF(COUNTIFS(Detalhamento!A9:A329,A30,Detalhamento!N9:N329,"Pendente")>0,"Pendente",IF(COUNTIFS(Detalhamento!A9:A329,A30,Detalhamento!N9:N329,"OK")>0,"OK","-"))) -> - | O30: Original | P30: =IF(A30="",0,COUNTIF(Detalhamento!A9:A329,A30)) -> 1 | Q30: =IF(A30="",0,COUNTIFS(Detalhamento!A9:A329,A30,Detalhamento!H9:H329,"Concluído")) -> 0 | R30: =IFERROR(IF(P30=0,"",Q30/P30),"") -> 0
A31: 4.6 | B31: Instalação de tomadas e interruptores e alimentação elétrica | C31: Elevadores | D31: 46166 | E31: 46366 | F31: =IF(OR($D31="",$E31=""),"Sem data",IF($E31<TODAY(),"Atrasado",IF($D31>TODAY(),"A iniciar","Em andamento"))) -> Em andamento | I31: =IF(COUNTIF(Detalhamento!A9:A329,A31)=0,"-",IF(COUNTIFS(Detalhamento!A9:A329,A31,Detalhamento!J9:J329,"Pendente")>0,"Pendente",IF(COUNTIFS(Detalhamento!A9:A329,A31,Detalhamento!J9:J329,"OK")>0,"OK","-"))) -> - | J31: =IF(COUNTIF(Detalhamento!A9:A329,A31)=0,"-",IF(COUNTIFS(Detalhamento!A9:A329,A31,Detalhamento!K9:K329,"Pendente")>0,"Pendente",IF(COUNTIFS(Detalhamento!A9:A329,A31,Detalhamento!K9:K329,"OK")>0,"OK","-"))) -> - | K31: =IF(COUNTIF(Detalhamento!A9:A329,A31)=0,"-",IF(COUNTIFS(Detalhamento!A9:A329,A31,Detalhamento!L9:L329,"Pendente")>0,"Pendente",IF(COUNTIFS(Detalhamento!A9:A329,A31,Detalhamento!L9:L329,"OK")>0,"OK","-"))) -> - | L31: =IF(COUNTIF(Detalhamento!A9:A329,A31)=0,"-",IF(COUNTIFS(Detalhamento!A9:A329,A31,Detalhamento!M9:M329,"Pendente")>0,"Pendente",IF(COUNTIFS(Detalhamento!A9:A329,A31,Detalhamento!M9:M329,"OK")>0,"OK","-"))) -> - | M31: =IF(COUNTIF(Detalhamento!A9:A329,A31)=0,"-",IF(COUNTIFS(Detalhamento!A9:A329,A31,Detalhamento!N9:N329,"Pendente")>0,"Pendente",IF(COUNTIFS(Detalhamento!A9:A329,A31,Detalhamento!N9:N329,"OK")>0,"OK","-"))) -> - | O31: Original | P31: =IF(A31="",0,COUNTIF(Detalhamento!A9:A329,A31)) -> 1 | Q31: =IF(A31="",0,COUNTIFS(Detalhamento!A9:A329,A31,Detalhamento!H9:H329,"Concluído")) -> 0 | R31: =IFERROR(IF(P31=0,"",Q31/P31),"") -> 0
A32: 4.7 | B32: Instalação de luz de emergência | C32: Elevadores | D32: 46204 | E32: 46366 | F32: =IF(OR($D32="",$E32=""),"Sem data",IF($E32<TODAY(),"Atrasado",IF($D32>TODAY(),"A iniciar","Em andamento"))) -> A iniciar | I32: =IF(COUNTIF(Detalhamento!A9:A329,A32)=0,"-",IF(COUNTIFS(Detalhamento!A9:A329,A32,Detalhamento!J9:J329,"Pendente")>0,"Pendente",IF(COUNTIFS(Detalhamento!A9:A329,A32,Detalhamento!J9:J329,"OK")>0,"OK","-"))) -> - | J32: =IF(COUNTIF(Detalhamento!A9:A329,A32)=0,"-",IF(COUNTIFS(Detalhamento!A9:A329,A32,Detalhamento!K9:K329,"Pendente")>0,"Pendente",IF(COUNTIFS(Detalhamento!A9:A329,A32,Detalhamento!K9:K329,"OK")>0,"OK","-"))) -> - | K32: =IF(COUNTIF(Detalhamento!A9:A329,A32)=0,"-",IF(COUNTIFS(Detalhamento!A9:A329,A32,Detalhamento!L9:L329,"Pendente")>0,"Pendente",IF(COUNTIFS(Detalhamento!A9:A329,A32,Detalhamento!L9:L329,"OK")>0,"OK","-"))) -> - | L32: =IF(COUNTIF(Detalhamento!A9:A329,A32)=0,"-",IF(COUNTIFS(Detalhamento!A9:A329,A32,Detalhamento!M9:M329,"Pendente")>0,"Pendente",IF(COUNTIFS(Detalhamento!A9:A329,A32,Detalhamento!M9:M329,"OK")>0,"OK","-"))) -> - | M32: =IF(COUNTIF(Detalhamento!A9:A329,A32)=0,"-",IF(COUNTIFS(Detalhamento!A9:A329,A32,Detalhamento!N9:N329,"Pendente")>0,"Pendente",IF(COUNTIFS(Detalhamento!A9:A329,A32,Detalhamento!N9:N329,"OK")>0,"OK","-"))) -> - | O32: Original | P32: =IF(A32="",0,COUNTIF(Detalhamento!A9:A329,A32)) -> 1 | Q32: =IF(A32="",0,COUNTIFS(Detalhamento!A9:A329,A32,Detalhamento!H9:H329,"Concluído")) -> 0 | R32: =IFERROR(IF(P32=0,"",Q32/P32),"") -> 0
A33: 4.8 | B33: Cabo Flexível PP Extensão 3x25mm Rolo Com 100 Metros- Prismyan afumex | C33: Elevadores | D33: 46173 | E33: 46180 | F33: =IF(OR($D33="",$E33=""),"Sem data",IF($E33<TODAY(),"Atrasado",IF($D33>TODAY(),"A iniciar","Em andamento"))) -> Atrasado | I33: =IF(COUNTIF(Detalhamento!A9:A329,A33)=0,"-",IF(COUNTIFS(Detalhamento!A9:A329,A33,Detalhamento!J9:J329,"Pendente")>0,"Pendente",IF(COUNTIFS(Detalhamento!A9:A329,A33,Detalhamento!J9:J329,"OK")>0,"OK","-"))) -> - | J33: =IF(COUNTIF(Detalhamento!A9:A329,A33)=0,"-",IF(COUNTIFS(Detalhamento!A9:A329,A33,Detalhamento!K9:K329,"Pendente")>0,"Pendente",IF(COUNTIFS(Detalhamento!A9:A329,A33,Detalhamento!K9:K329,"OK")>0,"OK","-"))) -> - | K33: =IF(COUNTIF(Detalhamento!A9:A329,A33)=0,"-",IF(COUNTIFS(Detalhamento!A9:A329,A33,Detalhamento!L9:L329,"Pendente")>0,"Pendente",IF(COUNTIFS(Detalhamento!A9:A329,A33,Detalhamento!L9:L329,"OK")>0,"OK","-"))) -> - | L33: =IF(COUNTIF(Detalhamento!A9:A329,A33)=0,"-",IF(COUNTIFS(Detalhamento!A9:A329,A33,Detalhamento!M9:M329,"Pendente")>0,"Pendente",IF(COUNTIFS(Detalhamento!A9:A329,A33,Detalhamento!M9:M329,"OK")>0,"OK","-"))) -> - | M33: =IF(COUNTIF(Detalhamento!A9:A329,A33)=0,"-",IF(COUNTIFS(Detalhamento!A9:A329,A33,Detalhamento!N9:N329,"Pendente")>0,"Pendente",IF(COUNTIFS(Detalhamento!A9:A329,A33,Detalhamento!N9:N329,"OK")>0,"OK","-"))) -> - | O33: Original | P33: =IF(A33="",0,COUNTIF(Detalhamento!A9:A329,A33)) -> 1 | Q33: =IF(A33="",0,COUNTIFS(Detalhamento!A9:A329,A33,Detalhamento!H9:H329,"Concluído")) -> 0 | R33: =IFERROR(IF(P33=0,"",Q33/P33),"") -> 0
A34: 4.9 | B34: Desmontagem sistema eletrico e de iluminação existente, com recupero das lampadas | C34: Elevadores | D34: 46152 | E34: 46337 | F34: =IF(OR($D34="",$E34=""),"Sem data",IF($E34<TODAY(),"Atrasado",IF($D34>TODAY(),"A iniciar","Em andamento"))) -> Em andamento | I34: =IF(COUNTIF(Detalhamento!A9:A329,A34)=0,"-",IF(COUNTIFS(Detalhamento!A9:A329,A34,Detalhamento!J9:J329,"Pendente")>0,"Pendente",IF(COUNTIFS(Detalhamento!A9:A329,A34,Detalhamento!J9:J329,"OK")>0,"OK","-"))) -> - | J34: =IF(COUNTIF(Detalhamento!A9:A329,A34)=0,"-",IF(COUNTIFS(Detalhamento!A9:A329,A34,Detalhamento!K9:K329,"Pendente")>0,"Pendente",IF(COUNTIFS(Detalhamento!A9:A329,A34,Detalhamento!K9:K329,"OK")>0,"OK","-"))) -> - | K34: =IF(COUNTIF(Detalhamento!A9:A329,A34)=0,"-",IF(COUNTIFS(Detalhamento!A9:A329,A34,Detalhamento!L9:L329,"Pendente")>0,"Pendente",IF(COUNTIFS(Detalhamento!A9:A329,A34,Detalhamento!L9:L329,"OK")>0,"OK","-"))) -> - | L34: =IF(COUNTIF(Detalhamento!A9:A329,A34)=0,"-",IF(COUNTIFS(Detalhamento!A9:A329,A34,Detalhamento!M9:M329,"Pendente")>0,"Pendente",IF(COUNTIFS(Detalhamento!A9:A329,A34,Detalhamento!M9:M329,"OK")>0,"OK","-"))) -> - | M34: =IF(COUNTIF(Detalhamento!A9:A329,A34)=0,"-",IF(COUNTIFS(Detalhamento!A9:A329,A34,Detalhamento!N9:N329,"Pendente")>0,"Pendente",IF(COUNTIFS(Detalhamento!A9:A329,A34,Detalhamento!N9:N329,"OK")>0,"OK","-"))) -> - | O34: Original | P34: =IF(A34="",0,COUNTIF(Detalhamento!A9:A329,A34)) -> 1 | Q34: =IF(A34="",0,COUNTIFS(Detalhamento!A9:A329,A34,Detalhamento!H9:H329,"Concluído")) -> 0 | R34: =IFERROR(IF(P34=0,"",Q34/P34),"") -> 0
A35: 4.10 | B35: Disjuntores 32A | C35: Elevadores | D35: 46173 | E35: 46180 | F35: =IF(OR($D35="",$E35=""),"Sem data",IF($E35<TODAY(),"Atrasado",IF($D35>TODAY(),"A iniciar","Em andamento"))) -> Atrasado | I35: =IF(COUNTIF(Detalhamento!A9:A329,A35)=0,"-",IF(COUNTIFS(Detalhamento!A9:A329,A35,Detalhamento!J9:J329,"Pendente")>0,"Pendente",IF(COUNTIFS(Detalhamento!A9:A329,A35,Detalhamento!J9:J329,"OK")>0,"OK","-"))) -> - | J35: =IF(COUNTIF(Detalhamento!A9:A329,A35)=0,"-",IF(COUNTIFS(Detalhamento!A9:A329,A35,Detalhamento!K9:K329,"Pendente")>0,"Pendente",IF(COUNTIFS(Detalhamento!A9:A329,A35,Detalhamento!K9:K329,"OK")>0,"OK","-"))) -> - | K35: =IF(COUNTIF(Detalhamento!A9:A329,A35)=0,"-",IF(COUNTIFS(Detalhamento!A9:A329,A35,Detalhamento!L9:L329,"Pendente")>0,"Pendente",IF(COUNTIFS(Detalhamento!A9:A329,A35,Detalhamento!L9:L329,"OK")>0,"OK","-"))) -> - | L35: =IF(COUNTIF(Detalhamento!A9:A329,A35)=0,"-",IF(COUNTIFS(Detalhamento!A9:A329,A35,Detalhamento!M9:M329,"Pendente")>0,"Pendente",IF(COUNTIFS(Detalhamento!A9:A329,A35,Detalhamento!M9:M329,"OK")>0,"OK","-"))) -> - | M35: =IF(COUNTIF(Detalhamento!A9:A329,A35)=0,"-",IF(COUNTIFS(Detalhamento!A9:A329,A35,Detalhamento!N9:N329,"Pendente")>0,"Pendente",IF(COUNTIFS(Detalhamento!A9:A329,A35,Detalhamento!N9:N329,"OK")>0,"OK","-"))) -> - | O35: Original | P35: =IF(A35="",0,COUNTIF(Detalhamento!A9:A329,A35)) -> 1 | Q35: =IF(A35="",0,COUNTIFS(Detalhamento!A9:A329,A35,Detalhamento!H9:H329,"Concluído")) -> 0 | R35: =IFERROR(IF(P35=0,"",Q35/P35),"") -> 0
A36: 4.11 | B36: Cabo Flexível PP Extensão 3x4mm Rolo Com 100 Metros - Prismyan afumex | C36: Elevadores | D36: 46173 | E36: 46180 | F36: =IF(OR($D36="",$E36=""),"Sem data",IF($E36<TODAY(),"Atrasado",IF($D36>TODAY(),"A iniciar","Em andamento"))) -> Atrasado | I36: =IF(COUNTIF(Detalhamento!A9:A329,A36)=0,"-",IF(COUNTIFS(Detalhamento!A9:A329,A36,Detalhamento!J9:J329,"Pendente")>0,"Pendente",IF(COUNTIFS(Detalhamento!A9:A329,A36,Detalhamento!J9:J329,"OK")>0,"OK","-"))) -> - | J36: =IF(COUNTIF(Detalhamento!A9:A329,A36)=0,"-",IF(COUNTIFS(Detalhamento!A9:A329,A36,Detalhamento!K9:K329,"Pendente")>0,"Pendente",IF(COUNTIFS(Detalhamento!A9:A329,A36,Detalhamento!K9:K329,"OK")>0,"OK","-"))) -> - | K36: =IF(COUNTIF(Detalhamento!A9:A329,A36)=0,"-",IF(COUNTIFS(Detalhamento!A9:A329,A36,Detalhamento!L9:L329,"Pendente")>0,"Pendente",IF(COUNTIFS(Detalhamento!A9:A329,A36,Detalhamento!L9:L329,"OK")>0,"OK","-"))) -> - | L36: =IF(COUNTIF(Detalhamento!A9:A329,A36)=0,"-",IF(COUNTIFS(Detalhamento!A9:A329,A36,Detalhamento!M9:M329,"Pendente")>0,"Pendente",IF(COUNTIFS(Detalhamento!A9:A329,A36,Detalhamento!M9:M329,"OK")>0,"OK","-"))) -> - | M36: =IF(COUNTIF(Detalhamento!A9:A329,A36)=0,"-",IF(COUNTIFS(Detalhamento!A9:A329,A36,Detalhamento!N9:N329,"Pendente")>0,"Pendente",IF(COUNTIFS(Detalhamento!A9:A329,A36,Detalhamento!N9:N329,"OK")>0,"OK","-"))) -> - | O36: Original | P36: =IF(A36="",0,COUNTIF(Detalhamento!A9:A329,A36)) -> 1 | Q36: =IF(A36="",0,COUNTIFS(Detalhamento!A9:A329,A36,Detalhamento!H9:H329,"Concluído")) -> 0 | R36: =IFERROR(IF(P36=0,"",Q36/P36),"") -> 0
A37: 4.12 | B37: Cabo Flexível PP Extensão 3x2,5mm Rolo Com 100 Metros- Prismyan afumex | C37: Elevadores | D37: 46173 | E37: 46180 | F37: =IF(OR($D37="",$E37=""),"Sem data",IF($E37<TODAY(),"Atrasado",IF($D37>TODAY(),"A iniciar","Em andamento"))) -> Atrasado | I37: =IF(COUNTIF(Detalhamento!A9:A329,A37)=0,"-",IF(COUNTIFS(Detalhamento!A9:A329,A37,Detalhamento!J9:J329,"Pendente")>0,"Pendente",IF(COUNTIFS(Detalhamento!A9:A329,A37,Detalhamento!J9:J329,"OK")>0,"OK","-"))) -> - | J37: =IF(COUNTIF(Detalhamento!A9:A329,A37)=0,"-",IF(COUNTIFS(Detalhamento!A9:A329,A37,Detalhamento!K9:K329,"Pendente")>0,"Pendente",IF(COUNTIFS(Detalhamento!A9:A329,A37,Detalhamento!K9:K329,"OK")>0,"OK","-"))) -> - | K37: =IF(COUNTIF(Detalhamento!A9:A329,A37)=0,"-",IF(COUNTIFS(Detalhamento!A9:A329,A37,Detalhamento!L9:L329,"Pendente")>0,"Pendente",IF(COUNTIFS(Detalhamento!A9:A329,A37,Detalhamento!L9:L329,"OK")>0,"OK","-"))) -> - | L37: =IF(COUNTIF(Detalhamento!A9:A329,A37)=0,"-",IF(COUNTIFS(Detalhamento!A9:A329,A37,Detalhamento!M9:M329,"Pendente")>0,"Pendente",IF(COUNTIFS(Detalhamento!A9:A329,A37,Detalhamento!M9:M329,"OK")>0,"OK","-"))) -> - | M37: =IF(COUNTIF(Detalhamento!A9:A329,A37)=0,"-",IF(COUNTIFS(Detalhamento!A9:A329,A37,Detalhamento!N9:N329,"Pendente")>0,"Pendente",IF(COUNTIFS(Detalhamento!A9:A329,A37,Detalhamento!N9:N329,"OK")>0,"OK","-"))) -> - | O37: Original | P37: =IF(A37="",0,COUNTIF(Detalhamento!A9:A329,A37)) -> 1 | Q37: =IF(A37="",0,COUNTIFS(Detalhamento!A9:A329,A37,Detalhamento!H9:H329,"Concluído")) -> 0 | R37: =IFERROR(IF(P37=0,"",Q37/P37),"") -> 0
A38: 4.13 | B38: Fornecimento e instalação de infraestrutura, Eletroduto Galvanizado Pre Zincado Leve 3/4, | C38: Elevadores | D38: 46166 | E38: 46337 | F38: =IF(OR($D38="",$E38=""),"Sem data",IF($E38<TODAY(),"Atrasado",IF($D38>TODAY(),"A iniciar","Em andamento"))) -> Em andamento | I38: =IF(COUNTIF(Detalhamento!A9:A329,A38)=0,"-",IF(COUNTIFS(Detalhamento!A9:A329,A38,Detalhamento!J9:J329,"Pendente")>0,"Pendente",IF(COUNTIFS(Detalhamento!A9:A329,A38,Detalhamento!J9:J329,"OK")>0,"OK","-"))) -> - | J38: =IF(COUNTIF(Detalhamento!A9:A329,A38)=0,"-",IF(COUNTIFS(Detalhamento!A9:A329,A38,Detalhamento!K9:K329,"Pendente")>0,"Pendente",IF(COUNTIFS(Detalhamento!A9:A329,A38,Detalhamento!K9:K329,"OK")>0,"OK","-"))) -> - | K38: =IF(COUNTIF(Detalhamento!A9:A329,A38)=0,"-",IF(COUNTIFS(Detalhamento!A9:A329,A38,Detalhamento!L9:L329,"Pendente")>0,"Pendente",IF(COUNTIFS(Detalhamento!A9:A329,A38,Detalhamento!L9:L329,"OK")>0,"OK","-"))) -> - | L38: =IF(COUNTIF(Detalhamento!A9:A329,A38)=0,"-",IF(COUNTIFS(Detalhamento!A9:A329,A38,Detalhamento!M9:M329,"Pendente")>0,"Pendente",IF(COUNTIFS(Detalhamento!A9:A329,A38,Detalhamento!M9:M329,"OK")>0,"OK","-"))) -> - | M38: =IF(COUNTIF(Detalhamento!A9:A329,A38)=0,"-",IF(COUNTIFS(Detalhamento!A9:A329,A38,Detalhamento!N9:N329,"Pendente")>0,"Pendente",IF(COUNTIFS(Detalhamento!A9:A329,A38,Detalhamento!N9:N329,"OK")>0,"OK","-"))) -> - | O38: Original | P38: =IF(A38="",0,COUNTIF(Detalhamento!A9:A329,A38)) -> 1 | Q38: =IF(A38="",0,COUNTIFS(Detalhamento!A9:A329,A38,Detalhamento!H9:H329,"Concluído")) -> 0 | R38: =IFERROR(IF(P38=0,"",Q38/P38),"") -> 0
A39: 4.14 | B39: Caixas de passagem e interruptores 4x2 galvanizado | C39: Elevadores | D39: 46173 | E39: 46337 | F39: =IF(OR($D39="",$E39=""),"Sem data",IF($E39<TODAY(),"Atrasado",IF($D39>TODAY(),"A iniciar","Em andamento"))) -> Em andamento | I39: =IF(COUNTIF(Detalhamento!A9:A329,A39)=0,"-",IF(COUNTIFS(Detalhamento!A9:A329,A39,Detalhamento!J9:J329,"Pendente")>0,"Pendente",IF(COUNTIFS(Detalhamento!A9:A329,A39,Detalhamento!J9:J329,"OK")>0,"OK","-"))) -> - | J39: =IF(COUNTIF(Detalhamento!A9:A329,A39)=0,"-",IF(COUNTIFS(Detalhamento!A9:A329,A39,Detalhamento!K9:K329,"Pendente")>0,"Pendente",IF(COUNTIFS(Detalhamento!A9:A329,A39,Detalhamento!K9:K329,"OK")>0,"OK","-"))) -> - | K39: =IF(COUNTIF(Detalhamento!A9:A329,A39)=0,"-",IF(COUNTIFS(Detalhamento!A9:A329,A39,Detalhamento!L9:L329,"Pendente")>0,"Pendente",IF(COUNTIFS(Detalhamento!A9:A329,A39,Detalhamento!L9:L329,"OK")>0,"OK","-"))) -> - | L39: =IF(COUNTIF(Detalhamento!A9:A329,A39)=0,"-",IF(COUNTIFS(Detalhamento!A9:A329,A39,Detalhamento!M9:M329,"Pendente")>0,"Pendente",IF(COUNTIFS(Detalhamento!A9:A329,A39,Detalhamento!M9:M329,"OK")>0,"OK","-"))) -> - | M39: =IF(COUNTIF(Detalhamento!A9:A329,A39)=0,"-",IF(COUNTIFS(Detalhamento!A9:A329,A39,Detalhamento!N9:N329,"Pendente")>0,"Pendente",IF(COUNTIFS(Detalhamento!A9:A329,A39,Detalhamento!N9:N329,"OK")>0,"OK","-"))) -> - | O39: Original | P39: =IF(A39="",0,COUNTIF(Detalhamento!A9:A329,A39)) -> 1 | Q39: =IF(A39="",0,COUNTIFS(Detalhamento!A9:A329,A39,Detalhamento!H9:H329,"Concluído")) -> 0 | R39: =IFERROR(IF(P39=0,"",Q39/P39),"") -> 0
A40: 4.15 | B40: Fornecimento Luminária Led com suporte 60 cm 9w 6500k | C40: Elevadores | D40: 46180 | E40: 46187 | F40: =IF(OR($D40="",$E40=""),"Sem data",IF($E40<TODAY(),"Atrasado",IF($D40>TODAY(),"A iniciar","Em andamento"))) -> Atrasado | I40: =IF(COUNTIF(Detalhamento!A9:A329,A40)=0,"-",IF(COUNTIFS(Detalhamento!A9:A329,A40,Detalhamento!J9:J329,"Pendente")>0,"Pendente",IF(COUNTIFS(Detalhamento!A9:A329,A40,Detalhamento!J9:J329,"OK")>0,"OK","-"))) -> - | J40: =IF(COUNTIF(Detalhamento!A9:A329,A40)=0,"-",IF(COUNTIFS(Detalhamento!A9:A329,A40,Detalhamento!K9:K329,"Pendente")>0,"Pendente",IF(COUNTIFS(Detalhamento!A9:A329,A40,Detalhamento!K9:K329,"OK")>0,"OK","-"))) -> - | K40: =IF(COUNTIF(Detalhamento!A9:A329,A40)=0,"-",IF(COUNTIFS(Detalhamento!A9:A329,A40,Detalhamento!L9:L329,"Pendente")>0,"Pendente",IF(COUNTIFS(Detalhamento!A9:A329,A40,Detalhamento!L9:L329,"OK")>0,"OK","-"))) -> - | L40: =IF(COUNTIF(Detalhamento!A9:A329,A40)=0,"-",IF(COUNTIFS(Detalhamento!A9:A329,A40,Detalhamento!M9:M329,"Pendente")>0,"Pendente",IF(COUNTIFS(Detalhamento!A9:A329,A40,Detalhamento!M9:M329,"OK")>0,"OK","-"))) -> - | M40: =IF(COUNTIF(Detalhamento!A9:A329,A40)=0,"-",IF(COUNTIFS(Detalhamento!A9:A329,A40,Detalhamento!N9:N329,"Pendente")>0,"Pendente",IF(COUNTIFS(Detalhamento!A9:A329,A40,Detalhamento!N9:N329,"OK")>0,"OK","-"))) -> - | O40: Original | P40: =IF(A40="",0,COUNTIF(Detalhamento!A9:A329,A40)) -> 1 | Q40: =IF(A40="",0,COUNTIFS(Detalhamento!A9:A329,A40,Detalhamento!H9:H329,"Concluído")) -> 0 | R40: =IFERROR(IF(P40=0,"",Q40/P40),"") -> 0
A41: 4.16 | B41: Fornecimento Luminária Led com suporte 120 cm 18w 6500k | C41: Elevadores | D41: 46180 | E41: 46187 | F41: =IF(OR($D41="",$E41=""),"Sem data",IF($E41<TODAY(),"Atrasado",IF($D41>TODAY(),"A iniciar","Em andamento"))) -> Atrasado | I41: =IF(COUNTIF(Detalhamento!A9:A329,A41)=0,"-",IF(COUNTIFS(Detalhamento!A9:A329,A41,Detalhamento!J9:J329,"Pendente")>0,"Pendente",IF(COUNTIFS(Detalhamento!A9:A329,A41,Detalhamento!J9:J329,"OK")>0,"OK","-"))) -> - | J41: =IF(COUNTIF(Detalhamento!A9:A329,A41)=0,"-",IF(COUNTIFS(Detalhamento!A9:A329,A41,Detalhamento!K9:K329,"Pendente")>0,"Pendente",IF(COUNTIFS(Detalhamento!A9:A329,A41,Detalhamento!K9:K329,"OK")>0,"OK","-"))) -> - | K41: =IF(COUNTIF(Detalhamento!A9:A329,A41)=0,"-",IF(COUNTIFS(Detalhamento!A9:A329,A41,Detalhamento!L9:L329,"Pendente")>0,"Pendente",IF(COUNTIFS(Detalhamento!A9:A329,A41,Detalhamento!L9:L329,"OK")>0,"OK","-"))) -> - | L41: =IF(COUNTIF(Detalhamento!A9:A329,A41)=0,"-",IF(COUNTIFS(Detalhamento!A9:A329,A41,Detalhamento!M9:M329,"Pendente")>0,"Pendente",IF(COUNTIFS(Detalhamento!A9:A329,A41,Detalhamento!M9:M329,"OK")>0,"OK","-"))) -> - | M41: =IF(COUNTIF(Detalhamento!A9:A329,A41)=0,"-",IF(COUNTIFS(Detalhamento!A9:A329,A41,Detalhamento!N9:N329,"Pendente")>0,"Pendente",IF(COUNTIFS(Detalhamento!A9:A329,A41,Detalhamento!N9:N329,"OK")>0,"OK","-"))) -> - | O41: Original | P41: =IF(A41="",0,COUNTIF(Detalhamento!A9:A329,A41)) -> 1 | Q41: =IF(A41="",0,COUNTIFS(Detalhamento!A9:A329,A41,Detalhamento!H9:H329,"Concluído")) -> 0 | R41: =IFERROR(IF(P41=0,"",Q41/P41),"") -> 0
A42: 4.17 | B42: Instalação luminarias | C42: Elevadores | D42: 46217 | E42: 46378 | F42: =IF(OR($D42="",$E42=""),"Sem data",IF($E42<TODAY(),"Atrasado",IF($D42>TODAY(),"A iniciar","Em andamento"))) -> A iniciar | I42: =IF(COUNTIF(Detalhamento!A9:A329,A42)=0,"-",IF(COUNTIFS(Detalhamento!A9:A329,A42,Detalhamento!J9:J329,"Pendente")>0,"Pendente",IF(COUNTIFS(Detalhamento!A9:A329,A42,Detalhamento!J9:J329,"OK")>0,"OK","-"))) -> - | J42: =IF(COUNTIF(Detalhamento!A9:A329,A42)=0,"-",IF(COUNTIFS(Detalhamento!A9:A329,A42,Detalhamento!K9:K329,"Pendente")>0,"Pendente",IF(COUNTIFS(Detalhamento!A9:A329,A42,Detalhamento!K9:K329,"OK")>0,"OK","-"))) -> - | K42: =IF(COUNTIF(Detalhamento!A9:A329,A42)=0,"-",IF(COUNTIFS(Detalhamento!A9:A329,A42,Detalhamento!L9:L329,"Pendente")>0,"Pendente",IF(COUNTIFS(Detalhamento!A9:A329,A42,Detalhamento!L9:L329,"OK")>0,"OK","-"))) -> - | L42: =IF(COUNTIF(Detalhamento!A9:A329,A42)=0,"-",IF(COUNTIFS(Detalhamento!A9:A329,A42,Detalhamento!M9:M329,"Pendente")>0,"Pendente",IF(COUNTIFS(Detalhamento!A9:A329,A42,Detalhamento!M9:M329,"OK")>0,"OK","-"))) -> - | M42: =IF(COUNTIF(Detalhamento!A9:A329,A42)=0,"-",IF(COUNTIFS(Detalhamento!A9:A329,A42,Detalhamento!N9:N329,"Pendente")>0,"Pendente",IF(COUNTIFS(Detalhamento!A9:A329,A42,Detalhamento!N9:N329,"OK")>0,"OK","-"))) -> - | O42: Original | P42: =IF(A42="",0,COUNTIF(Detalhamento!A9:A329,A42)) -> 1 | Q42: =IF(A42="",0,COUNTIFS(Detalhamento!A9:A329,A42,Detalhamento!H9:H329,"Concluído")) -> 0 | R42: =IFERROR(IF(P42=0,"",Q42/P42),"") -> 0
A43: 11 | B43: Elevador 1 - 17 andares - 8 pessoas - Estrutura de vidro roof top | C43: Elevadores | D43: 46222 | E43: 46408 | F43: =IF(OR($D43="",$E43=""),"Sem data",IF($E43<TODAY(),"Atrasado",IF($D43>TODAY(),"A iniciar","Em andamento"))) -> A iniciar | I43: =IF(COUNTIF(Detalhamento!A9:A329,A43)=0,"-",IF(COUNTIFS(Detalhamento!A9:A329,A43,Detalhamento!J9:J329,"Pendente")>0,"Pendente",IF(COUNTIFS(Detalhamento!A9:A329,A43,Detalhamento!J9:J329,"OK")>0,"OK","-"))) -> - | J43: =IF(COUNTIF(Detalhamento!A9:A329,A43)=0,"-",IF(COUNTIFS(Detalhamento!A9:A329,A43,Detalhamento!K9:K329,"Pendente")>0,"Pendente",IF(COUNTIFS(Detalhamento!A9:A329,A43,Detalhamento!K9:K329,"OK")>0,"OK","-"))) -> - | K43: =IF(COUNTIF(Detalhamento!A9:A329,A43)=0,"-",IF(COUNTIFS(Detalhamento!A9:A329,A43,Detalhamento!L9:L329,"Pendente")>0,"Pendente",IF(COUNTIFS(Detalhamento!A9:A329,A43,Detalhamento!L9:L329,"OK")>0,"OK","-"))) -> - | L43: =IF(COUNTIF(Detalhamento!A9:A329,A43)=0,"-",IF(COUNTIFS(Detalhamento!A9:A329,A43,Detalhamento!M9:M329,"Pendente")>0,"Pendente",IF(COUNTIFS(Detalhamento!A9:A329,A43,Detalhamento!M9:M329,"OK")>0,"OK","-"))) -> - | M43: =IF(COUNTIF(Detalhamento!A9:A329,A43)=0,"-",IF(COUNTIFS(Detalhamento!A9:A329,A43,Detalhamento!N9:N329,"Pendente")>0,"Pendente",IF(COUNTIFS(Detalhamento!A9:A329,A43,Detalhamento!N9:N329,"OK")>0,"OK","-"))) -> - | O43: Original | P43: =IF(A43="",0,COUNTIF(Detalhamento!A9:A329,A43)) -> 0 | Q43: =IF(A43="",0,COUNTIFS(Detalhamento!A9:A329,A43,Detalhamento!H9:H329,"Concluído")) -> 0 | R43: =IFERROR(IF(P43=0,"",Q43/P43),"")
A44: 12 | B44: Intervenções nos halls dos elevadores - fase - elevador 1 - 17 andares | C44: Elevadores | D44: 46223 | E44: 46304 | F44: =IF(OR($D44="",$E44=""),"Sem data",IF($E44<TODAY(),"Atrasado",IF($D44>TODAY(),"A iniciar","Em andamento"))) -> A iniciar | I44: =IF(COUNTIF(Detalhamento!A9:A329,A44)=0,"-",IF(COUNTIFS(Detalhamento!A9:A329,A44,Detalhamento!J9:J329,"Pendente")>0,"Pendente",IF(COUNTIFS(Detalhamento!A9:A329,A44,Detalhamento!J9:J329,"OK")>0,"OK","-"))) -> - | J44: =IF(COUNTIF(Detalhamento!A9:A329,A44)=0,"-",IF(COUNTIFS(Detalhamento!A9:A329,A44,Detalhamento!K9:K329,"Pendente")>0,"Pendente",IF(COUNTIFS(Detalhamento!A9:A329,A44,Detalhamento!K9:K329,"OK")>0,"OK","-"))) -> - | K44: =IF(COUNTIF(Detalhamento!A9:A329,A44)=0,"-",IF(COUNTIFS(Detalhamento!A9:A329,A44,Detalhamento!L9:L329,"Pendente")>0,"Pendente",IF(COUNTIFS(Detalhamento!A9:A329,A44,Detalhamento!L9:L329,"OK")>0,"OK","-"))) -> - | L44: =IF(COUNTIF(Detalhamento!A9:A329,A44)=0,"-",IF(COUNTIFS(Detalhamento!A9:A329,A44,Detalhamento!M9:M329,"Pendente")>0,"Pendente",IF(COUNTIFS(Detalhamento!A9:A329,A44,Detalhamento!M9:M329,"OK")>0,"OK","-"))) -> - | M44: =IF(COUNTIF(Detalhamento!A9:A329,A44)=0,"-",IF(COUNTIFS(Detalhamento!A9:A329,A44,Detalhamento!N9:N329,"Pendente")>0,"Pendente",IF(COUNTIFS(Detalhamento!A9:A329,A44,Detalhamento!N9:N329,"OK")>0,"OK","-"))) -> - | O44: Original | P44: =IF(A44="",0,COUNTIF(Detalhamento!A9:A329,A44)) -> 0 | Q44: =IF(A44="",0,COUNTIFS(Detalhamento!A9:A329,A44,Detalhamento!H9:H329,"Concluído")) -> 0 | R44: =IFERROR(IF(P44=0,"",Q44/P44),"")
A45: 12 | B45: Elevador 2 - 15 andar andares- 8 pessoas | C45: Elevadores | D45: 46131 | E45: 46227 | F45: =IF(OR($D45="",$E45=""),"Sem data",IF($E45<TODAY(),"Atrasado",IF($D45>TODAY(),"A iniciar","Em andamento"))) -> Em andamento | I45: =IF(COUNTIF(Detalhamento!A9:A329,A45)=0,"-",IF(COUNTIFS(Detalhamento!A9:A329,A45,Detalhamento!J9:J329,"Pendente")>0,"Pendente",IF(COUNTIFS(Detalhamento!A9:A329,A45,Detalhamento!J9:J329,"OK")>0,"OK","-"))) -> - | J45: =IF(COUNTIF(Detalhamento!A9:A329,A45)=0,"-",IF(COUNTIFS(Detalhamento!A9:A329,A45,Detalhamento!K9:K329,"Pendente")>0,"Pendente",IF(COUNTIFS(Detalhamento!A9:A329,A45,Detalhamento!K9:K329,"OK")>0,"OK","-"))) -> - | K45: =IF(COUNTIF(Detalhamento!A9:A329,A45)=0,"-",IF(COUNTIFS(Detalhamento!A9:A329,A45,Detalhamento!L9:L329,"Pendente")>0,"Pendente",IF(COUNTIFS(Detalhamento!A9:A329,A45,Detalhamento!L9:L329,"OK")>0,"OK","-"))) -> - | L45: =IF(COUNTIF(Detalhamento!A9:A329,A45)=0,"-",IF(COUNTIFS(Detalhamento!A9:A329,A45,Detalhamento!M9:M329,"Pendente")>0,"Pendente",IF(COUNTIFS(Detalhamento!A9:A329,A45,Detalhamento!M9:M329,"OK")>0,"OK","-"))) -> - | M45: =IF(COUNTIF(Detalhamento!A9:A329,A45)=0,"-",IF(COUNTIFS(Detalhamento!A9:A329,A45,Detalhamento!N9:N329,"Pendente")>0,"Pendente",IF(COUNTIFS(Detalhamento!A9:A329,A45,Detalhamento!N9:N329,"OK")>0,"OK","-"))) -> - | O45: Original | P45: =IF(A45="",0,COUNTIF(Detalhamento!A9:A329,A45)) -> 0 | Q45: =IF(A45="",0,COUNTIFS(Detalhamento!A9:A329,A45,Detalhamento!H9:H329,"Concluído")) -> 0 | R45: =IFERROR(IF(P45=0,"",Q45/P45),"")
A46: 12.1 | B46: Intervenções nos halls dos elevadores - fase - elevador 2 - 15 andares | C46: Elevadores | D46: 46132 | E46: 46218 | F46: =IF(OR($D46="",$E46=""),"Sem data",IF($E46<TODAY(),"Atrasado",IF($D46>TODAY(),"A iniciar","Em andamento"))) -> Em andamento | I46: =IF(COUNTIF(Detalhamento!A9:A329,A46)=0,"-",IF(COUNTIFS(Detalhamento!A9:A329,A46,Detalhamento!J9:J329,"Pendente")>0,"Pendente",IF(COUNTIFS(Detalhamento!A9:A329,A46,Detalhamento!J9:J329,"OK")>0,"OK","-"))) -> - | J46: =IF(COUNTIF(Detalhamento!A9:A329,A46)=0,"-",IF(COUNTIFS(Detalhamento!A9:A329,A46,Detalhamento!K9:K329,"Pendente")>0,"Pendente",IF(COUNTIFS(Detalhamento!A9:A329,A46,Detalhamento!K9:K329,"OK")>0,"OK","-"))) -> - | K46: =IF(COUNTIF(Detalhamento!A9:A329,A46)=0,"-",IF(COUNTIFS(Detalhamento!A9:A329,A46,Detalhamento!L9:L329,"Pendente")>0,"Pendente",IF(COUNTIFS(Detalhamento!A9:A329,A46,Detalhamento!L9:L329,"OK")>0,"OK","-"))) -> - | L46: =IF(COUNTIF(Detalhamento!A9:A329,A46)=0,"-",IF(COUNTIFS(Detalhamento!A9:A329,A46,Detalhamento!M9:M329,"Pendente")>0,"Pendente",IF(COUNTIFS(Detalhamento!A9:A329,A46,Detalhamento!M9:M329,"OK")>0,"OK","-"))) -> - | M46: =IF(COUNTIF(Detalhamento!A9:A329,A46)=0,"-",IF(COUNTIFS(Detalhamento!A9:A329,A46,Detalhamento!N9:N329,"Pendente")>0,"Pendente",IF(COUNTIFS(Detalhamento!A9:A329,A46,Detalhamento!N9:N329,"OK")>0,"OK","-"))) -> - | O46: Original | P46: =IF(A46="",0,COUNTIF(Detalhamento!A9:A329,A46)) -> 0 | Q46: =IF(A46="",0,COUNTIFS(Detalhamento!A9:A329,A46,Detalhamento!H9:H329,"Concluído")) -> 0 | R46: =IFERROR(IF(P46=0,"",Q46/P46),"")
A47: 13 | B47: Elevador 3 - 6 andares - 4 pessoas | C47: Elevadores | D47: 46327 | E47: 46400 | F47: =IF(OR($D47="",$E47=""),"Sem data",IF($E47<TODAY(),"Atrasado",IF($D47>TODAY(),"A iniciar","Em andamento"))) -> A iniciar | I47: =IF(COUNTIF(Detalhamento!A9:A329,A47)=0,"-",IF(COUNTIFS(Detalhamento!A9:A329,A47,Detalhamento!J9:J329,"Pendente")>0,"Pendente",IF(COUNTIFS(Detalhamento!A9:A329,A47,Detalhamento!J9:J329,"OK")>0,"OK","-"))) -> - | J47: =IF(COUNTIF(Detalhamento!A9:A329,A47)=0,"-",IF(COUNTIFS(Detalhamento!A9:A329,A47,Detalhamento!K9:K329,"Pendente")>0,"Pendente",IF(COUNTIFS(Detalhamento!A9:A329,A47,Detalhamento!K9:K329,"OK")>0,"OK","-"))) -> - | K47: =IF(COUNTIF(Detalhamento!A9:A329,A47)=0,"-",IF(COUNTIFS(Detalhamento!A9:A329,A47,Detalhamento!L9:L329,"Pendente")>0,"Pendente",IF(COUNTIFS(Detalhamento!A9:A329,A47,Detalhamento!L9:L329,"OK")>0,"OK","-"))) -> - | L47: =IF(COUNTIF(Detalhamento!A9:A329,A47)=0,"-",IF(COUNTIFS(Detalhamento!A9:A329,A47,Detalhamento!M9:M329,"Pendente")>0,"Pendente",IF(COUNTIFS(Detalhamento!A9:A329,A47,Detalhamento!M9:M329,"OK")>0,"OK","-"))) -> - | M47: =IF(COUNTIF(Detalhamento!A9:A329,A47)=0,"-",IF(COUNTIFS(Detalhamento!A9:A329,A47,Detalhamento!N9:N329,"Pendente")>0,"Pendente",IF(COUNTIFS(Detalhamento!A9:A329,A47,Detalhamento!N9:N329,"OK")>0,"OK","-"))) -> - | O47: Original | P47: =IF(A47="",0,COUNTIF(Detalhamento!A9:A329,A47)) -> 0 | Q47: =IF(A47="",0,COUNTIFS(Detalhamento!A9:A329,A47,Detalhamento!H9:H329,"Concluído")) -> 0 | R47: =IFERROR(IF(P47=0,"",Q47/P47),"")
A48: 14 | B48: Intervenções nos halls dos elevadores - fase - elevador 3 - 7 andares | C48: Elevadores | D48: 46132 | E48: 46218 | F48: =IF(OR($D48="",$E48=""),"Sem data",IF($E48<TODAY(),"Atrasado",IF($D48>TODAY(),"A iniciar","Em andamento"))) -> Em andamento | I48: =IF(COUNTIF(Detalhamento!A9:A329,A48)=0,"-",IF(COUNTIFS(Detalhamento!A9:A329,A48,Detalhamento!J9:J329,"Pendente")>0,"Pendente",IF(COUNTIFS(Detalhamento!A9:A329,A48,Detalhamento!J9:J329,"OK")>0,"OK","-"))) -> - | J48: =IF(COUNTIF(Detalhamento!A9:A329,A48)=0,"-",IF(COUNTIFS(Detalhamento!A9:A329,A48,Detalhamento!K9:K329,"Pendente")>0,"Pendente",IF(COUNTIFS(Detalhamento!A9:A329,A48,Detalhamento!K9:K329,"OK")>0,"OK","-"))) -> - | K48: =IF(COUNTIF(Detalhamento!A9:A329,A48)=0,"-",IF(COUNTIFS(Detalhamento!A9:A329,A48,Detalhamento!L9:L329,"Pendente")>0,"Pendente",IF(COUNTIFS(Detalhamento!A9:A329,A48,Detalhamento!L9:L329,"OK")>0,"OK","-"))) -> - | L48: =IF(COUNTIF(Detalhamento!A9:A329,A48)=0,"-",IF(COUNTIFS(Detalhamento!A9:A329,A48,Detalhamento!M9:M329,"Pendente")>0,"Pendente",IF(COUNTIFS(Detalhamento!A9:A329,A48,Detalhamento!M9:M329,"OK")>0,"OK","-"))) -> - | M48: =IF(COUNTIF(Detalhamento!A9:A329,A48)=0,"-",IF(COUNTIFS(Detalhamento!A9:A329,A48,Detalhamento!N9:N329,"Pendente")>0,"Pendente",IF(COUNTIFS(Detalhamento!A9:A329,A48,Detalhamento!N9:N329,"OK")>0,"OK","-"))) -> - | O48: Original | P48: =IF(A48="",0,COUNTIF(Detalhamento!A9:A329,A48)) -> 0 | Q48: =IF(A48="",0,COUNTIFS(Detalhamento!A9:A329,A48,Detalhamento!H9:H329,"Concluído")) -> 0 | R48: =IFERROR(IF(P48=0,"",Q48/P48),"")
A49: 13.1 | B49: Desmontagem/ Montagem e Test | C49: Elevadores | D49: 46327 | E49: 46394 | F49: =IF(OR($D49="",$E49=""),"Sem data",IF($E49<TODAY(),"Atrasado",IF($D49>TODAY(),"A iniciar","Em andamento"))) -> A iniciar | I49: =IF(COUNTIF(Detalhamento!A9:A329,A49)=0,"-",IF(COUNTIFS(Detalhamento!A9:A329,A49,Detalhamento!J9:J329,"Pendente")>0,"Pendente",IF(COUNTIFS(Detalhamento!A9:A329,A49,Detalhamento!J9:J329,"OK")>0,"OK","-"))) -> - | J49: =IF(COUNTIF(Detalhamento!A9:A329,A49)=0,"-",IF(COUNTIFS(Detalhamento!A9:A329,A49,Detalhamento!K9:K329,"Pendente")>0,"Pendente",IF(COUNTIFS(Detalhamento!A9:A329,A49,Detalhamento!K9:K329,"OK")>0,"OK","-"))) -> - | K49: =IF(COUNTIF(Detalhamento!A9:A329,A49)=0,"-",IF(COUNTIFS(Detalhamento!A9:A329,A49,Detalhamento!L9:L329,"Pendente")>0,"Pendente",IF(COUNTIFS(Detalhamento!A9:A329,A49,Detalhamento!L9:L329,"OK")>0,"OK","-"))) -> - | L49: =IF(COUNTIF(Detalhamento!A9:A329,A49)=0,"-",IF(COUNTIFS(Detalhamento!A9:A329,A49,Detalhamento!M9:M329,"Pendente")>0,"Pendente",IF(COUNTIFS(Detalhamento!A9:A329,A49,Detalhamento!M9:M329,"OK")>0,"OK","-"))) -> - | M49: =IF(COUNTIF(Detalhamento!A9:A329,A49)=0,"-",IF(COUNTIFS(Detalhamento!A9:A329,A49,Detalhamento!N9:N329,"Pendente")>0,"Pendente",IF(COUNTIFS(Detalhamento!A9:A329,A49,Detalhamento!N9:N329,"OK")>0,"OK","-"))) -> - | O49: Original | P49: =IF(A49="",0,COUNTIF(Detalhamento!A9:A329,A49)) -> 0 | Q49: =IF(A49="",0,COUNTIFS(Detalhamento!A9:A329,A49,Detalhamento!H9:H329,"Concluído")) -> 0 | R49: =IFERROR(IF(P49=0,"",Q49/P49),"")
A50: 5.1 | B50: Demolicão manual de alvenaria de tijolos furados, contrapiso de 5 cm no deposito 5, inclusive empilhamento dentro do canteiro de servico. | C50: Andar 8 | D50: 46064 | E50: 46094 | F50: =IF(OR($D50="",$E50=""),"Sem data",IF($E50<TODAY(),"Atrasado",IF($D50>TODAY(),"A iniciar","Em andamento"))) -> Atrasado | I50: =IF(COUNTIF(Detalhamento!A9:A329,A50)=0,"-",IF(COUNTIFS(Detalhamento!A9:A329,A50,Detalhamento!J9:J329,"Pendente")>0,"Pendente",IF(COUNTIFS(Detalhamento!A9:A329,A50,Detalhamento!J9:J329,"OK")>0,"OK","-"))) -> - | J50: =IF(COUNTIF(Detalhamento!A9:A329,A50)=0,"-",IF(COUNTIFS(Detalhamento!A9:A329,A50,Detalhamento!K9:K329,"Pendente")>0,"Pendente",IF(COUNTIFS(Detalhamento!A9:A329,A50,Detalhamento!K9:K329,"OK")>0,"OK","-"))) -> - | K50: =IF(COUNTIF(Detalhamento!A9:A329,A50)=0,"-",IF(COUNTIFS(Detalhamento!A9:A329,A50,Detalhamento!L9:L329,"Pendente")>0,"Pendente",IF(COUNTIFS(Detalhamento!A9:A329,A50,Detalhamento!L9:L329,"OK")>0,"OK","-"))) -> - | L50: =IF(COUNTIF(Detalhamento!A9:A329,A50)=0,"-",IF(COUNTIFS(Detalhamento!A9:A329,A50,Detalhamento!M9:M329,"Pendente")>0,"Pendente",IF(COUNTIFS(Detalhamento!A9:A329,A50,Detalhamento!M9:M329,"OK")>0,"OK","-"))) -> - | M50: =IF(COUNTIF(Detalhamento!A9:A329,A50)=0,"-",IF(COUNTIFS(Detalhamento!A9:A329,A50,Detalhamento!N9:N329,"Pendente")>0,"Pendente",IF(COUNTIFS(Detalhamento!A9:A329,A50,Detalhamento!N9:N329,"OK")>0,"OK","-"))) -> - | O50: Original | P50: =IF(A50="",0,COUNTIF(Detalhamento!A9:A329,A50)) -> 7 | Q50: =IF(A50="",0,COUNTIFS(Detalhamento!A9:A329,A50,Detalhamento!H9:H329,"Concluído")) -> 0 | R50: =IFERROR(IF(P50=0,"",Q50/P50),"") -> 0
A51: 5.2 | B51: Demolição controlada e monitrada para rebaixamento da laje e abertura na laje e paredes em concreto armado | C51: Andar 8 | D51: 46089 | E51: 46103 | F51: =IF(OR($D51="",$E51=""),"Sem data",IF($E51<TODAY(),"Atrasado",IF($D51>TODAY(),"A iniciar","Em andamento"))) -> Atrasado | I51: =IF(COUNTIF(Detalhamento!A9:A329,A51)=0,"-",IF(COUNTIFS(Detalhamento!A9:A329,A51,Detalhamento!J9:J329,"Pendente")>0,"Pendente",IF(COUNTIFS(Detalhamento!A9:A329,A51,Detalhamento!J9:J329,"OK")>0,"OK","-"))) -> - | J51: =IF(COUNTIF(Detalhamento!A9:A329,A51)=0,"-",IF(COUNTIFS(Detalhamento!A9:A329,A51,Detalhamento!K9:K329,"Pendente")>0,"Pendente",IF(COUNTIFS(Detalhamento!A9:A329,A51,Detalhamento!K9:K329,"OK")>0,"OK","-"))) -> - | K51: =IF(COUNTIF(Detalhamento!A9:A329,A51)=0,"-",IF(COUNTIFS(Detalhamento!A9:A329,A51,Detalhamento!L9:L329,"Pendente")>0,"Pendente",IF(COUNTIFS(Detalhamento!A9:A329,A51,Detalhamento!L9:L329,"OK")>0,"OK","-"))) -> - | L51: =IF(COUNTIF(Detalhamento!A9:A329,A51)=0,"-",IF(COUNTIFS(Detalhamento!A9:A329,A51,Detalhamento!M9:M329,"Pendente")>0,"Pendente",IF(COUNTIFS(Detalhamento!A9:A329,A51,Detalhamento!M9:M329,"OK")>0,"OK","-"))) -> - | M51: =IF(COUNTIF(Detalhamento!A9:A329,A51)=0,"-",IF(COUNTIFS(Detalhamento!A9:A329,A51,Detalhamento!N9:N329,"Pendente")>0,"Pendente",IF(COUNTIFS(Detalhamento!A9:A329,A51,Detalhamento!N9:N329,"OK")>0,"OK","-"))) -> - | O51: Original | P51: =IF(A51="",0,COUNTIF(Detalhamento!A9:A329,A51)) -> 8 | Q51: =IF(A51="",0,COUNTIFS(Detalhamento!A9:A329,A51,Detalhamento!H9:H329,"Concluído")) -> 0 | R51: =IFERROR(IF(P51=0,"",Q51/P51),"") -> 0
A52: 5.3 | B52: Transporte de entulho e grades | C52: Andar 8 | D52: 46064 | E52: 46184 | F52: =IF(OR($D52="",$E52=""),"Sem data",IF($E52<TODAY(),"Atrasado",IF($D52>TODAY(),"A iniciar","Em andamento"))) -> Atrasado | I52: =IF(COUNTIF(Detalhamento!A9:A329,A52)=0,"-",IF(COUNTIFS(Detalhamento!A9:A329,A52,Detalhamento!J9:J329,"Pendente")>0,"Pendente",IF(COUNTIFS(Detalhamento!A9:A329,A52,Detalhamento!J9:J329,"OK")>0,"OK","-"))) -> - | J52: =IF(COUNTIF(Detalhamento!A9:A329,A52)=0,"-",IF(COUNTIFS(Detalhamento!A9:A329,A52,Detalhamento!K9:K329,"Pendente")>0,"Pendente",IF(COUNTIFS(Detalhamento!A9:A329,A52,Detalhamento!K9:K329,"OK")>0,"OK","-"))) -> - | K52: =IF(COUNTIF(Detalhamento!A9:A329,A52)=0,"-",IF(COUNTIFS(Detalhamento!A9:A329,A52,Detalhamento!L9:L329,"Pendente")>0,"Pendente",IF(COUNTIFS(Detalhamento!A9:A329,A52,Detalhamento!L9:L329,"OK")>0,"OK","-"))) -> - | L52: =IF(COUNTIF(Detalhamento!A9:A329,A52)=0,"-",IF(COUNTIFS(Detalhamento!A9:A329,A52,Detalhamento!M9:M329,"Pendente")>0,"Pendente",IF(COUNTIFS(Detalhamento!A9:A329,A52,Detalhamento!M9:M329,"OK")>0,"OK","-"))) -> - | M52: =IF(COUNTIF(Detalhamento!A9:A329,A52)=0,"-",IF(COUNTIFS(Detalhamento!A9:A329,A52,Detalhamento!N9:N329,"Pendente")>0,"Pendente",IF(COUNTIFS(Detalhamento!A9:A329,A52,Detalhamento!N9:N329,"OK")>0,"OK","-"))) -> - | O52: Original | P52: =IF(A52="",0,COUNTIF(Detalhamento!A9:A329,A52)) -> 5 | Q52: =IF(A52="",0,COUNTIFS(Detalhamento!A9:A329,A52,Detalhamento!H9:H329,"Concluído")) -> 0 | R52: =IFERROR(IF(P52=0,"",Q52/P52),"") -> 0
A53: 5.4 | B53: Caçamba para entulho 4m³ | C53: Andar 8 | D53: 46064 | E53: 46202 | F53: =IF(OR($D53="",$E53=""),"Sem data",IF($E53<TODAY(),"Atrasado",IF($D53>TODAY(),"A iniciar","Em andamento"))) -> Em andamento | I53: =IF(COUNTIF(Detalhamento!A9:A329,A53)=0,"-",IF(COUNTIFS(Detalhamento!A9:A329,A53,Detalhamento!J9:J329,"Pendente")>0,"Pendente",IF(COUNTIFS(Detalhamento!A9:A329,A53,Detalhamento!J9:J329,"OK")>0,"OK","-"))) -> - | J53: =IF(COUNTIF(Detalhamento!A9:A329,A53)=0,"-",IF(COUNTIFS(Detalhamento!A9:A329,A53,Detalhamento!K9:K329,"Pendente")>0,"Pendente",IF(COUNTIFS(Detalhamento!A9:A329,A53,Detalhamento!K9:K329,"OK")>0,"OK","-"))) -> - | K53: =IF(COUNTIF(Detalhamento!A9:A329,A53)=0,"-",IF(COUNTIFS(Detalhamento!A9:A329,A53,Detalhamento!L9:L329,"Pendente")>0,"Pendente",IF(COUNTIFS(Detalhamento!A9:A329,A53,Detalhamento!L9:L329,"OK")>0,"OK","-"))) -> - | L53: =IF(COUNTIF(Detalhamento!A9:A329,A53)=0,"-",IF(COUNTIFS(Detalhamento!A9:A329,A53,Detalhamento!M9:M329,"Pendente")>0,"Pendente",IF(COUNTIFS(Detalhamento!A9:A329,A53,Detalhamento!M9:M329,"OK")>0,"OK","-"))) -> - | M53: =IF(COUNTIF(Detalhamento!A9:A329,A53)=0,"-",IF(COUNTIFS(Detalhamento!A9:A329,A53,Detalhamento!N9:N329,"Pendente")>0,"Pendente",IF(COUNTIFS(Detalhamento!A9:A329,A53,Detalhamento!N9:N329,"OK")>0,"OK","-"))) -> - | O53: Original | P53: =IF(A53="",0,COUNTIF(Detalhamento!A9:A329,A53)) -> 5 | Q53: =IF(A53="",0,COUNTIFS(Detalhamento!A9:A329,A53,Detalhamento!H9:H329,"Concluído")) -> 0 | R53: =IFERROR(IF(P53=0,"",Q53/P53),"") -> 0
A54: 5.5 | B54: Transporte de entulho | C54: Andar 8 | D54: 46187 | E54: 46394 | F54: =IF(OR($D54="",$E54=""),"Sem data",IF($E54<TODAY(),"Atrasado",IF($D54>TODAY(),"A iniciar","Em andamento"))) -> Em andamento | I54: =IF(COUNTIF(Detalhamento!A9:A329,A54)=0,"-",IF(COUNTIFS(Detalhamento!A9:A329,A54,Detalhamento!J9:J329,"Pendente")>0,"Pendente",IF(COUNTIFS(Detalhamento!A9:A329,A54,Detalhamento!J9:J329,"OK")>0,"OK","-"))) -> - | J54: =IF(COUNTIF(Detalhamento!A9:A329,A54)=0,"-",IF(COUNTIFS(Detalhamento!A9:A329,A54,Detalhamento!K9:K329,"Pendente")>0,"Pendente",IF(COUNTIFS(Detalhamento!A9:A329,A54,Detalhamento!K9:K329,"OK")>0,"OK","-"))) -> - | K54: =IF(COUNTIF(Detalhamento!A9:A329,A54)=0,"-",IF(COUNTIFS(Detalhamento!A9:A329,A54,Detalhamento!L9:L329,"Pendente")>0,"Pendente",IF(COUNTIFS(Detalhamento!A9:A329,A54,Detalhamento!L9:L329,"OK")>0,"OK","-"))) -> - | L54: =IF(COUNTIF(Detalhamento!A9:A329,A54)=0,"-",IF(COUNTIFS(Detalhamento!A9:A329,A54,Detalhamento!M9:M329,"Pendente")>0,"Pendente",IF(COUNTIFS(Detalhamento!A9:A329,A54,Detalhamento!M9:M329,"OK")>0,"OK","-"))) -> - | M54: =IF(COUNTIF(Detalhamento!A9:A329,A54)=0,"-",IF(COUNTIFS(Detalhamento!A9:A329,A54,Detalhamento!N9:N329,"Pendente")>0,"Pendente",IF(COUNTIFS(Detalhamento!A9:A329,A54,Detalhamento!N9:N329,"OK")>0,"OK","-"))) -> - | O54: Original | P54: =IF(A54="",0,COUNTIF(Detalhamento!A9:A329,A54)) -> 5 | Q54: =IF(A54="",0,COUNTIFS(Detalhamento!A9:A329,A54,Detalhamento!H9:H329,"Concluído")) -> 0 | R54: =IFERROR(IF(P54=0,"",Q54/P54),"") -> 0
A55: 5.6 | B55: Montagem e desmontagem de andaime direcional estrutural com chumbadores e plataforma e sistema de decida | C55: Andar 8 | D55: 46145 | E55: 46191 | F55: =IF(OR($D55="",$E55=""),"Sem data",IF($E55<TODAY(),"Atrasado",IF($D55>TODAY(),"A iniciar","Em andamento"))) -> Atrasado | I55: =IF(COUNTIF(Detalhamento!A9:A329,A55)=0,"-",IF(COUNTIFS(Detalhamento!A9:A329,A55,Detalhamento!J9:J329,"Pendente")>0,"Pendente",IF(COUNTIFS(Detalhamento!A9:A329,A55,Detalhamento!J9:J329,"OK")>0,"OK","-"))) -> - | J55: =IF(COUNTIF(Detalhamento!A9:A329,A55)=0,"-",IF(COUNTIFS(Detalhamento!A9:A329,A55,Detalhamento!K9:K329,"Pendente")>0,"Pendente",IF(COUNTIFS(Detalhamento!A9:A329,A55,Detalhamento!K9:K329,"OK")>0,"OK","-"))) -> - | K55: =IF(COUNTIF(Detalhamento!A9:A329,A55)=0,"-",IF(COUNTIFS(Detalhamento!A9:A329,A55,Detalhamento!L9:L329,"Pendente")>0,"Pendente",IF(COUNTIFS(Detalhamento!A9:A329,A55,Detalhamento!L9:L329,"OK")>0,"OK","-"))) -> - | L55: =IF(COUNTIF(Detalhamento!A9:A329,A55)=0,"-",IF(COUNTIFS(Detalhamento!A9:A329,A55,Detalhamento!M9:M329,"Pendente")>0,"Pendente",IF(COUNTIFS(Detalhamento!A9:A329,A55,Detalhamento!M9:M329,"OK")>0,"OK","-"))) -> - | M55: =IF(COUNTIF(Detalhamento!A9:A329,A55)=0,"-",IF(COUNTIFS(Detalhamento!A9:A329,A55,Detalhamento!N9:N329,"Pendente")>0,"Pendente",IF(COUNTIFS(Detalhamento!A9:A329,A55,Detalhamento!N9:N329,"OK")>0,"OK","-"))) -> - | O55: Original | P55: =IF(A55="",0,COUNTIF(Detalhamento!A9:A329,A55)) -> 7 | Q55: =IF(A55="",0,COUNTIFS(Detalhamento!A9:A329,A55,Detalhamento!H9:H329,"Concluído")) -> 0 | R55: =IFERROR(IF(P55=0,"",Q55/P55),"") -> 0
A56: 5.7 | B56: Retiro porta existente. | C56: Andar 8 | D56: 46064 | E56: 46080 | F56: =IF(OR($D56="",$E56=""),"Sem data",IF($E56<TODAY(),"Atrasado",IF($D56>TODAY(),"A iniciar","Em andamento"))) -> Atrasado | I56: =IF(COUNTIF(Detalhamento!A9:A329,A56)=0,"-",IF(COUNTIFS(Detalhamento!A9:A329,A56,Detalhamento!J9:J329,"Pendente")>0,"Pendente",IF(COUNTIFS(Detalhamento!A9:A329,A56,Detalhamento!J9:J329,"OK")>0,"OK","-"))) -> - | J56: =IF(COUNTIF(Detalhamento!A9:A329,A56)=0,"-",IF(COUNTIFS(Detalhamento!A9:A329,A56,Detalhamento!K9:K329,"Pendente")>0,"Pendente",IF(COUNTIFS(Detalhamento!A9:A329,A56,Detalhamento!K9:K329,"OK")>0,"OK","-"))) -> - | K56: =IF(COUNTIF(Detalhamento!A9:A329,A56)=0,"-",IF(COUNTIFS(Detalhamento!A9:A329,A56,Detalhamento!L9:L329,"Pendente")>0,"Pendente",IF(COUNTIFS(Detalhamento!A9:A329,A56,Detalhamento!L9:L329,"OK")>0,"OK","-"))) -> - | L56: =IF(COUNTIF(Detalhamento!A9:A329,A56)=0,"-",IF(COUNTIFS(Detalhamento!A9:A329,A56,Detalhamento!M9:M329,"Pendente")>0,"Pendente",IF(COUNTIFS(Detalhamento!A9:A329,A56,Detalhamento!M9:M329,"OK")>0,"OK","-"))) -> - | M56: =IF(COUNTIF(Detalhamento!A9:A329,A56)=0,"-",IF(COUNTIFS(Detalhamento!A9:A329,A56,Detalhamento!N9:N329,"Pendente")>0,"Pendente",IF(COUNTIFS(Detalhamento!A9:A329,A56,Detalhamento!N9:N329,"OK")>0,"OK","-"))) -> - | O56: Original | P56: =IF(A56="",0,COUNTIF(Detalhamento!A9:A329,A56)) -> 6 | Q56: =IF(A56="",0,COUNTIFS(Detalhamento!A9:A329,A56,Detalhamento!H9:H329,"Concluído")) -> 0 | R56: =IFERROR(IF(P56=0,"",Q56/P56),"") -> 0
A57: 5.8 | B57: Demolição controlada e monitorada do cocreto para abertura das novas portas | C57: Andar 8 | D57: 46089 | E57: 46122 | F57: =IF(OR($D57="",$E57=""),"Sem data",IF($E57<TODAY(),"Atrasado",IF($D57>TODAY(),"A iniciar","Em andamento"))) -> Atrasado | I57: =IF(COUNTIF(Detalhamento!A9:A329,A57)=0,"-",IF(COUNTIFS(Detalhamento!A9:A329,A57,Detalhamento!J9:J329,"Pendente")>0,"Pendente",IF(COUNTIFS(Detalhamento!A9:A329,A57,Detalhamento!J9:J329,"OK")>0,"OK","-"))) -> - | J57: =IF(COUNTIF(Detalhamento!A9:A329,A57)=0,"-",IF(COUNTIFS(Detalhamento!A9:A329,A57,Detalhamento!K9:K329,"Pendente")>0,"Pendente",IF(COUNTIFS(Detalhamento!A9:A329,A57,Detalhamento!K9:K329,"OK")>0,"OK","-"))) -> - | K57: =IF(COUNTIF(Detalhamento!A9:A329,A57)=0,"-",IF(COUNTIFS(Detalhamento!A9:A329,A57,Detalhamento!L9:L329,"Pendente")>0,"Pendente",IF(COUNTIFS(Detalhamento!A9:A329,A57,Detalhamento!L9:L329,"OK")>0,"OK","-"))) -> - | L57: =IF(COUNTIF(Detalhamento!A9:A329,A57)=0,"-",IF(COUNTIFS(Detalhamento!A9:A329,A57,Detalhamento!M9:M329,"Pendente")>0,"Pendente",IF(COUNTIFS(Detalhamento!A9:A329,A57,Detalhamento!M9:M329,"OK")>0,"OK","-"))) -> - | M57: =IF(COUNTIF(Detalhamento!A9:A329,A57)=0,"-",IF(COUNTIFS(Detalhamento!A9:A329,A57,Detalhamento!N9:N329,"Pendente")>0,"Pendente",IF(COUNTIFS(Detalhamento!A9:A329,A57,Detalhamento!N9:N329,"OK")>0,"OK","-"))) -> - | O57: Original | P57: =IF(A57="",0,COUNTIF(Detalhamento!A9:A329,A57)) -> 7 | Q57: =IF(A57="",0,COUNTIFS(Detalhamento!A9:A329,A57,Detalhamento!H9:H329,"Concluído")) -> 0 | R57: =IFERROR(IF(P57=0,"",Q57/P57),"") -> 0
A58: 5.9 | B58: Demolição do suporte em concreto do velho sistema de ar-condicionado e nivelamento bruto do piso | C58: Andar 8 | D58: 46077 | E58: 46094 | F58: =IF(OR($D58="",$E58=""),"Sem data",IF($E58<TODAY(),"Atrasado",IF($D58>TODAY(),"A iniciar","Em andamento"))) -> Atrasado | I58: =IF(COUNTIF(Detalhamento!A9:A329,A58)=0,"-",IF(COUNTIFS(Detalhamento!A9:A329,A58,Detalhamento!J9:J329,"Pendente")>0,"Pendente",IF(COUNTIFS(Detalhamento!A9:A329,A58,Detalhamento!J9:J329,"OK")>0,"OK","-"))) -> - | J58: =IF(COUNTIF(Detalhamento!A9:A329,A58)=0,"-",IF(COUNTIFS(Detalhamento!A9:A329,A58,Detalhamento!K9:K329,"Pendente")>0,"Pendente",IF(COUNTIFS(Detalhamento!A9:A329,A58,Detalhamento!K9:K329,"OK")>0,"OK","-"))) -> - | K58: =IF(COUNTIF(Detalhamento!A9:A329,A58)=0,"-",IF(COUNTIFS(Detalhamento!A9:A329,A58,Detalhamento!L9:L329,"Pendente")>0,"Pendente",IF(COUNTIFS(Detalhamento!A9:A329,A58,Detalhamento!L9:L329,"OK")>0,"OK","-"))) -> - | L58: =IF(COUNTIF(Detalhamento!A9:A329,A58)=0,"-",IF(COUNTIFS(Detalhamento!A9:A329,A58,Detalhamento!M9:M329,"Pendente")>0,"Pendente",IF(COUNTIFS(Detalhamento!A9:A329,A58,Detalhamento!M9:M329,"OK")>0,"OK","-"))) -> - | M58: =IF(COUNTIF(Detalhamento!A9:A329,A58)=0,"-",IF(COUNTIFS(Detalhamento!A9:A329,A58,Detalhamento!N9:N329,"Pendente")>0,"Pendente",IF(COUNTIFS(Detalhamento!A9:A329,A58,Detalhamento!N9:N329,"OK")>0,"OK","-"))) -> - | O58: Original | P58: =IF(A58="",0,COUNTIF(Detalhamento!A9:A329,A58)) -> 5 | Q58: =IF(A58="",0,COUNTIFS(Detalhamento!A9:A329,A58,Detalhamento!H9:H329,"Concluído")) -> 0 | R58: =IFERROR(IF(P58=0,"",Q58/P58),"") -> 0
A59: 5.10 | B59: Ampliamento laje +36,55 | C59: Andar 8 | D59: 46161 | E59: 46180 | F59: =IF(OR($D59="",$E59=""),"Sem data",IF($E59<TODAY(),"Atrasado",IF($D59>TODAY(),"A iniciar","Em andamento"))) -> Atrasado | I59: =IF(COUNTIF(Detalhamento!A9:A329,A59)=0,"-",IF(COUNTIFS(Detalhamento!A9:A329,A59,Detalhamento!J9:J329,"Pendente")>0,"Pendente",IF(COUNTIFS(Detalhamento!A9:A329,A59,Detalhamento!J9:J329,"OK")>0,"OK","-"))) -> - | J59: =IF(COUNTIF(Detalhamento!A9:A329,A59)=0,"-",IF(COUNTIFS(Detalhamento!A9:A329,A59,Detalhamento!K9:K329,"Pendente")>0,"Pendente",IF(COUNTIFS(Detalhamento!A9:A329,A59,Detalhamento!K9:K329,"OK")>0,"OK","-"))) -> - | K59: =IF(COUNTIF(Detalhamento!A9:A329,A59)=0,"-",IF(COUNTIFS(Detalhamento!A9:A329,A59,Detalhamento!L9:L329,"Pendente")>0,"Pendente",IF(COUNTIFS(Detalhamento!A9:A329,A59,Detalhamento!L9:L329,"OK")>0,"OK","-"))) -> - | L59: =IF(COUNTIF(Detalhamento!A9:A329,A59)=0,"-",IF(COUNTIFS(Detalhamento!A9:A329,A59,Detalhamento!M9:M329,"Pendente")>0,"Pendente",IF(COUNTIFS(Detalhamento!A9:A329,A59,Detalhamento!M9:M329,"OK")>0,"OK","-"))) -> - | M59: =IF(COUNTIF(Detalhamento!A9:A329,A59)=0,"-",IF(COUNTIFS(Detalhamento!A9:A329,A59,Detalhamento!N9:N329,"Pendente")>0,"Pendente",IF(COUNTIFS(Detalhamento!A9:A329,A59,Detalhamento!N9:N329,"OK")>0,"OK","-"))) -> - | O59: Original | P59: =IF(A59="",0,COUNTIF(Detalhamento!A9:A329,A59)) -> 8 | Q59: =IF(A59="",0,COUNTIFS(Detalhamento!A9:A329,A59,Detalhamento!H9:H329,"Concluído")) -> 0 | R59: =IFERROR(IF(P59=0,"",Q59/P59),"") -> 0
A60: 5.11 | B60: Realização da nova janela considerando as aberturas já existentes e os fechamentos com tijolos onde necessarios. | C60: Andar 8 | D60: 46076 | E60: 46086 | F60: =IF(OR($D60="",$E60=""),"Sem data",IF($E60<TODAY(),"Atrasado",IF($D60>TODAY(),"A iniciar","Em andamento"))) -> Atrasado | I60: =IF(COUNTIF(Detalhamento!A9:A329,A60)=0,"-",IF(COUNTIFS(Detalhamento!A9:A329,A60,Detalhamento!J9:J329,"Pendente")>0,"Pendente",IF(COUNTIFS(Detalhamento!A9:A329,A60,Detalhamento!J9:J329,"OK")>0,"OK","-"))) -> - | J60: =IF(COUNTIF(Detalhamento!A9:A329,A60)=0,"-",IF(COUNTIFS(Detalhamento!A9:A329,A60,Detalhamento!K9:K329,"Pendente")>0,"Pendente",IF(COUNTIFS(Detalhamento!A9:A329,A60,Detalhamento!K9:K329,"OK")>0,"OK","-"))) -> - | K60: =IF(COUNTIF(Detalhamento!A9:A329,A60)=0,"-",IF(COUNTIFS(Detalhamento!A9:A329,A60,Detalhamento!L9:L329,"Pendente")>0,"Pendente",IF(COUNTIFS(Detalhamento!A9:A329,A60,Detalhamento!L9:L329,"OK")>0,"OK","-"))) -> - | L60: =IF(COUNTIF(Detalhamento!A9:A329,A60)=0,"-",IF(COUNTIFS(Detalhamento!A9:A329,A60,Detalhamento!M9:M329,"Pendente")>0,"Pendente",IF(COUNTIFS(Detalhamento!A9:A329,A60,Detalhamento!M9:M329,"OK")>0,"OK","-"))) -> - | M60: =IF(COUNTIF(Detalhamento!A9:A329,A60)=0,"-",IF(COUNTIFS(Detalhamento!A9:A329,A60,Detalhamento!N9:N329,"Pendente")>0,"Pendente",IF(COUNTIFS(Detalhamento!A9:A329,A60,Detalhamento!N9:N329,"OK")>0,"OK","-"))) -> - | O60: Original | P60: =IF(A60="",0,COUNTIF(Detalhamento!A9:A329,A60)) -> 5 | Q60: =IF(A60="",0,COUNTIFS(Detalhamento!A9:A329,A60,Detalhamento!H9:H329,"Concluído")) -> 0 | R60: =IFERROR(IF(P60=0,"",Q60/P60),"") -> 0
A61: 5.12 | B61: Recupero com lixamento física de paredes e tetos | C61: Andar 8 | F61: =IF(OR($D61="",$E61=""),"Sem data",IF($E61<TODAY(),"Atrasado",IF($D61>TODAY(),"A iniciar","Em andamento"))) -> Sem data | I61: =IF(COUNTIF(Detalhamento!A9:A329,A61)=0,"-",IF(COUNTIFS(Detalhamento!A9:A329,A61,Detalhamento!J9:J329,"Pendente")>0,"Pendente",IF(COUNTIFS(Detalhamento!A9:A329,A61,Detalhamento!J9:J329,"OK")>0,"OK","-"))) -> - | J61: =IF(COUNTIF(Detalhamento!A9:A329,A61)=0,"-",IF(COUNTIFS(Detalhamento!A9:A329,A61,Detalhamento!K9:K329,"Pendente")>0,"Pendente",IF(COUNTIFS(Detalhamento!A9:A329,A61,Detalhamento!K9:K329,"OK")>0,"OK","-"))) -> - | K61: =IF(COUNTIF(Detalhamento!A9:A329,A61)=0,"-",IF(COUNTIFS(Detalhamento!A9:A329,A61,Detalhamento!L9:L329,"Pendente")>0,"Pendente",IF(COUNTIFS(Detalhamento!A9:A329,A61,Detalhamento!L9:L329,"OK")>0,"OK","-"))) -> - | L61: =IF(COUNTIF(Detalhamento!A9:A329,A61)=0,"-",IF(COUNTIFS(Detalhamento!A9:A329,A61,Detalhamento!M9:M329,"Pendente")>0,"Pendente",IF(COUNTIFS(Detalhamento!A9:A329,A61,Detalhamento!M9:M329,"OK")>0,"OK","-"))) -> - | M61: =IF(COUNTIF(Detalhamento!A9:A329,A61)=0,"-",IF(COUNTIFS(Detalhamento!A9:A329,A61,Detalhamento!N9:N329,"Pendente")>0,"Pendente",IF(COUNTIFS(Detalhamento!A9:A329,A61,Detalhamento!N9:N329,"OK")>0,"OK","-"))) -> - | O61: Original | P61: =IF(A61="",0,COUNTIF(Detalhamento!A9:A329,A61)) -> 10 | Q61: =IF(A61="",0,COUNTIFS(Detalhamento!A9:A329,A61,Detalhamento!H9:H329,"Concluído")) -> 0 | R61: =IFERROR(IF(P61=0,"",Q61/P61),"") -> 0
A62: 5.13 | B62: Construção da separação das duas novas portas e da parede de separação do novo corredor verso externo. | C62: Andar 8 | D62: 46111 | E62: 46136 | F62: =IF(OR($D62="",$E62=""),"Sem data",IF($E62<TODAY(),"Atrasado",IF($D62>TODAY(),"A iniciar","Em andamento"))) -> Atrasado | I62: =IF(COUNTIF(Detalhamento!A9:A329,A62)=0,"-",IF(COUNTIFS(Detalhamento!A9:A329,A62,Detalhamento!J9:J329,"Pendente")>0,"Pendente",IF(COUNTIFS(Detalhamento!A9:A329,A62,Detalhamento!J9:J329,"OK")>0,"OK","-"))) -> - | J62: =IF(COUNTIF(Detalhamento!A9:A329,A62)=0,"-",IF(COUNTIFS(Detalhamento!A9:A329,A62,Detalhamento!K9:K329,"Pendente")>0,"Pendente",IF(COUNTIFS(Detalhamento!A9:A329,A62,Detalhamento!K9:K329,"OK")>0,"OK","-"))) -> - | K62: =IF(COUNTIF(Detalhamento!A9:A329,A62)=0,"-",IF(COUNTIFS(Detalhamento!A9:A329,A62,Detalhamento!L9:L329,"Pendente")>0,"Pendente",IF(COUNTIFS(Detalhamento!A9:A329,A62,Detalhamento!L9:L329,"OK")>0,"OK","-"))) -> - | L62: =IF(COUNTIF(Detalhamento!A9:A329,A62)=0,"-",IF(COUNTIFS(Detalhamento!A9:A329,A62,Detalhamento!M9:M329,"Pendente")>0,"Pendente",IF(COUNTIFS(Detalhamento!A9:A329,A62,Detalhamento!M9:M329,"OK")>0,"OK","-"))) -> - | M62: =IF(COUNTIF(Detalhamento!A9:A329,A62)=0,"-",IF(COUNTIFS(Detalhamento!A9:A329,A62,Detalhamento!N9:N329,"Pendente")>0,"Pendente",IF(COUNTIFS(Detalhamento!A9:A329,A62,Detalhamento!N9:N329,"OK")>0,"OK","-"))) -> - | O62: Original | P62: =IF(A62="",0,COUNTIF(Detalhamento!A9:A329,A62)) -> 7 | Q62: =IF(A62="",0,COUNTIFS(Detalhamento!A9:A329,A62,Detalhamento!H9:H329,"Concluído")) -> 0 | R62: =IFERROR(IF(P62=0,"",Q62/P62),"") -> 0
A63: 5.14 | B63: Reforma sistema de elétrica e hidráulica a vista existente com substitução e embutimento no forro o na parede ex area tecnica | C63: Andar 8 | D63: 46271 | E63: 46317 | F63: =IF(OR($D63="",$E63=""),"Sem data",IF($E63<TODAY(),"Atrasado",IF($D63>TODAY(),"A iniciar","Em andamento"))) -> A iniciar | I63: =IF(COUNTIF(Detalhamento!A9:A329,A63)=0,"-",IF(COUNTIFS(Detalhamento!A9:A329,A63,Detalhamento!J9:J329,"Pendente")>0,"Pendente",IF(COUNTIFS(Detalhamento!A9:A329,A63,Detalhamento!J9:J329,"OK")>0,"OK","-"))) -> - | J63: =IF(COUNTIF(Detalhamento!A9:A329,A63)=0,"-",IF(COUNTIFS(Detalhamento!A9:A329,A63,Detalhamento!K9:K329,"Pendente")>0,"Pendente",IF(COUNTIFS(Detalhamento!A9:A329,A63,Detalhamento!K9:K329,"OK")>0,"OK","-"))) -> - | K63: =IF(COUNTIF(Detalhamento!A9:A329,A63)=0,"-",IF(COUNTIFS(Detalhamento!A9:A329,A63,Detalhamento!L9:L329,"Pendente")>0,"Pendente",IF(COUNTIFS(Detalhamento!A9:A329,A63,Detalhamento!L9:L329,"OK")>0,"OK","-"))) -> - | L63: =IF(COUNTIF(Detalhamento!A9:A329,A63)=0,"-",IF(COUNTIFS(Detalhamento!A9:A329,A63,Detalhamento!M9:M329,"Pendente")>0,"Pendente",IF(COUNTIFS(Detalhamento!A9:A329,A63,Detalhamento!M9:M329,"OK")>0,"OK","-"))) -> - | M63: =IF(COUNTIF(Detalhamento!A9:A329,A63)=0,"-",IF(COUNTIFS(Detalhamento!A9:A329,A63,Detalhamento!N9:N329,"Pendente")>0,"Pendente",IF(COUNTIFS(Detalhamento!A9:A329,A63,Detalhamento!N9:N329,"OK")>0,"OK","-"))) -> - | O63: Original | P63: =IF(A63="",0,COUNTIF(Detalhamento!A9:A329,A63)) -> 12 | Q63: =IF(A63="",0,COUNTIFS(Detalhamento!A9:A329,A63,Detalhamento!H9:H329,"Concluído")) -> 0 | R63: =IFERROR(IF(P63=0,"",Q63/P63),"") -> 0
A64: 5.15 | B64: Fornecimento e execução de parede em alvenaria com bloco cimentício, considerando chapisco e reboco (desonerado) | C64: Andar 8 | D64: 46111 | E64: 46136 | F64: =IF(OR($D64="",$E64=""),"Sem data",IF($E64<TODAY(),"Atrasado",IF($D64>TODAY(),"A iniciar","Em andamento"))) -> Atrasado | I64: =IF(COUNTIF(Detalhamento!A9:A329,A64)=0,"-",IF(COUNTIFS(Detalhamento!A9:A329,A64,Detalhamento!J9:J329,"Pendente")>0,"Pendente",IF(COUNTIFS(Detalhamento!A9:A329,A64,Detalhamento!J9:J329,"OK")>0,"OK","-"))) -> - | J64: =IF(COUNTIF(Detalhamento!A9:A329,A64)=0,"-",IF(COUNTIFS(Detalhamento!A9:A329,A64,Detalhamento!K9:K329,"Pendente")>0,"Pendente",IF(COUNTIFS(Detalhamento!A9:A329,A64,Detalhamento!K9:K329,"OK")>0,"OK","-"))) -> - | K64: =IF(COUNTIF(Detalhamento!A9:A329,A64)=0,"-",IF(COUNTIFS(Detalhamento!A9:A329,A64,Detalhamento!L9:L329,"Pendente")>0,"Pendente",IF(COUNTIFS(Detalhamento!A9:A329,A64,Detalhamento!L9:L329,"OK")>0,"OK","-"))) -> - | L64: =IF(COUNTIF(Detalhamento!A9:A329,A64)=0,"-",IF(COUNTIFS(Detalhamento!A9:A329,A64,Detalhamento!M9:M329,"Pendente")>0,"Pendente",IF(COUNTIFS(Detalhamento!A9:A329,A64,Detalhamento!M9:M329,"OK")>0,"OK","-"))) -> - | M64: =IF(COUNTIF(Detalhamento!A9:A329,A64)=0,"-",IF(COUNTIFS(Detalhamento!A9:A329,A64,Detalhamento!N9:N329,"Pendente")>0,"Pendente",IF(COUNTIFS(Detalhamento!A9:A329,A64,Detalhamento!N9:N329,"OK")>0,"OK","-"))) -> - | O64: Original | P64: =IF(A64="",0,COUNTIF(Detalhamento!A9:A329,A64)) -> 9 | Q64: =IF(A64="",0,COUNTIFS(Detalhamento!A9:A329,A64,Detalhamento!H9:H329,"Concluído")) -> 0 | R64: =IFERROR(IF(P64=0,"",Q64/P64),"") -> 0
A65: 5.16 | B65: Forro mineral modular, em placas 625x625 mm ou 625x1250 mm, com acabamento texturizado branco, espessura média de 15 a 20 mm, com propriedades acústicas e térmicas, instalado em estrutura metálica tipo T (aparen­te), com nivelamento e alinhamento conforme projeto. Incluso todos os materiais, cortes, arremates, peças de fixação e mão de obra. | C65: Andar 8 | D65: 46145 | E65: 46177 | F65: =IF(OR($D65="",$E65=""),"Sem data",IF($E65<TODAY(),"Atrasado",IF($D65>TODAY(),"A iniciar","Em andamento"))) -> Atrasado | I65: =IF(COUNTIF(Detalhamento!A9:A329,A65)=0,"-",IF(COUNTIFS(Detalhamento!A9:A329,A65,Detalhamento!J9:J329,"Pendente")>0,"Pendente",IF(COUNTIFS(Detalhamento!A9:A329,A65,Detalhamento!J9:J329,"OK")>0,"OK","-"))) -> - | J65: =IF(COUNTIF(Detalhamento!A9:A329,A65)=0,"-",IF(COUNTIFS(Detalhamento!A9:A329,A65,Detalhamento!K9:K329,"Pendente")>0,"Pendente",IF(COUNTIFS(Detalhamento!A9:A329,A65,Detalhamento!K9:K329,"OK")>0,"OK","-"))) -> - | K65: =IF(COUNTIF(Detalhamento!A9:A329,A65)=0,"-",IF(COUNTIFS(Detalhamento!A9:A329,A65,Detalhamento!L9:L329,"Pendente")>0,"Pendente",IF(COUNTIFS(Detalhamento!A9:A329,A65,Detalhamento!L9:L329,"OK")>0,"OK","-"))) -> - | L65: =IF(COUNTIF(Detalhamento!A9:A329,A65)=0,"-",IF(COUNTIFS(Detalhamento!A9:A329,A65,Detalhamento!M9:M329,"Pendente")>0,"Pendente",IF(COUNTIFS(Detalhamento!A9:A329,A65,Detalhamento!M9:M329,"OK")>0,"OK","-"))) -> - | M65: =IF(COUNTIF(Detalhamento!A9:A329,A65)=0,"-",IF(COUNTIFS(Detalhamento!A9:A329,A65,Detalhamento!N9:N329,"Pendente")>0,"Pendente",IF(COUNTIFS(Detalhamento!A9:A329,A65,Detalhamento!N9:N329,"OK")>0,"OK","-"))) -> - | O65: Original | P65: =IF(A65="",0,COUNTIF(Detalhamento!A9:A329,A65)) -> 10 | Q65: =IF(A65="",0,COUNTIFS(Detalhamento!A9:A329,A65,Detalhamento!H9:H329,"Concluído")) -> 0 | R65: =IFERROR(IF(P65=0,"",Q65/P65),"") -> 0
A66: 5.17 | B66: Fornecimento e instalação de forro de gesso acartonado tipo RU (resistente à umidade – cor verde), fixado em estrutura metálica galvanizada (perfil F530, montantes e guias), com parafusos apropriados, fita telada nas juntas e aplicação de massa para tratamento de emendas. Indicado para áreas úmidas como banheiros e lavabos. Incluso todos os materiais, mão de obra, fixações, nivelamento e limpeza da área. Execução conforme normas técnicas da ABNT e boas práticas de instalação. | C66: Andar 8 | D66: 46138 | E66: 46201 | F66: =IF(OR($D66="",$E66=""),"Sem data",IF($E66<TODAY(),"Atrasado",IF($D66>TODAY(),"A iniciar","Em andamento"))) -> Em andamento | I66: =IF(COUNTIF(Detalhamento!A9:A329,A66)=0,"-",IF(COUNTIFS(Detalhamento!A9:A329,A66,Detalhamento!J9:J329,"Pendente")>0,"Pendente",IF(COUNTIFS(Detalhamento!A9:A329,A66,Detalhamento!J9:J329,"OK")>0,"OK","-"))) -> - | J66: =IF(COUNTIF(Detalhamento!A9:A329,A66)=0,"-",IF(COUNTIFS(Detalhamento!A9:A329,A66,Detalhamento!K9:K329,"Pendente")>0,"Pendente",IF(COUNTIFS(Detalhamento!A9:A329,A66,Detalhamento!K9:K329,"OK")>0,"OK","-"))) -> - | K66: =IF(COUNTIF(Detalhamento!A9:A329,A66)=0,"-",IF(COUNTIFS(Detalhamento!A9:A329,A66,Detalhamento!L9:L329,"Pendente")>0,"Pendente",IF(COUNTIFS(Detalhamento!A9:A329,A66,Detalhamento!L9:L329,"OK")>0,"OK","-"))) -> - | L66: =IF(COUNTIF(Detalhamento!A9:A329,A66)=0,"-",IF(COUNTIFS(Detalhamento!A9:A329,A66,Detalhamento!M9:M329,"Pendente")>0,"Pendente",IF(COUNTIFS(Detalhamento!A9:A329,A66,Detalhamento!M9:M329,"OK")>0,"OK","-"))) -> - | M66: =IF(COUNTIF(Detalhamento!A9:A329,A66)=0,"-",IF(COUNTIFS(Detalhamento!A9:A329,A66,Detalhamento!N9:N329,"Pendente")>0,"Pendente",IF(COUNTIFS(Detalhamento!A9:A329,A66,Detalhamento!N9:N329,"OK")>0,"OK","-"))) -> - | O66: Original | P66: =IF(A66="",0,COUNTIF(Detalhamento!A9:A329,A66)) -> 9 | Q66: =IF(A66="",0,COUNTIFS(Detalhamento!A9:A329,A66,Detalhamento!H9:H329,"Concluído")) -> 0 | R66: =IFERROR(IF(P66=0,"",Q66/P66),"") -> 0
A67: 5.18 | B67: Novo reboco nas paredes e no teto. | C67: Andar 8 | D67: 46129 | E67: 46147 | F67: =IF(OR($D67="",$E67=""),"Sem data",IF($E67<TODAY(),"Atrasado",IF($D67>TODAY(),"A iniciar","Em andamento"))) -> Atrasado | I67: =IF(COUNTIF(Detalhamento!A9:A329,A67)=0,"-",IF(COUNTIFS(Detalhamento!A9:A329,A67,Detalhamento!J9:J329,"Pendente")>0,"Pendente",IF(COUNTIFS(Detalhamento!A9:A329,A67,Detalhamento!J9:J329,"OK")>0,"OK","-"))) -> - | J67: =IF(COUNTIF(Detalhamento!A9:A329,A67)=0,"-",IF(COUNTIFS(Detalhamento!A9:A329,A67,Detalhamento!K9:K329,"Pendente")>0,"Pendente",IF(COUNTIFS(Detalhamento!A9:A329,A67,Detalhamento!K9:K329,"OK")>0,"OK","-"))) -> - | K67: =IF(COUNTIF(Detalhamento!A9:A329,A67)=0,"-",IF(COUNTIFS(Detalhamento!A9:A329,A67,Detalhamento!L9:L329,"Pendente")>0,"Pendente",IF(COUNTIFS(Detalhamento!A9:A329,A67,Detalhamento!L9:L329,"OK")>0,"OK","-"))) -> - | L67: =IF(COUNTIF(Detalhamento!A9:A329,A67)=0,"-",IF(COUNTIFS(Detalhamento!A9:A329,A67,Detalhamento!M9:M329,"Pendente")>0,"Pendente",IF(COUNTIFS(Detalhamento!A9:A329,A67,Detalhamento!M9:M329,"OK")>0,"OK","-"))) -> - | M67: =IF(COUNTIF(Detalhamento!A9:A329,A67)=0,"-",IF(COUNTIFS(Detalhamento!A9:A329,A67,Detalhamento!N9:N329,"Pendente")>0,"Pendente",IF(COUNTIFS(Detalhamento!A9:A329,A67,Detalhamento!N9:N329,"OK")>0,"OK","-"))) -> - | O67: Original | P67: =IF(A67="",0,COUNTIF(Detalhamento!A9:A329,A67)) -> 2 | Q67: =IF(A67="",0,COUNTIFS(Detalhamento!A9:A329,A67,Detalhamento!H9:H329,"Concluído")) -> 0 | R67: =IFERROR(IF(P67=0,"",Q67/P67),"") -> 0
A68: 5.19 | B68: Nivelamento fino do piso. | C68: Andar 8 | D68: 46124 | E68: 46170 | F68: =IF(OR($D68="",$E68=""),"Sem data",IF($E68<TODAY(),"Atrasado",IF($D68>TODAY(),"A iniciar","Em andamento"))) -> Atrasado | I68: =IF(COUNTIF(Detalhamento!A9:A329,A68)=0,"-",IF(COUNTIFS(Detalhamento!A9:A329,A68,Detalhamento!J9:J329,"Pendente")>0,"Pendente",IF(COUNTIFS(Detalhamento!A9:A329,A68,Detalhamento!J9:J329,"OK")>0,"OK","-"))) -> - | J68: =IF(COUNTIF(Detalhamento!A9:A329,A68)=0,"-",IF(COUNTIFS(Detalhamento!A9:A329,A68,Detalhamento!K9:K329,"Pendente")>0,"Pendente",IF(COUNTIFS(Detalhamento!A9:A329,A68,Detalhamento!K9:K329,"OK")>0,"OK","-"))) -> - | K68: =IF(COUNTIF(Detalhamento!A9:A329,A68)=0,"-",IF(COUNTIFS(Detalhamento!A9:A329,A68,Detalhamento!L9:L329,"Pendente")>0,"Pendente",IF(COUNTIFS(Detalhamento!A9:A329,A68,Detalhamento!L9:L329,"OK")>0,"OK","-"))) -> - | L68: =IF(COUNTIF(Detalhamento!A9:A329,A68)=0,"-",IF(COUNTIFS(Detalhamento!A9:A329,A68,Detalhamento!M9:M329,"Pendente")>0,"Pendente",IF(COUNTIFS(Detalhamento!A9:A329,A68,Detalhamento!M9:M329,"OK")>0,"OK","-"))) -> - | M68: =IF(COUNTIF(Detalhamento!A9:A329,A68)=0,"-",IF(COUNTIFS(Detalhamento!A9:A329,A68,Detalhamento!N9:N329,"Pendente")>0,"Pendente",IF(COUNTIFS(Detalhamento!A9:A329,A68,Detalhamento!N9:N329,"OK")>0,"OK","-"))) -> - | O68: Original | P68: =IF(A68="",0,COUNTIF(Detalhamento!A9:A329,A68)) -> 7 | Q68: =IF(A68="",0,COUNTIFS(Detalhamento!A9:A329,A68,Detalhamento!H9:H329,"Concluído")) -> 0 | R68: =IFERROR(IF(P68=0,"",Q68/P68),"") -> 0
A69: 5.20 | B69: Azulejo para piso 60 x 60 ou diferente completo de argamassa e rejunte | C69: Andar 8 | D69: 46166 | E69: 46264 | F69: =IF(OR($D69="",$E69=""),"Sem data",IF($E69<TODAY(),"Atrasado",IF($D69>TODAY(),"A iniciar","Em andamento"))) -> Em andamento | I69: =IF(COUNTIF(Detalhamento!A9:A329,A69)=0,"-",IF(COUNTIFS(Detalhamento!A9:A329,A69,Detalhamento!J9:J329,"Pendente")>0,"Pendente",IF(COUNTIFS(Detalhamento!A9:A329,A69,Detalhamento!J9:J329,"OK")>0,"OK","-"))) -> - | J69: =IF(COUNTIF(Detalhamento!A9:A329,A69)=0,"-",IF(COUNTIFS(Detalhamento!A9:A329,A69,Detalhamento!K9:K329,"Pendente")>0,"Pendente",IF(COUNTIFS(Detalhamento!A9:A329,A69,Detalhamento!K9:K329,"OK")>0,"OK","-"))) -> - | K69: =IF(COUNTIF(Detalhamento!A9:A329,A69)=0,"-",IF(COUNTIFS(Detalhamento!A9:A329,A69,Detalhamento!L9:L329,"Pendente")>0,"Pendente",IF(COUNTIFS(Detalhamento!A9:A329,A69,Detalhamento!L9:L329,"OK")>0,"OK","-"))) -> - | L69: =IF(COUNTIF(Detalhamento!A9:A329,A69)=0,"-",IF(COUNTIFS(Detalhamento!A9:A329,A69,Detalhamento!M9:M329,"Pendente")>0,"Pendente",IF(COUNTIFS(Detalhamento!A9:A329,A69,Detalhamento!M9:M329,"OK")>0,"OK","-"))) -> - | M69: =IF(COUNTIF(Detalhamento!A9:A329,A69)=0,"-",IF(COUNTIFS(Detalhamento!A9:A329,A69,Detalhamento!N9:N329,"Pendente")>0,"Pendente",IF(COUNTIFS(Detalhamento!A9:A329,A69,Detalhamento!N9:N329,"OK")>0,"OK","-"))) -> - | O69: Original | P69: =IF(A69="",0,COUNTIF(Detalhamento!A9:A329,A69)) -> 8 | Q69: =IF(A69="",0,COUNTIFS(Detalhamento!A9:A329,A69,Detalhamento!H9:H329,"Concluído")) -> 0 | R69: =IFERROR(IF(P69=0,"",Q69/P69),"") -> 0
A70: 5.21 | B70: Rivestimento banheiro azulejo 40x40 ou diferente,piso e parede completo de argamassa e rejunte | C70: Andar 8 | D70: 46166 | E70: 46264 | F70: =IF(OR($D70="",$E70=""),"Sem data",IF($E70<TODAY(),"Atrasado",IF($D70>TODAY(),"A iniciar","Em andamento"))) -> Em andamento | I70: =IF(COUNTIF(Detalhamento!A9:A329,A70)=0,"-",IF(COUNTIFS(Detalhamento!A9:A329,A70,Detalhamento!J9:J329,"Pendente")>0,"Pendente",IF(COUNTIFS(Detalhamento!A9:A329,A70,Detalhamento!J9:J329,"OK")>0,"OK","-"))) -> - | J70: =IF(COUNTIF(Detalhamento!A9:A329,A70)=0,"-",IF(COUNTIFS(Detalhamento!A9:A329,A70,Detalhamento!K9:K329,"Pendente")>0,"Pendente",IF(COUNTIFS(Detalhamento!A9:A329,A70,Detalhamento!K9:K329,"OK")>0,"OK","-"))) -> - | K70: =IF(COUNTIF(Detalhamento!A9:A329,A70)=0,"-",IF(COUNTIFS(Detalhamento!A9:A329,A70,Detalhamento!L9:L329,"Pendente")>0,"Pendente",IF(COUNTIFS(Detalhamento!A9:A329,A70,Detalhamento!L9:L329,"OK")>0,"OK","-"))) -> - | L70: =IF(COUNTIF(Detalhamento!A9:A329,A70)=0,"-",IF(COUNTIFS(Detalhamento!A9:A329,A70,Detalhamento!M9:M329,"Pendente")>0,"Pendente",IF(COUNTIFS(Detalhamento!A9:A329,A70,Detalhamento!M9:M329,"OK")>0,"OK","-"))) -> - | M70: =IF(COUNTIF(Detalhamento!A9:A329,A70)=0,"-",IF(COUNTIFS(Detalhamento!A9:A329,A70,Detalhamento!N9:N329,"Pendente")>0,"Pendente",IF(COUNTIFS(Detalhamento!A9:A329,A70,Detalhamento!N9:N329,"OK")>0,"OK","-"))) -> - | O70: Original | P70: =IF(A70="",0,COUNTIF(Detalhamento!A9:A329,A70)) -> 8 | Q70: =IF(A70="",0,COUNTIFS(Detalhamento!A9:A329,A70,Detalhamento!H9:H329,"Concluído")) -> 0 | R70: =IFERROR(IF(P70=0,"",Q70/P70),"") -> 0
A71: 5.22 | B71: Azulejo para piso 40 x 40 da externo completo de argamassa e rejunte -Escada | C71: Andar 8 | D71: 46166 | E71: 46264 | F71: =IF(OR($D71="",$E71=""),"Sem data",IF($E71<TODAY(),"Atrasado",IF($D71>TODAY(),"A iniciar","Em andamento"))) -> Em andamento | I71: =IF(COUNTIF(Detalhamento!A9:A329,A71)=0,"-",IF(COUNTIFS(Detalhamento!A9:A329,A71,Detalhamento!J9:J329,"Pendente")>0,"Pendente",IF(COUNTIFS(Detalhamento!A9:A329,A71,Detalhamento!J9:J329,"OK")>0,"OK","-"))) -> - | J71: =IF(COUNTIF(Detalhamento!A9:A329,A71)=0,"-",IF(COUNTIFS(Detalhamento!A9:A329,A71,Detalhamento!K9:K329,"Pendente")>0,"Pendente",IF(COUNTIFS(Detalhamento!A9:A329,A71,Detalhamento!K9:K329,"OK")>0,"OK","-"))) -> - | K71: =IF(COUNTIF(Detalhamento!A9:A329,A71)=0,"-",IF(COUNTIFS(Detalhamento!A9:A329,A71,Detalhamento!L9:L329,"Pendente")>0,"Pendente",IF(COUNTIFS(Detalhamento!A9:A329,A71,Detalhamento!L9:L329,"OK")>0,"OK","-"))) -> - | L71: =IF(COUNTIF(Detalhamento!A9:A329,A71)=0,"-",IF(COUNTIFS(Detalhamento!A9:A329,A71,Detalhamento!M9:M329,"Pendente")>0,"Pendente",IF(COUNTIFS(Detalhamento!A9:A329,A71,Detalhamento!M9:M329,"OK")>0,"OK","-"))) -> - | M71: =IF(COUNTIF(Detalhamento!A9:A329,A71)=0,"-",IF(COUNTIFS(Detalhamento!A9:A329,A71,Detalhamento!N9:N329,"Pendente")>0,"Pendente",IF(COUNTIFS(Detalhamento!A9:A329,A71,Detalhamento!N9:N329,"OK")>0,"OK","-"))) -> - | O71: Original | P71: =IF(A71="",0,COUNTIF(Detalhamento!A9:A329,A71)) -> 8 | Q71: =IF(A71="",0,COUNTIFS(Detalhamento!A9:A329,A71,Detalhamento!H9:H329,"Concluído")) -> 0 | R71: =IFERROR(IF(P71=0,"",Q71/P71),"") -> 0
A72: 5.23 | B72: Piso elevado drenante Ref. Concrefit e Braston | C72: Andar 8 | D72: 46166 | E72: 46264 | F72: =IF(OR($D72="",$E72=""),"Sem data",IF($E72<TODAY(),"Atrasado",IF($D72>TODAY(),"A iniciar","Em andamento"))) -> Em andamento | I72: =IF(COUNTIF(Detalhamento!A9:A329,A72)=0,"-",IF(COUNTIFS(Detalhamento!A9:A329,A72,Detalhamento!J9:J329,"Pendente")>0,"Pendente",IF(COUNTIFS(Detalhamento!A9:A329,A72,Detalhamento!J9:J329,"OK")>0,"OK","-"))) -> - | J72: =IF(COUNTIF(Detalhamento!A9:A329,A72)=0,"-",IF(COUNTIFS(Detalhamento!A9:A329,A72,Detalhamento!K9:K329,"Pendente")>0,"Pendente",IF(COUNTIFS(Detalhamento!A9:A329,A72,Detalhamento!K9:K329,"OK")>0,"OK","-"))) -> - | K72: =IF(COUNTIF(Detalhamento!A9:A329,A72)=0,"-",IF(COUNTIFS(Detalhamento!A9:A329,A72,Detalhamento!L9:L329,"Pendente")>0,"Pendente",IF(COUNTIFS(Detalhamento!A9:A329,A72,Detalhamento!L9:L329,"OK")>0,"OK","-"))) -> - | L72: =IF(COUNTIF(Detalhamento!A9:A329,A72)=0,"-",IF(COUNTIFS(Detalhamento!A9:A329,A72,Detalhamento!M9:M329,"Pendente")>0,"Pendente",IF(COUNTIFS(Detalhamento!A9:A329,A72,Detalhamento!M9:M329,"OK")>0,"OK","-"))) -> - | M72: =IF(COUNTIF(Detalhamento!A9:A329,A72)=0,"-",IF(COUNTIFS(Detalhamento!A9:A329,A72,Detalhamento!N9:N329,"Pendente")>0,"Pendente",IF(COUNTIFS(Detalhamento!A9:A329,A72,Detalhamento!N9:N329,"OK")>0,"OK","-"))) -> - | O72: Original | P72: =IF(A72="",0,COUNTIF(Detalhamento!A9:A329,A72)) -> 9 | Q72: =IF(A72="",0,COUNTIFS(Detalhamento!A9:A329,A72,Detalhamento!H9:H329,"Concluído")) -> 0 | R72: =IFERROR(IF(P72=0,"",Q72/P72),"") -> 0
A73: 5.24 | B73: Serviço de preparação de superfície interna para pintura, incluindo limpeza, lixamento, correção de imperfeições com massa corrida (1 a 2 demãos, conforme necessidade), nivelamento da superfície e aplicação de fundo preparador, quando necessário. Incluso todo o material, ferramentas e mão de obra especializada. Execução conforme normas da ABNT e padrão de acabamento especificado em projeto. | C73: Andar 8 | D73: 46264 | E73: 46294 | F73: =IF(OR($D73="",$E73=""),"Sem data",IF($E73<TODAY(),"Atrasado",IF($D73>TODAY(),"A iniciar","Em andamento"))) -> A iniciar | I73: =IF(COUNTIF(Detalhamento!A9:A329,A73)=0,"-",IF(COUNTIFS(Detalhamento!A9:A329,A73,Detalhamento!J9:J329,"Pendente")>0,"Pendente",IF(COUNTIFS(Detalhamento!A9:A329,A73,Detalhamento!J9:J329,"OK")>0,"OK","-"))) -> - | J73: =IF(COUNTIF(Detalhamento!A9:A329,A73)=0,"-",IF(COUNTIFS(Detalhamento!A9:A329,A73,Detalhamento!K9:K329,"Pendente")>0,"Pendente",IF(COUNTIFS(Detalhamento!A9:A329,A73,Detalhamento!K9:K329,"OK")>0,"OK","-"))) -> - | K73: =IF(COUNTIF(Detalhamento!A9:A329,A73)=0,"-",IF(COUNTIFS(Detalhamento!A9:A329,A73,Detalhamento!L9:L329,"Pendente")>0,"Pendente",IF(COUNTIFS(Detalhamento!A9:A329,A73,Detalhamento!L9:L329,"OK")>0,"OK","-"))) -> - | L73: =IF(COUNTIF(Detalhamento!A9:A329,A73)=0,"-",IF(COUNTIFS(Detalhamento!A9:A329,A73,Detalhamento!M9:M329,"Pendente")>0,"Pendente",IF(COUNTIFS(Detalhamento!A9:A329,A73,Detalhamento!M9:M329,"OK")>0,"OK","-"))) -> - | M73: =IF(COUNTIF(Detalhamento!A9:A329,A73)=0,"-",IF(COUNTIFS(Detalhamento!A9:A329,A73,Detalhamento!N9:N329,"Pendente")>0,"Pendente",IF(COUNTIFS(Detalhamento!A9:A329,A73,Detalhamento!N9:N329,"OK")>0,"OK","-"))) -> - | O73: Original | P73: =IF(A73="",0,COUNTIF(Detalhamento!A9:A329,A73)) -> 8 | Q73: =IF(A73="",0,COUNTIFS(Detalhamento!A9:A329,A73,Detalhamento!H9:H329,"Concluído")) -> 0 | R73: =IFERROR(IF(P73=0,"",Q73/P73),"") -> 0
A74: 5.25 | B74: Pintura em paredes e tetos internos com tinta látex PVA ou acrílica (conforme especificação), incluindo 2 a 3 demãos com rolo e pincel, acabamento fosco ou acetinado. Superfície previamente preparada com lixamento, correções com massa corrida e aplicação de fundo preparador, quando necessário. Incluso todos os materiais, proteção das áreas, ferramentas e mão de obra especializada. Execução conforme normas da ABNT. | C74: Andar 8 | D74: 46264 | E74: 46294 | F74: =IF(OR($D74="",$E74=""),"Sem data",IF($E74<TODAY(),"Atrasado",IF($D74>TODAY(),"A iniciar","Em andamento"))) -> A iniciar | I74: =IF(COUNTIF(Detalhamento!A9:A329,A74)=0,"-",IF(COUNTIFS(Detalhamento!A9:A329,A74,Detalhamento!J9:J329,"Pendente")>0,"Pendente",IF(COUNTIFS(Detalhamento!A9:A329,A74,Detalhamento!J9:J329,"OK")>0,"OK","-"))) -> - | J74: =IF(COUNTIF(Detalhamento!A9:A329,A74)=0,"-",IF(COUNTIFS(Detalhamento!A9:A329,A74,Detalhamento!K9:K329,"Pendente")>0,"Pendente",IF(COUNTIFS(Detalhamento!A9:A329,A74,Detalhamento!K9:K329,"OK")>0,"OK","-"))) -> - | K74: =IF(COUNTIF(Detalhamento!A9:A329,A74)=0,"-",IF(COUNTIFS(Detalhamento!A9:A329,A74,Detalhamento!L9:L329,"Pendente")>0,"Pendente",IF(COUNTIFS(Detalhamento!A9:A329,A74,Detalhamento!L9:L329,"OK")>0,"OK","-"))) -> - | L74: =IF(COUNTIF(Detalhamento!A9:A329,A74)=0,"-",IF(COUNTIFS(Detalhamento!A9:A329,A74,Detalhamento!M9:M329,"Pendente")>0,"Pendente",IF(COUNTIFS(Detalhamento!A9:A329,A74,Detalhamento!M9:M329,"OK")>0,"OK","-"))) -> - | M74: =IF(COUNTIF(Detalhamento!A9:A329,A74)=0,"-",IF(COUNTIFS(Detalhamento!A9:A329,A74,Detalhamento!N9:N329,"Pendente")>0,"Pendente",IF(COUNTIFS(Detalhamento!A9:A329,A74,Detalhamento!N9:N329,"OK")>0,"OK","-"))) -> - | O74: Original | P74: =IF(A74="",0,COUNTIF(Detalhamento!A9:A329,A74)) -> 4 | Q74: =IF(A74="",0,COUNTIFS(Detalhamento!A9:A329,A74,Detalhamento!H9:H329,"Concluído")) -> 0 | R74: =IFERROR(IF(P74=0,"",Q74/P74),"") -> 0
A75: 5.26 | B75: Serviço de preparação de superfície externa para pintura, incluindo limpeza manual ou com lavadora de alta pressão, remoção de partes soltas, lixamento, raspagem de tinta antiga, correções com massa acrílica (onde necessário), aplicação de fundo preparador ou selador acrílico, conforme tipo de substrato. Incluso materiais, ferramentas e mão de obra qualificada. Execução conforme normas técnicas da ABNT. | C75: Andar 8 | D75: 46289 | E75: 46310 | F75: =IF(OR($D75="",$E75=""),"Sem data",IF($E75<TODAY(),"Atrasado",IF($D75>TODAY(),"A iniciar","Em andamento"))) -> A iniciar | I75: =IF(COUNTIF(Detalhamento!A9:A329,A75)=0,"-",IF(COUNTIFS(Detalhamento!A9:A329,A75,Detalhamento!J9:J329,"Pendente")>0,"Pendente",IF(COUNTIFS(Detalhamento!A9:A329,A75,Detalhamento!J9:J329,"OK")>0,"OK","-"))) -> - | J75: =IF(COUNTIF(Detalhamento!A9:A329,A75)=0,"-",IF(COUNTIFS(Detalhamento!A9:A329,A75,Detalhamento!K9:K329,"Pendente")>0,"Pendente",IF(COUNTIFS(Detalhamento!A9:A329,A75,Detalhamento!K9:K329,"OK")>0,"OK","-"))) -> - | K75: =IF(COUNTIF(Detalhamento!A9:A329,A75)=0,"-",IF(COUNTIFS(Detalhamento!A9:A329,A75,Detalhamento!L9:L329,"Pendente")>0,"Pendente",IF(COUNTIFS(Detalhamento!A9:A329,A75,Detalhamento!L9:L329,"OK")>0,"OK","-"))) -> - | L75: =IF(COUNTIF(Detalhamento!A9:A329,A75)=0,"-",IF(COUNTIFS(Detalhamento!A9:A329,A75,Detalhamento!M9:M329,"Pendente")>0,"Pendente",IF(COUNTIFS(Detalhamento!A9:A329,A75,Detalhamento!M9:M329,"OK")>0,"OK","-"))) -> - | M75: =IF(COUNTIF(Detalhamento!A9:A329,A75)=0,"-",IF(COUNTIFS(Detalhamento!A9:A329,A75,Detalhamento!N9:N329,"Pendente")>0,"Pendente",IF(COUNTIFS(Detalhamento!A9:A329,A75,Detalhamento!N9:N329,"OK")>0,"OK","-"))) -> - | O75: Original | P75: =IF(A75="",0,COUNTIF(Detalhamento!A9:A329,A75)) -> 8 | Q75: =IF(A75="",0,COUNTIFS(Detalhamento!A9:A329,A75,Detalhamento!H9:H329,"Concluído")) -> 0 | R75: =IFERROR(IF(P75=0,"",Q75/P75),"") -> 0
A76: 5.27 | B76: Pintura em área externa com tinta acrílica premium para fachadas, incluindo preparo da superfície (limpeza, lixamento, correção com massa acrílica onde necessário), aplicação de selador acrílico e 2 demãos de tinta, com acabamento fosco ou semi-brilho, conforme especificações do projeto. Serviço realizado com andaime, equipamentos de segurança e mão de obra especializada. Todos os materiais e insumos inclusos. Execução conforme normas técnicas da ABNT. | C76: Andar 8 | D76: 46289 | E76: 46341 | F76: =IF(OR($D76="",$E76=""),"Sem data",IF($E76<TODAY(),"Atrasado",IF($D76>TODAY(),"A iniciar","Em andamento"))) -> A iniciar | I76: =IF(COUNTIF(Detalhamento!A9:A329,A76)=0,"-",IF(COUNTIFS(Detalhamento!A9:A329,A76,Detalhamento!J9:J329,"Pendente")>0,"Pendente",IF(COUNTIFS(Detalhamento!A9:A329,A76,Detalhamento!J9:J329,"OK")>0,"OK","-"))) -> - | J76: =IF(COUNTIF(Detalhamento!A9:A329,A76)=0,"-",IF(COUNTIFS(Detalhamento!A9:A329,A76,Detalhamento!K9:K329,"Pendente")>0,"Pendente",IF(COUNTIFS(Detalhamento!A9:A329,A76,Detalhamento!K9:K329,"OK")>0,"OK","-"))) -> - | K76: =IF(COUNTIF(Detalhamento!A9:A329,A76)=0,"-",IF(COUNTIFS(Detalhamento!A9:A329,A76,Detalhamento!L9:L329,"Pendente")>0,"Pendente",IF(COUNTIFS(Detalhamento!A9:A329,A76,Detalhamento!L9:L329,"OK")>0,"OK","-"))) -> - | L76: =IF(COUNTIF(Detalhamento!A9:A329,A76)=0,"-",IF(COUNTIFS(Detalhamento!A9:A329,A76,Detalhamento!M9:M329,"Pendente")>0,"Pendente",IF(COUNTIFS(Detalhamento!A9:A329,A76,Detalhamento!M9:M329,"OK")>0,"OK","-"))) -> - | M76: =IF(COUNTIF(Detalhamento!A9:A329,A76)=0,"-",IF(COUNTIFS(Detalhamento!A9:A329,A76,Detalhamento!N9:N329,"Pendente")>0,"Pendente",IF(COUNTIFS(Detalhamento!A9:A329,A76,Detalhamento!N9:N329,"OK")>0,"OK","-"))) -> - | O76: Original | P76: =IF(A76="",0,COUNTIF(Detalhamento!A9:A329,A76)) -> 4 | Q76: =IF(A76="",0,COUNTIFS(Detalhamento!A9:A329,A76,Detalhamento!H9:H329,"Concluído")) -> 0 | R76: =IFERROR(IF(P76=0,"",Q76/P76),"") -> 0
A77: 5.28 | B77: Instalações portas completa | C77: Andar 8 | D77: 46236 | E77: 46264 | F77: =IF(OR($D77="",$E77=""),"Sem data",IF($E77<TODAY(),"Atrasado",IF($D77>TODAY(),"A iniciar","Em andamento"))) -> A iniciar | I77: =IF(COUNTIF(Detalhamento!A9:A329,A77)=0,"-",IF(COUNTIFS(Detalhamento!A9:A329,A77,Detalhamento!J9:J329,"Pendente")>0,"Pendente",IF(COUNTIFS(Detalhamento!A9:A329,A77,Detalhamento!J9:J329,"OK")>0,"OK","-"))) -> - | J77: =IF(COUNTIF(Detalhamento!A9:A329,A77)=0,"-",IF(COUNTIFS(Detalhamento!A9:A329,A77,Detalhamento!K9:K329,"Pendente")>0,"Pendente",IF(COUNTIFS(Detalhamento!A9:A329,A77,Detalhamento!K9:K329,"OK")>0,"OK","-"))) -> - | K77: =IF(COUNTIF(Detalhamento!A9:A329,A77)=0,"-",IF(COUNTIFS(Detalhamento!A9:A329,A77,Detalhamento!L9:L329,"Pendente")>0,"Pendente",IF(COUNTIFS(Detalhamento!A9:A329,A77,Detalhamento!L9:L329,"OK")>0,"OK","-"))) -> - | L77: =IF(COUNTIF(Detalhamento!A9:A329,A77)=0,"-",IF(COUNTIFS(Detalhamento!A9:A329,A77,Detalhamento!M9:M329,"Pendente")>0,"Pendente",IF(COUNTIFS(Detalhamento!A9:A329,A77,Detalhamento!M9:M329,"OK")>0,"OK","-"))) -> - | M77: =IF(COUNTIF(Detalhamento!A9:A329,A77)=0,"-",IF(COUNTIFS(Detalhamento!A9:A329,A77,Detalhamento!N9:N329,"Pendente")>0,"Pendente",IF(COUNTIFS(Detalhamento!A9:A329,A77,Detalhamento!N9:N329,"OK")>0,"OK","-"))) -> - | O77: Original | P77: =IF(A77="",0,COUNTIF(Detalhamento!A9:A329,A77)) -> 6 | Q77: =IF(A77="",0,COUNTIFS(Detalhamento!A9:A329,A77,Detalhamento!H9:H329,"Concluído")) -> 0 | R77: =IFERROR(IF(P77=0,"",Q77/P77),"") -> 0
A78: 5.29 | B78: Instalações nova janela em alumínio perfil Gold e vidro 10 mm | C78: Andar 8 | D78: 46236 | E78: 46264 | F78: =IF(OR($D78="",$E78=""),"Sem data",IF($E78<TODAY(),"Atrasado",IF($D78>TODAY(),"A iniciar","Em andamento"))) -> A iniciar | I78: =IF(COUNTIF(Detalhamento!A9:A329,A78)=0,"-",IF(COUNTIFS(Detalhamento!A9:A329,A78,Detalhamento!J9:J329,"Pendente")>0,"Pendente",IF(COUNTIFS(Detalhamento!A9:A329,A78,Detalhamento!J9:J329,"OK")>0,"OK","-"))) -> - | J78: =IF(COUNTIF(Detalhamento!A9:A329,A78)=0,"-",IF(COUNTIFS(Detalhamento!A9:A329,A78,Detalhamento!K9:K329,"Pendente")>0,"Pendente",IF(COUNTIFS(Detalhamento!A9:A329,A78,Detalhamento!K9:K329,"OK")>0,"OK","-"))) -> - | K78: =IF(COUNTIF(Detalhamento!A9:A329,A78)=0,"-",IF(COUNTIFS(Detalhamento!A9:A329,A78,Detalhamento!L9:L329,"Pendente")>0,"Pendente",IF(COUNTIFS(Detalhamento!A9:A329,A78,Detalhamento!L9:L329,"OK")>0,"OK","-"))) -> - | L78: =IF(COUNTIF(Detalhamento!A9:A329,A78)=0,"-",IF(COUNTIFS(Detalhamento!A9:A329,A78,Detalhamento!M9:M329,"Pendente")>0,"Pendente",IF(COUNTIFS(Detalhamento!A9:A329,A78,Detalhamento!M9:M329,"OK")>0,"OK","-"))) -> - | M78: =IF(COUNTIF(Detalhamento!A9:A329,A78)=0,"-",IF(COUNTIFS(Detalhamento!A9:A329,A78,Detalhamento!N9:N329,"Pendente")>0,"Pendente",IF(COUNTIFS(Detalhamento!A9:A329,A78,Detalhamento!N9:N329,"OK")>0,"OK","-"))) -> - | O78: Original | P78: =IF(A78="",0,COUNTIF(Detalhamento!A9:A329,A78)) -> 5 | Q78: =IF(A78="",0,COUNTIFS(Detalhamento!A9:A329,A78,Detalhamento!H9:H329,"Concluído")) -> 0 | R78: =IFERROR(IF(P78=0,"",Q78/P78),"") -> 0
A79: 5.30 | B79: Instalação esquadrias spbre trilho perfil Gold vidro 10 mm | C79: Andar 8 | D79: 46236 | E79: 46264 | F79: =IF(OR($D79="",$E79=""),"Sem data",IF($E79<TODAY(),"Atrasado",IF($D79>TODAY(),"A iniciar","Em andamento"))) -> A iniciar | I79: =IF(COUNTIF(Detalhamento!A9:A329,A79)=0,"-",IF(COUNTIFS(Detalhamento!A9:A329,A79,Detalhamento!J9:J329,"Pendente")>0,"Pendente",IF(COUNTIFS(Detalhamento!A9:A329,A79,Detalhamento!J9:J329,"OK")>0,"OK","-"))) -> - | J79: =IF(COUNTIF(Detalhamento!A9:A329,A79)=0,"-",IF(COUNTIFS(Detalhamento!A9:A329,A79,Detalhamento!K9:K329,"Pendente")>0,"Pendente",IF(COUNTIFS(Detalhamento!A9:A329,A79,Detalhamento!K9:K329,"OK")>0,"OK","-"))) -> - | K79: =IF(COUNTIF(Detalhamento!A9:A329,A79)=0,"-",IF(COUNTIFS(Detalhamento!A9:A329,A79,Detalhamento!L9:L329,"Pendente")>0,"Pendente",IF(COUNTIFS(Detalhamento!A9:A329,A79,Detalhamento!L9:L329,"OK")>0,"OK","-"))) -> - | L79: =IF(COUNTIF(Detalhamento!A9:A329,A79)=0,"-",IF(COUNTIFS(Detalhamento!A9:A329,A79,Detalhamento!M9:M329,"Pendente")>0,"Pendente",IF(COUNTIFS(Detalhamento!A9:A329,A79,Detalhamento!M9:M329,"OK")>0,"OK","-"))) -> - | M79: =IF(COUNTIF(Detalhamento!A9:A329,A79)=0,"-",IF(COUNTIFS(Detalhamento!A9:A329,A79,Detalhamento!N9:N329,"Pendente")>0,"Pendente",IF(COUNTIFS(Detalhamento!A9:A329,A79,Detalhamento!N9:N329,"OK")>0,"OK","-"))) -> - | O79: Original | P79: =IF(A79="",0,COUNTIF(Detalhamento!A9:A329,A79)) -> 6 | Q79: =IF(A79="",0,COUNTIFS(Detalhamento!A9:A329,A79,Detalhamento!H9:H329,"Concluído")) -> 0 | R79: =IFERROR(IF(P79=0,"",Q79/P79),"") -> 0
A80: 5.31 | B80: Brize externo drenagem a vista | C80: Andar 8 | D80: 46343 | E80: 46378 | F80: =IF(OR($D80="",$E80=""),"Sem data",IF($E80<TODAY(),"Atrasado",IF($D80>TODAY(),"A iniciar","Em andamento"))) -> A iniciar | I80: =IF(COUNTIF(Detalhamento!A9:A329,A80)=0,"-",IF(COUNTIFS(Detalhamento!A9:A329,A80,Detalhamento!J9:J329,"Pendente")>0,"Pendente",IF(COUNTIFS(Detalhamento!A9:A329,A80,Detalhamento!J9:J329,"OK")>0,"OK","-"))) -> - | J80: =IF(COUNTIF(Detalhamento!A9:A329,A80)=0,"-",IF(COUNTIFS(Detalhamento!A9:A329,A80,Detalhamento!K9:K329,"Pendente")>0,"Pendente",IF(COUNTIFS(Detalhamento!A9:A329,A80,Detalhamento!K9:K329,"OK")>0,"OK","-"))) -> - | K80: =IF(COUNTIF(Detalhamento!A9:A329,A80)=0,"-",IF(COUNTIFS(Detalhamento!A9:A329,A80,Detalhamento!L9:L329,"Pendente")>0,"Pendente",IF(COUNTIFS(Detalhamento!A9:A329,A80,Detalhamento!L9:L329,"OK")>0,"OK","-"))) -> - | L80: =IF(COUNTIF(Detalhamento!A9:A329,A80)=0,"-",IF(COUNTIFS(Detalhamento!A9:A329,A80,Detalhamento!M9:M329,"Pendente")>0,"Pendente",IF(COUNTIFS(Detalhamento!A9:A329,A80,Detalhamento!M9:M329,"OK")>0,"OK","-"))) -> - | M80: =IF(COUNTIF(Detalhamento!A9:A329,A80)=0,"-",IF(COUNTIFS(Detalhamento!A9:A329,A80,Detalhamento!N9:N329,"Pendente")>0,"Pendente",IF(COUNTIFS(Detalhamento!A9:A329,A80,Detalhamento!N9:N329,"OK")>0,"OK","-"))) -> - | O80: Original | P80: =IF(A80="",0,COUNTIF(Detalhamento!A9:A329,A80)) -> 5 | Q80: =IF(A80="",0,COUNTIFS(Detalhamento!A9:A329,A80,Detalhamento!H9:H329,"Concluído")) -> 0 | R80: =IFERROR(IF(P80=0,"",Q80/P80),"") -> 0
A81: 5.32 | B81: Fornecimento e instalação de QUADRO DE DITRIBUÇÃO completo, embutido ou sobreposto, em caixa metálica ou termoplástica, com porta, pintura eletrostática e grau de proteção mínimo IP40. Equipado com disjuntores termomagnéticos monopolares, bipolares ou tripolares conforme projeto, barramentos de fase, neutro e terra, trilho DIN, identificação dos circuitos e acessórios. Inclusos todos os materiais, componentes, mão de obra para montagem, fixação, aterramento, testes e conformidade com as normas técnicas vigentes (NBR 5410 e NR-10). | C81: Andar 8 | D81: 46111 | E81: 46142 | F81: =IF(OR($D81="",$E81=""),"Sem data",IF($E81<TODAY(),"Atrasado",IF($D81>TODAY(),"A iniciar","Em andamento"))) -> Atrasado | I81: =IF(COUNTIF(Detalhamento!A9:A329,A81)=0,"-",IF(COUNTIFS(Detalhamento!A9:A329,A81,Detalhamento!J9:J329,"Pendente")>0,"Pendente",IF(COUNTIFS(Detalhamento!A9:A329,A81,Detalhamento!J9:J329,"OK")>0,"OK","-"))) -> - | J81: =IF(COUNTIF(Detalhamento!A9:A329,A81)=0,"-",IF(COUNTIFS(Detalhamento!A9:A329,A81,Detalhamento!K9:K329,"Pendente")>0,"Pendente",IF(COUNTIFS(Detalhamento!A9:A329,A81,Detalhamento!K9:K329,"OK")>0,"OK","-"))) -> - | K81: =IF(COUNTIF(Detalhamento!A9:A329,A81)=0,"-",IF(COUNTIFS(Detalhamento!A9:A329,A81,Detalhamento!L9:L329,"Pendente")>0,"Pendente",IF(COUNTIFS(Detalhamento!A9:A329,A81,Detalhamento!L9:L329,"OK")>0,"OK","-"))) -> - | L81: =IF(COUNTIF(Detalhamento!A9:A329,A81)=0,"-",IF(COUNTIFS(Detalhamento!A9:A329,A81,Detalhamento!M9:M329,"Pendente")>0,"Pendente",IF(COUNTIFS(Detalhamento!A9:A329,A81,Detalhamento!M9:M329,"OK")>0,"OK","-"))) -> - | M81: =IF(COUNTIF(Detalhamento!A9:A329,A81)=0,"-",IF(COUNTIFS(Detalhamento!A9:A329,A81,Detalhamento!N9:N329,"Pendente")>0,"Pendente",IF(COUNTIFS(Detalhamento!A9:A329,A81,Detalhamento!N9:N329,"OK")>0,"OK","-"))) -> - | O81: Original | P81: =IF(A81="",0,COUNTIF(Detalhamento!A9:A329,A81)) -> 7 | Q81: =IF(A81="",0,COUNTIFS(Detalhamento!A9:A329,A81,Detalhamento!H9:H329,"Concluído")) -> 0 | R81: =IFERROR(IF(P81=0,"",Q81/P81),"") -> 0
A82: 5.33 | B82: Execução de ponto elétrico completo embutido, composto por 1 tomada 2P+T 20A, 220V e 1 ponto de luz (sem luminária), com fornecimento e instalação de eletrodutos rígidos PVC, caixas de embutir, cabos de cobre ( 25 tomadas + 25 ponto de luz) antichama (fase, neutro e terra), conectores, suporte e espelho. Inclui instalação da infraestrutura embutida em alvenaria, passagem dos condutores, fixação dos mecanismos, identificação dos circuitos e testes de funcionamento, conforme NBR 5410 e NR-10. | C82: Andar 8 | D82: 46111 | E82: 46142 | F82: =IF(OR($D82="",$E82=""),"Sem data",IF($E82<TODAY(),"Atrasado",IF($D82>TODAY(),"A iniciar","Em andamento"))) -> Atrasado | I82: =IF(COUNTIF(Detalhamento!A9:A329,A82)=0,"-",IF(COUNTIFS(Detalhamento!A9:A329,A82,Detalhamento!J9:J329,"Pendente")>0,"Pendente",IF(COUNTIFS(Detalhamento!A9:A329,A82,Detalhamento!J9:J329,"OK")>0,"OK","-"))) -> - | J82: =IF(COUNTIF(Detalhamento!A9:A329,A82)=0,"-",IF(COUNTIFS(Detalhamento!A9:A329,A82,Detalhamento!K9:K329,"Pendente")>0,"Pendente",IF(COUNTIFS(Detalhamento!A9:A329,A82,Detalhamento!K9:K329,"OK")>0,"OK","-"))) -> - | K82: =IF(COUNTIF(Detalhamento!A9:A329,A82)=0,"-",IF(COUNTIFS(Detalhamento!A9:A329,A82,Detalhamento!L9:L329,"Pendente")>0,"Pendente",IF(COUNTIFS(Detalhamento!A9:A329,A82,Detalhamento!L9:L329,"OK")>0,"OK","-"))) -> - | L82: =IF(COUNTIF(Detalhamento!A9:A329,A82)=0,"-",IF(COUNTIFS(Detalhamento!A9:A329,A82,Detalhamento!M9:M329,"Pendente")>0,"Pendente",IF(COUNTIFS(Detalhamento!A9:A329,A82,Detalhamento!M9:M329,"OK")>0,"OK","-"))) -> - | M82: =IF(COUNTIF(Detalhamento!A9:A329,A82)=0,"-",IF(COUNTIFS(Detalhamento!A9:A329,A82,Detalhamento!N9:N329,"Pendente")>0,"Pendente",IF(COUNTIFS(Detalhamento!A9:A329,A82,Detalhamento!N9:N329,"OK")>0,"OK","-"))) -> - | O82: Original | P82: =IF(A82="",0,COUNTIF(Detalhamento!A9:A329,A82)) -> 5 | Q82: =IF(A82="",0,COUNTIFS(Detalhamento!A9:A329,A82,Detalhamento!H9:H329,"Concluído")) -> 0 | R82: =IFERROR(IF(P82=0,"",Q82/P82),"") -> 0
A83: 5.34 | B83: Ponto de água fria em PVC Marrom | C83: Andar 8 | D83: 46111 | E83: 46142 | F83: =IF(OR($D83="",$E83=""),"Sem data",IF($E83<TODAY(),"Atrasado",IF($D83>TODAY(),"A iniciar","Em andamento"))) -> Atrasado | I83: =IF(COUNTIF(Detalhamento!A9:A329,A83)=0,"-",IF(COUNTIFS(Detalhamento!A9:A329,A83,Detalhamento!J9:J329,"Pendente")>0,"Pendente",IF(COUNTIFS(Detalhamento!A9:A329,A83,Detalhamento!J9:J329,"OK")>0,"OK","-"))) -> - | J83: =IF(COUNTIF(Detalhamento!A9:A329,A83)=0,"-",IF(COUNTIFS(Detalhamento!A9:A329,A83,Detalhamento!K9:K329,"Pendente")>0,"Pendente",IF(COUNTIFS(Detalhamento!A9:A329,A83,Detalhamento!K9:K329,"OK")>0,"OK","-"))) -> - | K83: =IF(COUNTIF(Detalhamento!A9:A329,A83)=0,"-",IF(COUNTIFS(Detalhamento!A9:A329,A83,Detalhamento!L9:L329,"Pendente")>0,"Pendente",IF(COUNTIFS(Detalhamento!A9:A329,A83,Detalhamento!L9:L329,"OK")>0,"OK","-"))) -> - | L83: =IF(COUNTIF(Detalhamento!A9:A329,A83)=0,"-",IF(COUNTIFS(Detalhamento!A9:A329,A83,Detalhamento!M9:M329,"Pendente")>0,"Pendente",IF(COUNTIFS(Detalhamento!A9:A329,A83,Detalhamento!M9:M329,"OK")>0,"OK","-"))) -> - | M83: =IF(COUNTIF(Detalhamento!A9:A329,A83)=0,"-",IF(COUNTIFS(Detalhamento!A9:A329,A83,Detalhamento!N9:N329,"Pendente")>0,"Pendente",IF(COUNTIFS(Detalhamento!A9:A329,A83,Detalhamento!N9:N329,"OK")>0,"OK","-"))) -> - | O83: Original | P83: =IF(A83="",0,COUNTIF(Detalhamento!A9:A329,A83)) -> 2 | Q83: =IF(A83="",0,COUNTIFS(Detalhamento!A9:A329,A83,Detalhamento!H9:H329,"Concluído")) -> 0 | R83: =IFERROR(IF(P83=0,"",Q83/P83),"") -> 0
A84: 5.35 | B84: Ponto de esgoto em PVC branco 50mm ou 100mm | C84: Andar 8 | D84: 46111 | E84: 46142 | F84: =IF(OR($D84="",$E84=""),"Sem data",IF($E84<TODAY(),"Atrasado",IF($D84>TODAY(),"A iniciar","Em andamento"))) -> Atrasado | I84: =IF(COUNTIF(Detalhamento!A9:A329,A84)=0,"-",IF(COUNTIFS(Detalhamento!A9:A329,A84,Detalhamento!J9:J329,"Pendente")>0,"Pendente",IF(COUNTIFS(Detalhamento!A9:A329,A84,Detalhamento!J9:J329,"OK")>0,"OK","-"))) -> - | J84: =IF(COUNTIF(Detalhamento!A9:A329,A84)=0,"-",IF(COUNTIFS(Detalhamento!A9:A329,A84,Detalhamento!K9:K329,"Pendente")>0,"Pendente",IF(COUNTIFS(Detalhamento!A9:A329,A84,Detalhamento!K9:K329,"OK")>0,"OK","-"))) -> - | K84: =IF(COUNTIF(Detalhamento!A9:A329,A84)=0,"-",IF(COUNTIFS(Detalhamento!A9:A329,A84,Detalhamento!L9:L329,"Pendente")>0,"Pendente",IF(COUNTIFS(Detalhamento!A9:A329,A84,Detalhamento!L9:L329,"OK")>0,"OK","-"))) -> - | L84: =IF(COUNTIF(Detalhamento!A9:A329,A84)=0,"-",IF(COUNTIFS(Detalhamento!A9:A329,A84,Detalhamento!M9:M329,"Pendente")>0,"Pendente",IF(COUNTIFS(Detalhamento!A9:A329,A84,Detalhamento!M9:M329,"OK")>0,"OK","-"))) -> - | M84: =IF(COUNTIF(Detalhamento!A9:A329,A84)=0,"-",IF(COUNTIFS(Detalhamento!A9:A329,A84,Detalhamento!N9:N329,"Pendente")>0,"Pendente",IF(COUNTIFS(Detalhamento!A9:A329,A84,Detalhamento!N9:N329,"OK")>0,"OK","-"))) -> - | O84: Original | P84: =IF(A84="",0,COUNTIF(Detalhamento!A9:A329,A84)) -> 2 | Q84: =IF(A84="",0,COUNTIFS(Detalhamento!A9:A329,A84,Detalhamento!H9:H329,"Concluído")) -> 0 | R84: =IFERROR(IF(P84=0,"",Q84/P84),"") -> 0
A85: 5.36 | B85: Louças sanitárias com gabinete em MDF ultra | C85: Andar 8 | D85: 46327 | E85: 46338 | F85: =IF(OR($D85="",$E85=""),"Sem data",IF($E85<TODAY(),"Atrasado",IF($D85>TODAY(),"A iniciar","Em andamento"))) -> A iniciar | I85: =IF(COUNTIF(Detalhamento!A9:A329,A85)=0,"-",IF(COUNTIFS(Detalhamento!A9:A329,A85,Detalhamento!J9:J329,"Pendente")>0,"Pendente",IF(COUNTIFS(Detalhamento!A9:A329,A85,Detalhamento!J9:J329,"OK")>0,"OK","-"))) -> - | J85: =IF(COUNTIF(Detalhamento!A9:A329,A85)=0,"-",IF(COUNTIFS(Detalhamento!A9:A329,A85,Detalhamento!K9:K329,"Pendente")>0,"Pendente",IF(COUNTIFS(Detalhamento!A9:A329,A85,Detalhamento!K9:K329,"OK")>0,"OK","-"))) -> - | K85: =IF(COUNTIF(Detalhamento!A9:A329,A85)=0,"-",IF(COUNTIFS(Detalhamento!A9:A329,A85,Detalhamento!L9:L329,"Pendente")>0,"Pendente",IF(COUNTIFS(Detalhamento!A9:A329,A85,Detalhamento!L9:L329,"OK")>0,"OK","-"))) -> - | L85: =IF(COUNTIF(Detalhamento!A9:A329,A85)=0,"-",IF(COUNTIFS(Detalhamento!A9:A329,A85,Detalhamento!M9:M329,"Pendente")>0,"Pendente",IF(COUNTIFS(Detalhamento!A9:A329,A85,Detalhamento!M9:M329,"OK")>0,"OK","-"))) -> - | M85: =IF(COUNTIF(Detalhamento!A9:A329,A85)=0,"-",IF(COUNTIFS(Detalhamento!A9:A329,A85,Detalhamento!N9:N329,"Pendente")>0,"Pendente",IF(COUNTIFS(Detalhamento!A9:A329,A85,Detalhamento!N9:N329,"OK")>0,"OK","-"))) -> - | O85: Original | P85: =IF(A85="",0,COUNTIF(Detalhamento!A9:A329,A85)) -> 0 | Q85: =IF(A85="",0,COUNTIFS(Detalhamento!A9:A329,A85,Detalhamento!H9:H329,"Concluído")) -> 0 | R85: =IFERROR(IF(P85=0,"",Q85/P85),"")
A86: 5.37 | B86: Metais sanitários | C86: Andar 8 | D86: 46327 | E86: 46338 | F86: =IF(OR($D86="",$E86=""),"Sem data",IF($E86<TODAY(),"Atrasado",IF($D86>TODAY(),"A iniciar","Em andamento"))) -> A iniciar | I86: =IF(COUNTIF(Detalhamento!A9:A329,A86)=0,"-",IF(COUNTIFS(Detalhamento!A9:A329,A86,Detalhamento!J9:J329,"Pendente")>0,"Pendente",IF(COUNTIFS(Detalhamento!A9:A329,A86,Detalhamento!J9:J329,"OK")>0,"OK","-"))) -> - | J86: =IF(COUNTIF(Detalhamento!A9:A329,A86)=0,"-",IF(COUNTIFS(Detalhamento!A9:A329,A86,Detalhamento!K9:K329,"Pendente")>0,"Pendente",IF(COUNTIFS(Detalhamento!A9:A329,A86,Detalhamento!K9:K329,"OK")>0,"OK","-"))) -> - | K86: =IF(COUNTIF(Detalhamento!A9:A329,A86)=0,"-",IF(COUNTIFS(Detalhamento!A9:A329,A86,Detalhamento!L9:L329,"Pendente")>0,"Pendente",IF(COUNTIFS(Detalhamento!A9:A329,A86,Detalhamento!L9:L329,"OK")>0,"OK","-"))) -> - | L86: =IF(COUNTIF(Detalhamento!A9:A329,A86)=0,"-",IF(COUNTIFS(Detalhamento!A9:A329,A86,Detalhamento!M9:M329,"Pendente")>0,"Pendente",IF(COUNTIFS(Detalhamento!A9:A329,A86,Detalhamento!M9:M329,"OK")>0,"OK","-"))) -> - | M86: =IF(COUNTIF(Detalhamento!A9:A329,A86)=0,"-",IF(COUNTIFS(Detalhamento!A9:A329,A86,Detalhamento!N9:N329,"Pendente")>0,"Pendente",IF(COUNTIFS(Detalhamento!A9:A329,A86,Detalhamento!N9:N329,"OK")>0,"OK","-"))) -> - | O86: Original | P86: =IF(A86="",0,COUNTIF(Detalhamento!A9:A329,A86)) -> 0 | Q86: =IF(A86="",0,COUNTIFS(Detalhamento!A9:A329,A86,Detalhamento!H9:H329,"Concluído")) -> 0 | R86: =IFERROR(IF(P86=0,"",Q86/P86),"")
A87: 5.38 | B87: Revestimento de parede em madeira ripada cumarú | C87: Andar 8 | D87: 46327 | E87: 46352 | F87: =IF(OR($D87="",$E87=""),"Sem data",IF($E87<TODAY(),"Atrasado",IF($D87>TODAY(),"A iniciar","Em andamento"))) -> A iniciar | I87: =IF(COUNTIF(Detalhamento!A9:A329,A87)=0,"-",IF(COUNTIFS(Detalhamento!A9:A329,A87,Detalhamento!J9:J329,"Pendente")>0,"Pendente",IF(COUNTIFS(Detalhamento!A9:A329,A87,Detalhamento!J9:J329,"OK")>0,"OK","-"))) -> - | J87: =IF(COUNTIF(Detalhamento!A9:A329,A87)=0,"-",IF(COUNTIFS(Detalhamento!A9:A329,A87,Detalhamento!K9:K329,"Pendente")>0,"Pendente",IF(COUNTIFS(Detalhamento!A9:A329,A87,Detalhamento!K9:K329,"OK")>0,"OK","-"))) -> - | K87: =IF(COUNTIF(Detalhamento!A9:A329,A87)=0,"-",IF(COUNTIFS(Detalhamento!A9:A329,A87,Detalhamento!L9:L329,"Pendente")>0,"Pendente",IF(COUNTIFS(Detalhamento!A9:A329,A87,Detalhamento!L9:L329,"OK")>0,"OK","-"))) -> - | L87: =IF(COUNTIF(Detalhamento!A9:A329,A87)=0,"-",IF(COUNTIFS(Detalhamento!A9:A329,A87,Detalhamento!M9:M329,"Pendente")>0,"Pendente",IF(COUNTIFS(Detalhamento!A9:A329,A87,Detalhamento!M9:M329,"OK")>0,"OK","-"))) -> - | M87: =IF(COUNTIF(Detalhamento!A9:A329,A87)=0,"-",IF(COUNTIFS(Detalhamento!A9:A329,A87,Detalhamento!N9:N329,"Pendente")>0,"Pendente",IF(COUNTIFS(Detalhamento!A9:A329,A87,Detalhamento!N9:N329,"OK")>0,"OK","-"))) -> - | O87: Original | P87: =IF(A87="",0,COUNTIF(Detalhamento!A9:A329,A87)) -> 0 | Q87: =IF(A87="",0,COUNTIFS(Detalhamento!A9:A329,A87,Detalhamento!H9:H329,"Concluído")) -> 0 | R87: =IFERROR(IF(P87=0,"",Q87/P87),"")
A88: 5.39 | B88: Luminárias 50w tipo embutido quadrado (ref.: embutido quadrado PAR 20 50w, Labluz) | C88: Andar 8 | D88: 46278 | E88: 46317 | F88: =IF(OR($D88="",$E88=""),"Sem data",IF($E88<TODAY(),"Atrasado",IF($D88>TODAY(),"A iniciar","Em andamento"))) -> A iniciar | I88: =IF(COUNTIF(Detalhamento!A9:A329,A88)=0,"-",IF(COUNTIFS(Detalhamento!A9:A329,A88,Detalhamento!J9:J329,"Pendente")>0,"Pendente",IF(COUNTIFS(Detalhamento!A9:A329,A88,Detalhamento!J9:J329,"OK")>0,"OK","-"))) -> - | J88: =IF(COUNTIF(Detalhamento!A9:A329,A88)=0,"-",IF(COUNTIFS(Detalhamento!A9:A329,A88,Detalhamento!K9:K329,"Pendente")>0,"Pendente",IF(COUNTIFS(Detalhamento!A9:A329,A88,Detalhamento!K9:K329,"OK")>0,"OK","-"))) -> - | K88: =IF(COUNTIF(Detalhamento!A9:A329,A88)=0,"-",IF(COUNTIFS(Detalhamento!A9:A329,A88,Detalhamento!L9:L329,"Pendente")>0,"Pendente",IF(COUNTIFS(Detalhamento!A9:A329,A88,Detalhamento!L9:L329,"OK")>0,"OK","-"))) -> - | L88: =IF(COUNTIF(Detalhamento!A9:A329,A88)=0,"-",IF(COUNTIFS(Detalhamento!A9:A329,A88,Detalhamento!M9:M329,"Pendente")>0,"Pendente",IF(COUNTIFS(Detalhamento!A9:A329,A88,Detalhamento!M9:M329,"OK")>0,"OK","-"))) -> - | M88: =IF(COUNTIF(Detalhamento!A9:A329,A88)=0,"-",IF(COUNTIFS(Detalhamento!A9:A329,A88,Detalhamento!N9:N329,"Pendente")>0,"Pendente",IF(COUNTIFS(Detalhamento!A9:A329,A88,Detalhamento!N9:N329,"OK")>0,"OK","-"))) -> - | O88: Original | P88: =IF(A88="",0,COUNTIF(Detalhamento!A9:A329,A88)) -> 0 | Q88: =IF(A88="",0,COUNTIFS(Detalhamento!A9:A329,A88,Detalhamento!H9:H329,"Concluído")) -> 0 | R88: =IFERROR(IF(P88=0,"",Q88/P88),"")
A89: 5.40 | B89: Luminária Calha Embutir 2 Lâmpadas LED T8 | C89: Andar 8 | D89: 46278 | E89: 46317 | F89: =IF(OR($D89="",$E89=""),"Sem data",IF($E89<TODAY(),"Atrasado",IF($D89>TODAY(),"A iniciar","Em andamento"))) -> A iniciar | I89: =IF(COUNTIF(Detalhamento!A9:A329,A89)=0,"-",IF(COUNTIFS(Detalhamento!A9:A329,A89,Detalhamento!J9:J329,"Pendente")>0,"Pendente",IF(COUNTIFS(Detalhamento!A9:A329,A89,Detalhamento!J9:J329,"OK")>0,"OK","-"))) -> - | J89: =IF(COUNTIF(Detalhamento!A9:A329,A89)=0,"-",IF(COUNTIFS(Detalhamento!A9:A329,A89,Detalhamento!K9:K329,"Pendente")>0,"Pendente",IF(COUNTIFS(Detalhamento!A9:A329,A89,Detalhamento!K9:K329,"OK")>0,"OK","-"))) -> - | K89: =IF(COUNTIF(Detalhamento!A9:A329,A89)=0,"-",IF(COUNTIFS(Detalhamento!A9:A329,A89,Detalhamento!L9:L329,"Pendente")>0,"Pendente",IF(COUNTIFS(Detalhamento!A9:A329,A89,Detalhamento!L9:L329,"OK")>0,"OK","-"))) -> - | L89: =IF(COUNTIF(Detalhamento!A9:A329,A89)=0,"-",IF(COUNTIFS(Detalhamento!A9:A329,A89,Detalhamento!M9:M329,"Pendente")>0,"Pendente",IF(COUNTIFS(Detalhamento!A9:A329,A89,Detalhamento!M9:M329,"OK")>0,"OK","-"))) -> - | M89: =IF(COUNTIF(Detalhamento!A9:A329,A89)=0,"-",IF(COUNTIFS(Detalhamento!A9:A329,A89,Detalhamento!N9:N329,"Pendente")>0,"Pendente",IF(COUNTIFS(Detalhamento!A9:A329,A89,Detalhamento!N9:N329,"OK")>0,"OK","-"))) -> - | O89: Original | P89: =IF(A89="",0,COUNTIF(Detalhamento!A9:A329,A89)) -> 0 | Q89: =IF(A89="",0,COUNTIFS(Detalhamento!A9:A329,A89,Detalhamento!H9:H329,"Concluído")) -> 0 | R89: =IFERROR(IF(P89=0,"",Q89/P89),"")
A90: 5.41 | B90: Fita de LED IP68 à prova de água | C90: Andar 8 | D90: 46278 | E90: 46317 | F90: =IF(OR($D90="",$E90=""),"Sem data",IF($E90<TODAY(),"Atrasado",IF($D90>TODAY(),"A iniciar","Em andamento"))) -> A iniciar | I90: =IF(COUNTIF(Detalhamento!A9:A329,A90)=0,"-",IF(COUNTIFS(Detalhamento!A9:A329,A90,Detalhamento!J9:J329,"Pendente")>0,"Pendente",IF(COUNTIFS(Detalhamento!A9:A329,A90,Detalhamento!J9:J329,"OK")>0,"OK","-"))) -> - | J90: =IF(COUNTIF(Detalhamento!A9:A329,A90)=0,"-",IF(COUNTIFS(Detalhamento!A9:A329,A90,Detalhamento!K9:K329,"Pendente")>0,"Pendente",IF(COUNTIFS(Detalhamento!A9:A329,A90,Detalhamento!K9:K329,"OK")>0,"OK","-"))) -> - | K90: =IF(COUNTIF(Detalhamento!A9:A329,A90)=0,"-",IF(COUNTIFS(Detalhamento!A9:A329,A90,Detalhamento!L9:L329,"Pendente")>0,"Pendente",IF(COUNTIFS(Detalhamento!A9:A329,A90,Detalhamento!L9:L329,"OK")>0,"OK","-"))) -> - | L90: =IF(COUNTIF(Detalhamento!A9:A329,A90)=0,"-",IF(COUNTIFS(Detalhamento!A9:A329,A90,Detalhamento!M9:M329,"Pendente")>0,"Pendente",IF(COUNTIFS(Detalhamento!A9:A329,A90,Detalhamento!M9:M329,"OK")>0,"OK","-"))) -> - | M90: =IF(COUNTIF(Detalhamento!A9:A329,A90)=0,"-",IF(COUNTIFS(Detalhamento!A9:A329,A90,Detalhamento!N9:N329,"Pendente")>0,"Pendente",IF(COUNTIFS(Detalhamento!A9:A329,A90,Detalhamento!N9:N329,"OK")>0,"OK","-"))) -> - | O90: Original | P90: =IF(A90="",0,COUNTIF(Detalhamento!A9:A329,A90)) -> 0 | Q90: =IF(A90="",0,COUNTIFS(Detalhamento!A9:A329,A90,Detalhamento!H9:H329,"Concluído")) -> 0 | R90: =IFERROR(IF(P90=0,"",Q90/P90),"")
A91: 5.42 | B91: Iluminação esterna com Fita e Led | C91: Andar 8 | D91: 46278 | E91: 46317 | F91: =IF(OR($D91="",$E91=""),"Sem data",IF($E91<TODAY(),"Atrasado",IF($D91>TODAY(),"A iniciar","Em andamento"))) -> A iniciar | I91: =IF(COUNTIF(Detalhamento!A9:A329,A91)=0,"-",IF(COUNTIFS(Detalhamento!A9:A329,A91,Detalhamento!J9:J329,"Pendente")>0,"Pendente",IF(COUNTIFS(Detalhamento!A9:A329,A91,Detalhamento!J9:J329,"OK")>0,"OK","-"))) -> - | J91: =IF(COUNTIF(Detalhamento!A9:A329,A91)=0,"-",IF(COUNTIFS(Detalhamento!A9:A329,A91,Detalhamento!K9:K329,"Pendente")>0,"Pendente",IF(COUNTIFS(Detalhamento!A9:A329,A91,Detalhamento!K9:K329,"OK")>0,"OK","-"))) -> - | K91: =IF(COUNTIF(Detalhamento!A9:A329,A91)=0,"-",IF(COUNTIFS(Detalhamento!A9:A329,A91,Detalhamento!L9:L329,"Pendente")>0,"Pendente",IF(COUNTIFS(Detalhamento!A9:A329,A91,Detalhamento!L9:L329,"OK")>0,"OK","-"))) -> - | L91: =IF(COUNTIF(Detalhamento!A9:A329,A91)=0,"-",IF(COUNTIFS(Detalhamento!A9:A329,A91,Detalhamento!M9:M329,"Pendente")>0,"Pendente",IF(COUNTIFS(Detalhamento!A9:A329,A91,Detalhamento!M9:M329,"OK")>0,"OK","-"))) -> - | M91: =IF(COUNTIF(Detalhamento!A9:A329,A91)=0,"-",IF(COUNTIFS(Detalhamento!A9:A329,A91,Detalhamento!N9:N329,"Pendente")>0,"Pendente",IF(COUNTIFS(Detalhamento!A9:A329,A91,Detalhamento!N9:N329,"OK")>0,"OK","-"))) -> - | O91: Original | P91: =IF(A91="",0,COUNTIF(Detalhamento!A9:A329,A91)) -> 0 | Q91: =IF(A91="",0,COUNTIFS(Detalhamento!A9:A329,A91,Detalhamento!H9:H329,"Concluído")) -> 0 | R91: =IFERROR(IF(P91=0,"",Q91/P91),"")
A92: 5.43 | B92: Fornecimento e instalação de corrimão em alumínio anodizado ou pintado (conforme especificação), com seção tubular ou retangular, fixado em suportes metálicos ou diretamente na alvenaria ou guarda-corpo, resistente às intempéries e adequado para uso externo. Incluso materiais, suportes, parafusos, buchas, mão de obra para instalação e acabamento final. Execução conforme normas de acessibilidade (NBR 9050) e segurança. | C92: Andar 8 | D92: 46327 | E92: 46352 | F92: =IF(OR($D92="",$E92=""),"Sem data",IF($E92<TODAY(),"Atrasado",IF($D92>TODAY(),"A iniciar","Em andamento"))) -> A iniciar | I92: =IF(COUNTIF(Detalhamento!A9:A329,A92)=0,"-",IF(COUNTIFS(Detalhamento!A9:A329,A92,Detalhamento!J9:J329,"Pendente")>0,"Pendente",IF(COUNTIFS(Detalhamento!A9:A329,A92,Detalhamento!J9:J329,"OK")>0,"OK","-"))) -> - | J92: =IF(COUNTIF(Detalhamento!A9:A329,A92)=0,"-",IF(COUNTIFS(Detalhamento!A9:A329,A92,Detalhamento!K9:K329,"Pendente")>0,"Pendente",IF(COUNTIFS(Detalhamento!A9:A329,A92,Detalhamento!K9:K329,"OK")>0,"OK","-"))) -> - | K92: =IF(COUNTIF(Detalhamento!A9:A329,A92)=0,"-",IF(COUNTIFS(Detalhamento!A9:A329,A92,Detalhamento!L9:L329,"Pendente")>0,"Pendente",IF(COUNTIFS(Detalhamento!A9:A329,A92,Detalhamento!L9:L329,"OK")>0,"OK","-"))) -> - | L92: =IF(COUNTIF(Detalhamento!A9:A329,A92)=0,"-",IF(COUNTIFS(Detalhamento!A9:A329,A92,Detalhamento!M9:M329,"Pendente")>0,"Pendente",IF(COUNTIFS(Detalhamento!A9:A329,A92,Detalhamento!M9:M329,"OK")>0,"OK","-"))) -> - | M92: =IF(COUNTIF(Detalhamento!A9:A329,A92)=0,"-",IF(COUNTIFS(Detalhamento!A9:A329,A92,Detalhamento!N9:N329,"Pendente")>0,"Pendente",IF(COUNTIFS(Detalhamento!A9:A329,A92,Detalhamento!N9:N329,"OK")>0,"OK","-"))) -> - | O92: Original | P92: =IF(A92="",0,COUNTIF(Detalhamento!A9:A329,A92)) -> 0 | Q92: =IF(A92="",0,COUNTIFS(Detalhamento!A9:A329,A92,Detalhamento!H9:H329,"Concluído")) -> 0 | R92: =IFERROR(IF(P92=0,"",Q92/P92),"")
A93: 5.44 | B93: Ar condicionado split - Cassete/split - 24.000 BTUs - Sistema completo + material + rede frigorígena e rede elétrica | C93: Andar 8 | D93: 46141 | E93: 46352 | F93: =IF(OR($D93="",$E93=""),"Sem data",IF($E93<TODAY(),"Atrasado",IF($D93>TODAY(),"A iniciar","Em andamento"))) -> Em andamento | I93: =IF(COUNTIF(Detalhamento!A9:A329,A93)=0,"-",IF(COUNTIFS(Detalhamento!A9:A329,A93,Detalhamento!J9:J329,"Pendente")>0,"Pendente",IF(COUNTIFS(Detalhamento!A9:A329,A93,Detalhamento!J9:J329,"OK")>0,"OK","-"))) -> - | J93: =IF(COUNTIF(Detalhamento!A9:A329,A93)=0,"-",IF(COUNTIFS(Detalhamento!A9:A329,A93,Detalhamento!K9:K329,"Pendente")>0,"Pendente",IF(COUNTIFS(Detalhamento!A9:A329,A93,Detalhamento!K9:K329,"OK")>0,"OK","-"))) -> - | K93: =IF(COUNTIF(Detalhamento!A9:A329,A93)=0,"-",IF(COUNTIFS(Detalhamento!A9:A329,A93,Detalhamento!L9:L329,"Pendente")>0,"Pendente",IF(COUNTIFS(Detalhamento!A9:A329,A93,Detalhamento!L9:L329,"OK")>0,"OK","-"))) -> - | L93: =IF(COUNTIF(Detalhamento!A9:A329,A93)=0,"-",IF(COUNTIFS(Detalhamento!A9:A329,A93,Detalhamento!M9:M329,"Pendente")>0,"Pendente",IF(COUNTIFS(Detalhamento!A9:A329,A93,Detalhamento!M9:M329,"OK")>0,"OK","-"))) -> - | M93: =IF(COUNTIF(Detalhamento!A9:A329,A93)=0,"-",IF(COUNTIFS(Detalhamento!A9:A329,A93,Detalhamento!N9:N329,"Pendente")>0,"Pendente",IF(COUNTIFS(Detalhamento!A9:A329,A93,Detalhamento!N9:N329,"OK")>0,"OK","-"))) -> - | O93: Original | P93: =IF(A93="",0,COUNTIF(Detalhamento!A9:A329,A93)) -> 0 | Q93: =IF(A93="",0,COUNTIFS(Detalhamento!A9:A329,A93,Detalhamento!H9:H329,"Concluído")) -> 0 | R93: =IFERROR(IF(P93=0,"",Q93/P93),"")
A94: 5.45 | B94: REMOÇÃO,MANUTENÇÂO,LIMPEZA E NOVA INSTALAÇÃO DE CONDENSADORAS EXISTENTES NO LOCAL DETERMINADO EM PROJETO (FAÇADAS) COM REAPROVEITAMENTO E INTERLIGAÇÃO COM AS EVAPORADORAS COM DOS DUTOS EM COBRE E PROTEÇÕES ELASTOMÉRICAS PROTETOR TUBOS ISOLANTE TÉRMICO CINZA REF.WESTAFLEXEXISTENTES | C94: Andar 8 | D94: 46243 | E94: 46324 | F94: =IF(OR($D94="",$E94=""),"Sem data",IF($E94<TODAY(),"Atrasado",IF($D94>TODAY(),"A iniciar","Em andamento"))) -> A iniciar | I94: =IF(COUNTIF(Detalhamento!A9:A329,A94)=0,"-",IF(COUNTIFS(Detalhamento!A9:A329,A94,Detalhamento!J9:J329,"Pendente")>0,"Pendente",IF(COUNTIFS(Detalhamento!A9:A329,A94,Detalhamento!J9:J329,"OK")>0,"OK","-"))) -> - | J94: =IF(COUNTIF(Detalhamento!A9:A329,A94)=0,"-",IF(COUNTIFS(Detalhamento!A9:A329,A94,Detalhamento!K9:K329,"Pendente")>0,"Pendente",IF(COUNTIFS(Detalhamento!A9:A329,A94,Detalhamento!K9:K329,"OK")>0,"OK","-"))) -> - | K94: =IF(COUNTIF(Detalhamento!A9:A329,A94)=0,"-",IF(COUNTIFS(Detalhamento!A9:A329,A94,Detalhamento!L9:L329,"Pendente")>0,"Pendente",IF(COUNTIFS(Detalhamento!A9:A329,A94,Detalhamento!L9:L329,"OK")>0,"OK","-"))) -> - | L94: =IF(COUNTIF(Detalhamento!A9:A329,A94)=0,"-",IF(COUNTIFS(Detalhamento!A9:A329,A94,Detalhamento!M9:M329,"Pendente")>0,"Pendente",IF(COUNTIFS(Detalhamento!A9:A329,A94,Detalhamento!M9:M329,"OK")>0,"OK","-"))) -> - | M94: =IF(COUNTIF(Detalhamento!A9:A329,A94)=0,"-",IF(COUNTIFS(Detalhamento!A9:A329,A94,Detalhamento!N9:N329,"Pendente")>0,"Pendente",IF(COUNTIFS(Detalhamento!A9:A329,A94,Detalhamento!N9:N329,"OK")>0,"OK","-"))) -> - | O94: Original | P94: =IF(A94="",0,COUNTIF(Detalhamento!A9:A329,A94)) -> 0 | Q94: =IF(A94="",0,COUNTIFS(Detalhamento!A9:A329,A94,Detalhamento!H9:H329,"Concluído")) -> 0 | R94: =IFERROR(IF(P94=0,"",Q94/P94),"")
A95: 5.46 | B95: Serviço de adequação de impermeabilização em área externa, incluindo demolição pontual do revestimento existente (se necessário), regularização da base com argamassa, aplicação de primer e manta asfáltica ou impermeabilizante cimentício bicomponente, com reforço em áreas de ralos e cantos. Inclusa instalação ou substituição de ralos de descida em PVC ou inox, conexões e vedação com anel de estanqueidade. Incluso todos os materiais, equipamentos e mão de obra especializada. Execução conforme normas da ABNT (NBR 9575 e NBR 9574) | C95: Andar 8 | D95: 46138 | E95: 46197 | F95: =IF(OR($D95="",$E95=""),"Sem data",IF($E95<TODAY(),"Atrasado",IF($D95>TODAY(),"A iniciar","Em andamento"))) -> Atrasado | I95: =IF(COUNTIF(Detalhamento!A9:A329,A95)=0,"-",IF(COUNTIFS(Detalhamento!A9:A329,A95,Detalhamento!J9:J329,"Pendente")>0,"Pendente",IF(COUNTIFS(Detalhamento!A9:A329,A95,Detalhamento!J9:J329,"OK")>0,"OK","-"))) -> - | J95: =IF(COUNTIF(Detalhamento!A9:A329,A95)=0,"-",IF(COUNTIFS(Detalhamento!A9:A329,A95,Detalhamento!K9:K329,"Pendente")>0,"Pendente",IF(COUNTIFS(Detalhamento!A9:A329,A95,Detalhamento!K9:K329,"OK")>0,"OK","-"))) -> - | K95: =IF(COUNTIF(Detalhamento!A9:A329,A95)=0,"-",IF(COUNTIFS(Detalhamento!A9:A329,A95,Detalhamento!L9:L329,"Pendente")>0,"Pendente",IF(COUNTIFS(Detalhamento!A9:A329,A95,Detalhamento!L9:L329,"OK")>0,"OK","-"))) -> - | L95: =IF(COUNTIF(Detalhamento!A9:A329,A95)=0,"-",IF(COUNTIFS(Detalhamento!A9:A329,A95,Detalhamento!M9:M329,"Pendente")>0,"Pendente",IF(COUNTIFS(Detalhamento!A9:A329,A95,Detalhamento!M9:M329,"OK")>0,"OK","-"))) -> - | M95: =IF(COUNTIF(Detalhamento!A9:A329,A95)=0,"-",IF(COUNTIFS(Detalhamento!A9:A329,A95,Detalhamento!N9:N329,"Pendente")>0,"Pendente",IF(COUNTIFS(Detalhamento!A9:A329,A95,Detalhamento!N9:N329,"OK")>0,"OK","-"))) -> - | O95: Original | P95: =IF(A95="",0,COUNTIF(Detalhamento!A9:A329,A95)) -> 0 | Q95: =IF(A95="",0,COUNTIFS(Detalhamento!A9:A329,A95,Detalhamento!H9:H329,"Concluído")) -> 0 | R95: =IFERROR(IF(P95=0,"",Q95/P95),"")
A96: 5.47 | B96: Execução de revestimento de shaft com estrutura interna em MDF de 25 mm, tratado contra umidade, com fixação mecânica ou colada, e acabamento externo em chapa de aço inox escovado (AISI 304), incluindo recortes, molduras, arremates, parafusos, dobradiças (quando houver porta de inspeção) e demais ferragens. Incluso todos os materiais, mão de obra especializada, transporte e limpeza da área. Execução conforme projeto e normas técnicas vigentes. | C96: Andar 8 | D96: 46355 | E96: 46378 | F96: =IF(OR($D96="",$E96=""),"Sem data",IF($E96<TODAY(),"Atrasado",IF($D96>TODAY(),"A iniciar","Em andamento"))) -> A iniciar | I96: =IF(COUNTIF(Detalhamento!A9:A329,A96)=0,"-",IF(COUNTIFS(Detalhamento!A9:A329,A96,Detalhamento!J9:J329,"Pendente")>0,"Pendente",IF(COUNTIFS(Detalhamento!A9:A329,A96,Detalhamento!J9:J329,"OK")>0,"OK","-"))) -> - | J96: =IF(COUNTIF(Detalhamento!A9:A329,A96)=0,"-",IF(COUNTIFS(Detalhamento!A9:A329,A96,Detalhamento!K9:K329,"Pendente")>0,"Pendente",IF(COUNTIFS(Detalhamento!A9:A329,A96,Detalhamento!K9:K329,"OK")>0,"OK","-"))) -> - | K96: =IF(COUNTIF(Detalhamento!A9:A329,A96)=0,"-",IF(COUNTIFS(Detalhamento!A9:A329,A96,Detalhamento!L9:L329,"Pendente")>0,"Pendente",IF(COUNTIFS(Detalhamento!A9:A329,A96,Detalhamento!L9:L329,"OK")>0,"OK","-"))) -> - | L96: =IF(COUNTIF(Detalhamento!A9:A329,A96)=0,"-",IF(COUNTIFS(Detalhamento!A9:A329,A96,Detalhamento!M9:M329,"Pendente")>0,"Pendente",IF(COUNTIFS(Detalhamento!A9:A329,A96,Detalhamento!M9:M329,"OK")>0,"OK","-"))) -> - | M96: =IF(COUNTIF(Detalhamento!A9:A329,A96)=0,"-",IF(COUNTIFS(Detalhamento!A9:A329,A96,Detalhamento!N9:N329,"Pendente")>0,"Pendente",IF(COUNTIFS(Detalhamento!A9:A329,A96,Detalhamento!N9:N329,"OK")>0,"OK","-"))) -> - | O96: Original | P96: =IF(A96="",0,COUNTIF(Detalhamento!A9:A329,A96)) -> 0 | Q96: =IF(A96="",0,COUNTIFS(Detalhamento!A9:A329,A96,Detalhamento!H9:H329,"Concluído")) -> 0 | R96: =IFERROR(IF(P96=0,"",Q96/P96),"")
A97: 5.48 | B97: Serviço de adequação e pintura de armário de combate a incêndio existente, incluindo lixamento, remoção de ferrugem, limpeza, tratamento anticorrosivo e aplicação de tinta esmalte sintético na cor padrão (vermelho segurança), com acabamento brilhante ou acetinado. Inclusa a substituição ou ajuste de dobradiças, fechos, vidros e adesivos de sinalização, conforme necessidade. Todos os materiais e mão de obra inclusos. Execução conforme normas do Corpo de Bombeiros e ABNT (NBR 12693). | C97: Andar 8 | D97: 46362 | E97: 46378 | F97: =IF(OR($D97="",$E97=""),"Sem data",IF($E97<TODAY(),"Atrasado",IF($D97>TODAY(),"A iniciar","Em andamento"))) -> A iniciar | I97: =IF(COUNTIF(Detalhamento!A9:A329,A97)=0,"-",IF(COUNTIFS(Detalhamento!A9:A329,A97,Detalhamento!J9:J329,"Pendente")>0,"Pendente",IF(COUNTIFS(Detalhamento!A9:A329,A97,Detalhamento!J9:J329,"OK")>0,"OK","-"))) -> - | J97: =IF(COUNTIF(Detalhamento!A9:A329,A97)=0,"-",IF(COUNTIFS(Detalhamento!A9:A329,A97,Detalhamento!K9:K329,"Pendente")>0,"Pendente",IF(COUNTIFS(Detalhamento!A9:A329,A97,Detalhamento!K9:K329,"OK")>0,"OK","-"))) -> - | K97: =IF(COUNTIF(Detalhamento!A9:A329,A97)=0,"-",IF(COUNTIFS(Detalhamento!A9:A329,A97,Detalhamento!L9:L329,"Pendente")>0,"Pendente",IF(COUNTIFS(Detalhamento!A9:A329,A97,Detalhamento!L9:L329,"OK")>0,"OK","-"))) -> - | L97: =IF(COUNTIF(Detalhamento!A9:A329,A97)=0,"-",IF(COUNTIFS(Detalhamento!A9:A329,A97,Detalhamento!M9:M329,"Pendente")>0,"Pendente",IF(COUNTIFS(Detalhamento!A9:A329,A97,Detalhamento!M9:M329,"OK")>0,"OK","-"))) -> - | M97: =IF(COUNTIF(Detalhamento!A9:A329,A97)=0,"-",IF(COUNTIFS(Detalhamento!A9:A329,A97,Detalhamento!N9:N329,"Pendente")>0,"Pendente",IF(COUNTIFS(Detalhamento!A9:A329,A97,Detalhamento!N9:N329,"OK")>0,"OK","-"))) -> - | O97: Original | P97: =IF(A97="",0,COUNTIF(Detalhamento!A9:A329,A97)) -> 0 | Q97: =IF(A97="",0,COUNTIFS(Detalhamento!A9:A329,A97,Detalhamento!H9:H329,"Concluído")) -> 0 | R97: =IFERROR(IF(P97=0,"",Q97/P97),"")
